Workbook

Sheet ENERO
A1: FECHA DE EMISION DEL COMPROBANTE DE PAGO O DOCUMENTO | B1: FECHA DE VENCIMIENTO O FECHA DE PAGO | C1: COMPROBANTE DE PAGO O DOCUMENTO | F1: N° COMPROBANTE PAGO | G1: INFORMACION PROVEEDOR | J1: ADQUISICIONES GRAVADAS DESTINADAS A OPERACIONES GRAVADAS Y/O EXPORTACION | L1: ADQUISICIONES GRAVADAS DESTINADAS A OPERACIONES GRAVADAS Y/O DE EXPORTACION Y A OPERACIONES NO GRAVADAS | N1: ADQUISICIONES GRAVADAS DESTINADAS A OPERACIONES NO GRAVADAS | P1: VALOR DE LAS ADQUISICIONES NO GRAVADAS | Q1: ISC | R1: OTROS TRIBUTOS Y CARGOS | S1: IMPORTE TOTAL | T1: N° COMPROBANTE DE PAGO EMITIDO POR SUJETO NO DOMICILIADO | U1: CONSTANCIA DE DEPOSITO DE DETRACCION | W1: TIPO DE CAMBIO | X1: REFERENCIA DEL COMPROBANTE DE PAGO O DOCUMENTO ORIGINAL QUE SE MODIFICA | AB1: MONEDA | AC1: EQUIVALENTE EN DOLARES AMERICANOS | AD1: FECHA VENCIMIENTO | AE1: CONDICION CONTADO/CREDITO | AF1: CUENTA CONTABLE BASE IMPONIBLE | AG1: CUENTA CONTABLE OTROS TRIBUTOS Y CARGOS | AH1: CUENTA CONTABLE TOTAL | AI1: CODIGO CENTRO DE COSTOS | AJ1: CODIGO CENTRO DE COSTOS 2 | AK1: REGIMEN ESPECIAL | AL1: PORCENTAJE REGIMEN ESPECIAL | AM1: IMPORTE REGIMEN ESPECIAL | AN1: SERIE DOCUMENTO REGIMEN ESPECIAL | AO1: NUMERO DOCUMENTO REGIMEN ESPECIAL | AP1: FECHA DOCUMENTO REGIMEN ESPECIAL | AQ1: CODIGO PRESUPUESTO | AR1: PORCENTAJE I.G.V. | AS1: GLOSA | AT1: CONDICIÓN DE PERCEPCIÓN | AU1: IMPORTE RÉGIMEN ESPECIAL | AV1: CLASIFICACIÓN DE BIENES Y SERVICIOS ADQUIRIDOS
G2: DOCUMENTO IDENTIDAD | I2: APELLIDOS Y NOMBRES, DENOMINACION O RAZON SOCIAL
D3: SERIE/CODIGO ADUANA | E3: AÑO EMISION DUA O DSI | G3: TIPO | H3: NUMERO | J3: BASE IMPONIBLE | K3: IGV | L3: BASE IMPONIBLE | M3: IGV | N3: BASE IMPONIBLE | O3: IGV | U3: NUMERO | V3: FECHA EMISION | X3: FECHA | Y3: TIPO | Z3: SERIE | AA3: N° COMPROBANTE PAGO O DOCUMENTO
A4: 46021 | C4: 14 | D4: 00S898 | F4: 85617271 | G4: 6 | H4: 20129646099 | I4: =IF(H4="","",VLOOKUP(H4,ENTIDAD!$B$2:$C$613,2,0)) -> ELECTROCENTRO S.A. | N4: =(S4-P4)/1.18 -> 0 | O4: =N4*0.18 -> 0 | P4: 604.4 | S4: 604.4 | AB4: S | AD4: 46037 | AE4: CRE | AF4: 6361095 | AH4: 4212 | AR4: 18 | AS4: POR EL SERVICIO DE ENERGIA ELECTRICA
A5: 46022 | C5: 14 | D5: 000060 | F5: 1046898 | G5: 6 | H5: 20121876290 | I5: =IF(H5="","",VLOOKUP(H5,ENTIDAD!$B$2:$C$613,2,0)) -> ENT.PREST.SERV.SANEAM.SELVA CENTRAL S.A | N5: =(S5-P5)/1.18 -> 0 | O5: =N5*0.18 -> 0 | P5: 45.8 | S5: 45.8 | AB5: S | AD5: 46053 | AE5: CRE | AF5: 6363095 | AH5: 4212 | AR5: 18 | AS5: POR EL SERVICIO DE AGUA POTABLE
A6: 46025 | C6: 01 | D6: 00F001 | F6: 116472 | G6: 6 | H6: 20568499043 | I6: =IF(H6="","",VLOOKUP(H6,ENTIDAD!$B$2:$C$613,2,0)) -> SURTIDORES SAN MIGUEL E.I.R.L. | N6: =(S6-P6)/1.18 -> 0 | O6: =N6*0.18 -> 0 | P6: 100.02 | S6: 100.02 | AB6: S | AD6: 46025 | AE6: CON | AF6: 656009401 | AH6: 4212 | AR6: 18 | AS6: POR LA COMPRA DE COMBUSTIBLE
A7: 46026 | C7: 01 | D7: 00E001 | F7: 133 | G7: 6 | H7: 10447422951 | I7: =IF(H7="","",VLOOKUP(H7,ENTIDAD!$B$2:$C$613,2,0)) -> ZEGARRA AZAÑERO JORGE KEY | N7: =(S7-P7)/1.18 -> 0 | O7: =N7*0.18 -> 0 | P7: 450 | S7: 450 | AB7: S | AD7: 46026 | AE7: CRE | AF7: 6599094 | AH7: 4212 | AR7: 18 | AS7: SOPORTE TECNICO
A8: 46027 | C8: 01 | D8: 00F001 | F8: 116533 | G8: 6 | H8: 20568499043 | I8: =IF(H8="","",VLOOKUP(H8,ENTIDAD!$B$2:$C$613,2,0)) -> SURTIDORES SAN MIGUEL E.I.R.L. | N8: =(S8-P8)/1.18 -> 0 | O8: =N8*0.18 -> 0 | P8: 100.02 | S8: 100.02 | AB8: S | AD8: 46027 | AE8: CON | AF8: 656009401 | AH8: 4212 | AR8: 18 | AS8: POR LA COMPRA DE COMBUSTIBLE
A9: 46027 | C9: 01 | D9: 00E001 | F9: 144 | G9: 6 | H9: 10447422951 | I9: =IF(H9="","",VLOOKUP(H9,ENTIDAD!$B$2:$C$613,2,0)) -> ZEGARRA AZAÑERO JORGE KEY | N9: =(S9-P9)/1.18 -> 0 | O9: =N9*0.18 -> 0 | P9: 1000 | S9: 1000 | AB9: S | AD9: 46027 | AE9: CRE | AF9: 6599094 | AH9: 4212 | AR9: 18 | AS9: ACTUALIZACION DEL MODULO DE CREDITOS
A10: 46027 | C10: 01 | D10: 00E001 | F10: 5947 | G10: 6 | H10: 20602783341 | I10: =IF(H10="","",VLOOKUP(H10,ENTIDAD!$B$2:$C$613,2,0)) -> CODISSER VRAEM E.I.R.L. | N10: =(S10-P10)/1.18 -> 0 | O10: =N10*0.18 -> 0 | P10: 16 | S10: 16 | AB10: S | AD10: 46027 | AE10: CON | AF10: 6250095 | AH10: 4212 | AR10: 18 | AS10: POR LA COMPRA DE AGUA MESA
A11: 46027 | C11: 01 | D11: 00FE01 | F11: 2675796 | G11: 6 | H11: 20100047218 | I11: =IF(H11="","",VLOOKUP(H11,ENTIDAD!$B$2:$C$613,2,0)) -> BANCO DE CREDITO DEL PERU | N11: =(S11-P11)/1.18 -> 0 | O11: =N11*0.18 -> 0 | P11: 117.88 | S11: =W11*AC11 -> 117.88 | W11: 3.368 | AB11: D | AC11: 35 | AD11: 46027 | AE11: CRE | AF11: 6391094 | AH11: 4212 | AR11: 18 | AS11: POR LA COMISION BANCARIA
A12: 46027 | C12: 01 | D12: 00FC04 | F12: 4694311 | G12: 6 | H12: 20100130204 | I12: =IF(H12="","",VLOOKUP(H12,ENTIDAD!$B$2:$C$613,2,0)) -> BANCO BBVA PERU | N12: =(S12-P12)/1.18 -> 0 | O12: =N12*0.18 -> 0 | P12: 40 | S12: 40 | AB12: S | AD12: 46027 | AE12: CRE | AF12: 6391094 | AH12: 4212 | AR12: 18 | AS12: POR LA COMISION BANCARIA
A13: 46027 | C13: 01 | D13: 00FB25 | F13: 25369180 | G13: 6 | H13: 20100130204 | I13: =IF(H13="","",VLOOKUP(H13,ENTIDAD!$B$2:$C$613,2,0)) -> BANCO BBVA PERU | N13: =(S13-P13)/1.18 -> 0 | O13: =N13*0.18 -> 0 | P13: 10 | S13: 10 | AB13: S | AD13: 46027 | AE13: CRE | AF13: 6391094 | AH13: 4212 | AR13: 18 | AS13: POR LA COMISION BANCARIA
A14: 46028 | C14: 01 | D14: 00FI01 | F14: 18054814 | G14: 6 | H14: 20100047218 | I14: =IF(H14="","",VLOOKUP(H14,ENTIDAD!$B$2:$C$613,2,0)) -> BANCO DE CREDITO DEL PERU | N14: =(S14-P14)/1.18 -> 0 | O14: =N14*0.18 -> 0 | P14: 914.5 | R14: 0 | S14: 914.5 | AB14: S | AD14: 46028 | AE14: CRE | AF14: 6391094 | AH14: 4212 | AR14: 18 | AS14: POR LA COMISION BANCARIA
A15: 46028 | C15: 01 | D15: 00E001 | F15: 1525 | G15: 6 | H15: 20611910887 | I15: =IF(H15="","",VLOOKUP(H15,ENTIDAD!$B$2:$C$613,2,0)) -> CORPORACION UNIVERSAL M&F SOCIEDAD ANONIMA CERRADA | N15: =(S15-P15)/1.18 -> 0 | O15: =N15*0.18 -> 0 | P15: 170 | R15: 0 | S15: 170 | AB15: S | AD15: 46028 | AE15: CRE | AF15: 656009506 | AH15: 4212 | AR15: 18 | AS15: POR LA IMPRESIÓN DE DE FORMATOS
A16: 46028 | C16: 01 | D16: 00E001 | F16: 60 | G16: 6 | H16: 10733619207 | I16: =IF(H16="","",VLOOKUP(H16,ENTIDAD!$B$2:$C$613,2,0)) -> UNTIVEROS SOLDEVILLA MIGUEL COLIN | N16: =(S16-P16)/1.18 -> 0 | O16: =N16*0.18 -> 0 | P16: 5500 | R16: 0 | S16: 5500 | AB16: S | AD16: 46028 | AE16: CRE | AH16: 4212 | AR16: 18 | AS16: LETREROS CON LUCES LED
A17: 46028 | C17: 01 | D17: 00E001 | F17: 81 | G17: 6 | H17: 20568685424 | I17: =IF(H17="","",VLOOKUP(H17,ENTIDAD!$B$2:$C$613,2,0)) -> VISUAL´S MERCHANDISING S.A.C. | N17: =(S17-P17)/1.18 -> 0 | O17: =N17*0.18 -> 0 | P17: 1000 | S17: 1000 | AB17: S | AD17: 46028 | AE17: CRE | AF17: 6371095 | AH17: 4212 | AR17: 18 | AS17: POR EL SERVICIO DE PUBLICIDAD
A18: 46029 | C18: 01 | D18: 00E001 | F18: 182 | G18: 6 | H18: 10207070098 | I18: =IF(H18="","",VLOOKUP(H18,ENTIDAD!$B$2:$C$613,2,0)) -> ROJAS FLORES ELISEO MAXIMO | N18: =(S18-P18)/1.18 -> 0 | O18: =N18*0.18 -> 0 | P18: 2000 | R18: 0 | S18: 2000 | AB18: S | AD18: 46029 | AE18: CRE | AF18: 6011020 | AH18: 4212 | AR18: 18 | AS18: POR LA COMPRA DE PARABRIZAS
A19: 46029 | C19: 01 | D19: 00FV13 | F19: 1272573 | G19: 6 | H19: 20100047218 | I19: =IF(H19="","",VLOOKUP(H19,ENTIDAD!$B$2:$C$613,2,0)) -> BANCO DE CREDITO DEL PERU | N19: =(S19-P19)/1.18 -> 0 | O19: =N19*0.18 -> 0 | P19: 154.5 | S19: 154.5 | AB19: S | AD19: 46029 | AE19: CRE | AF19: 6391094 | AH19: 4212 | AR19: 18 | AS19: POR LA COMISION BANCARIA
A20: 46030 | C20: 01 | D20: 00E001 | F20: 115 | G20: 6 | H20: 20604194211 | I20: =IF(H20="","",VLOOKUP(H20,ENTIDAD!$B$2:$C$613,2,0)) -> MULTISERVICIOS COMPANY SELVA SOCIEDAD ANÓNIMA CERRADA | N20: =(S20-P20)/1.18 -> 0 | O20: =N20*0.18 -> 0 | P20: 1028.5 | R20: 0 | S20: 1028.5 | AB20: S | AD20: 46030 | AE20: CRE | AF20: 6314095 | AH20: 4212 | AR20: 18 | AS20: POR CONSUMO DE ALIMENTOS
A21: 46031 | C21: 01 | D21: 00F005 | F21: 16248 | G21: 6 | H21: 20493508645 | I21: =IF(H21="","",VLOOKUP(H21,ENTIDAD!$B$2:$C$613,2,0)) -> HONDA SELVA DEL PERU S.A. | N21: =(S21-P21)/1.18 -> -0.00088135593 | O21: =N21*0.18 -> -0.00015864407 | P21: 34926.06 | S21: =W21*AC21 -> 34926.059 | W21: 3.368 | AB21: D | AC21: 10369.97 | AD21: 46062 | AE21: CRE | AF21: 6011021 | AH21: 4212 | AR21: 18 | AS21: EXISTENCIAS POR RECIBIR
A22: 46031 | C22: 07 | D22: 00FN11 | F22: 75 | G22: 6 | H22: 20600014529 | I22: =IF(H22="","",VLOOKUP(H22,ENTIDAD!$B$2:$C$613,2,0)) -> OSPINA FERRETERA S.R.L. | N22: =(S22-P22)/1.18 -> -279.66102 | O22: =N22*0.18 -> -50.338983 | S22: -330 | X22: 46008 | Y22: 01 | Z22: F011 | AA22: 4319 | AB22: S | AD22: 46031 | AE22: CRE | AF22: 6560095 | AH22: 4212 | AR22: 18 | AS22: ANULACION DE LA OPERACIÓN
A23: 46031 | C23: 07 | D23: 00E001 | F23: 3 | G23: 6 | H23: 10207070098 | I23: =IF(H23="","",VLOOKUP(H23,ENTIDAD!$B$2:$C$613,2,0)) -> ROJAS FLORES ELISEO MAXIMO | N23: =(S23-P23)/1.18 -> 0 | O23: =N23*0.18 -> 0 | P23: -2000 | S23: -2000 | X23: 46029 | Y23: 01 | Z23: E001 | AA23: 182 | AB23: S | AD23: 46031 | AE23: CRE | AF23: 6011020 | AH23: 4212 | AR23: 18 | AS23: ANULACION DE LA OPERACIÓN
A24: 46031 | C24: 01 | D24: 00F011 | F24: 4664 | G24: 6 | H24: 20600014529 | I24: =IF(H24="","",VLOOKUP(H24,ENTIDAD!$B$2:$C$613,2,0)) -> OSPINA FERRETERA S.R.L. | N24: =(S24-P24)/1.18 -> 279.66102 | O24: =N24*0.18 -> 50.338983 | P24: 0 | S24: 330 | AB24: S | AD24: 46031 | AE24: CRE | AF24: 6560095 | AH24: 4212 | AR24: 18 | AS24: CANDADO DE BRONCE
A25: 46034 | C25: 01 | D25: 00E001 | F25: 1319 | G25: 6 | H25: 20573301715 | I25: =IF(H25="","",VLOOKUP(H25,ENTIDAD!$B$2:$C$613,2,0)) -> CASCOS FORRADOS PERICO S.A.C | N25: =(S25-P25)/1.18 -> 0 | O25: =N25*0.18 -> 0 | P25: 3600 | R25: 0 | S25: 3600 | AB25: S | AD25: 46034 | AE25: CRE | AF25: 6031025 | AH25: 4212 | AR25: 18 | AS25: POR LA COMPRA DE CASCOS
A26: 46034 | C26: 01 | D26: 00F341 | F26: 10045 | G26: 6 | H26: 20512528458 | I26: =IF(H26="","",VLOOKUP(H26,ENTIDAD!$B$2:$C$613,2,0)) -> SHALOM EMPRESARIAL S.A.C. | N26: =(S26-P26)/1.18 -> 86.440678 | O26: =N26*0.18 -> 15.559322 | R26: 0 | S26: 102 | AB26: S | AD26: 46034 | AE26: CRE | AF26: 6311195 | AH26: 4212 | AR26: 18 | AS26: POR EL SERVICIO DE TRANSPORTE
A27: 46034 | C27: 01 | D27: 00F001 | F27: 12551 | G27: 6 | H27: 10209907327 | I27: =IF(H27="","",VLOOKUP(H27,ENTIDAD!$B$2:$C$613,2,0)) -> TORPOCO,MAYTA,HECTOR,ALFONSO | N27: =(S27-P27)/1.18 -> 0 | O27: =N27*0.18 -> 0 | P27: 10 | R27: 0 | S27: 10 | AB27: S | AD27: 46034 | AE27: CON | AF27: 656009501 | AH27: 4212 | AR27: 18 | AS27: POR LA COMPRA DE COMBUSTIBLE
A28: 46035 | C28: 01 | D28: 00E001 | F28: 1106 | G28: 6 | H28: 20607824666 | I28: =IF(H28="","",VLOOKUP(H28,ENTIDAD!$B$2:$C$613,2,0)) -> J&H CASA LINDA E.I.R.L. | N28: =(S28-P28)/1.18 -> 0 | O28: =N28*0.18 -> 0 | P28: 615 | R28: 0 | S28: 615 | AB28: S | AD28: 46035 | AE28: CRE | AF28: 6344095 | AH28: 4212 | AR28: 18 | AS28: POR LA COMPRA DE CERAMICA
A29: 46035 | C29: 01 | D29: 00F005 | F29: 530 | G29: 6 | H29: 20602109225 | I29: =IF(H29="","",VLOOKUP(H29,ENTIDAD!$B$2:$C$613,2,0)) -> SISTEMA ECOLÓGICO INTEGRAL DE TECNOLOGÍAS E INFORMÁTICA SOCIEDAD ANONIMA CERRADA - ECO SITI S.A.C. | N29: =(S29-P29)/1.18 -> 0 | O29: =N29*0.18 -> 0 | P29: 119.7 | R29: 0 | S29: 119.7 | AB29: S | AD29: 46035 | AE29: CON | AF29: 6364095 | AH29: 4212 | AR29: 18 | AS29: POR EL SERVICIO DE LLAMADAS
A30: 46036 | C30: 01 | D30: 00F001 | F30: 5117 | G30: 6 | H30: 10061702071 | I30: =IF(H30="","",VLOOKUP(H30,ENTIDAD!$B$2:$C$613,2,0)) -> CORAL FLORES IVAN MARTIN | N30: =(S30-P30)/1.18 -> 0 | O30: =N30*0.18 -> 0 | P30: 645 | R30: 0 | S30: 645 | AB30: S | AD30: 46036 | AE30: CRE | AF30: 6329095 | AG30: 1413 | AH30: 4212 | AR30: 18 | AS30: POR EL SERVICIO DE LEGALIZACION
A31: 46037 | C31: 01 | D31: 00FF08 | F31: 708 | G31: 6 | H31: 20611526572 | I31: =IF(H31="","",VLOOKUP(H31,ENTIDAD!$B$2:$C$613,2,0)) -> GRUPO SUKKIE E.I.R.L. | N31: =(S31-P31)/1.18 -> 0 | O31: =N31*0.18 -> 0 | P31: 61.2 | R31: 0 | S31: 61.2 | AB31: S | AD31: 46037 | AE31: CON | AF31: 656009502 | AH31: 4212 | AR31: 18 | AS31: POR LA COMPRA DE ARTICULOS DE LIMPIEZA
A32: 46037 | C32: 01 | D32: 00F005 | F32: 16314 | G32: 6 | H32: 20493508645 | I32: =IF(H32="","",VLOOKUP(H32,ENTIDAD!$B$2:$C$613,2,0)) -> HONDA SELVA DEL PERU S.A. | N32: =(S32-P32)/1.18 -> 0.00040677966 | O32: =N32*0.18 -> 7.3220338e-05 | P32: 61102.43 | S32: =W32*AC32 -> 61102.43 | W32: 3.367 | AB32: D | AC32: 18147.44 | AD32: 46068 | AE32: CRE | AF32: 6011021 | AH32: 4212 | AR32: 18 | AS32: EXISTENCIAS POR RECIBIR
A33: 46037 | C33: 01 | D33: 00FC01 | F33: 573296 | G33: 6 | H33: 20100047218 | I33: =IF(H33="","",VLOOKUP(H33,ENTIDAD!$B$2:$C$613,2,0)) -> BANCO DE CREDITO DEL PERU | N33: =(S33-P33)/1.18 -> 0 | O33: =N33*0.18 -> 0 | P33: 5503.5 | S33: 5503.5 | AB33: S | AD33: 46037 | AE33: CRE | AH33: 4212 | AR33: 18
A34: 46038 | C34: 01 | D34: 00F001 | F34: 15611 | G34: 6 | H34: 20444766906 | I34: =IF(H34="","",VLOOKUP(H34,ENTIDAD!$B$2:$C$613,2,0)) -> EMPRESA DE TRANSPORTES PROFAMSE SRL | N34: =(S34-P34)/1.18 -> 0 | O34: =N34*0.18 -> 0 | P34: 40 | R34: 0 | S34: 40 | AB34: S | AD34: 46038 | AE34: CRE | AF34: 6311295 | AG34: 1413 | AH34: 4212 | AR34: 18 | AS34: POR EL SERVICIO DE TRANSPORTE DE PASAJERO
A35: 46038 | C35: 01 | D35: 00E001 | F35: 1160 | G35: 6 | H35: 20485903811 | I35: =IF(H35="","",VLOOKUP(H35,ENTIDAD!$B$2:$C$613,2,0)) -> EMPRESA DE TRANSPORTES ECO TURISTICO SA | N35: =(S35-P35)/1.18 -> 0 | O35: =N35*0.18 -> 0 | P35: 40 | R35: 0 | S35: 40 | AB35: S | AD35: 46038 | AE35: CRE | AF35: 6311295 | AG35: 1413 | AH35: 4212 | AR35: 18 | AS35: POR EL SERVICIO DE TRANSPORTE DE PASAJERO
A36: 46038 | C36: 01 | D36: 00E001 | F36: 5965 | G36: 6 | H36: 20602783341 | I36: =IF(H36="","",VLOOKUP(H36,ENTIDAD!$B$2:$C$613,2,0)) -> CODISSER VRAEM E.I.R.L. | N36: =(S36-P36)/1.18 -> 0 | O36: =N36*0.18 -> 0 | P36: 16 | R36: 0 | S36: 16 | AB36: S | AD36: 46038 | AE36: CON | AF36: 6250095 | AH36: 4212 | AR36: 18 | AS36: POR LA COMPRA DE AGUA MESA
A37: 46038 | C37: 01 | D37: 00E001 | F37: 2281 | G37: 6 | H37: 20541326384 | I37: =IF(H37="","",VLOOKUP(H37,ENTIDAD!$B$2:$C$613,2,0)) -> AEROM INVERSIONES NEGOCIOS SERVICIOS E.I.R.L. | N37: =(S37-P37)/1.18 -> 0 | O37: =N37*0.18 -> 0 | P37: 46 | R37: 0 | S37: 46 | AB37: S | AD37: 46038 | AE37: CRE | AF37: 6344095 | AH37: 4212 | AR37: 18 | AS37: POR LA COMPRA DE PEGAMENTO EXTRAFUERTE
A38: 46038 | C38: 01 | D38: 00FN01 | F38: 41464917 | G38: 6 | H38: 20100047218 | I38: =IF(H38="","",VLOOKUP(H38,ENTIDAD!$B$2:$C$613,2,0)) -> BANCO DE CREDITO DEL PERU | N38: =(S38-P38)/1.18 -> 0 | O38: =N38*0.18 -> 0 | P38: 10 | S38: 10 | AB38: S | AD38: 46038 | AE38: CRE | AF38: 6391094 | AH38: 4212 | AR38: 18 | AS38: POR LA COMISION BANCARIA
A39: 46038 | C39: 01 | D39: 00FN01 | F39: 41464993 | G39: 6 | H39: 20100047218 | I39: =IF(H39="","",VLOOKUP(H39,ENTIDAD!$B$2:$C$613,2,0)) -> BANCO DE CREDITO DEL PERU | N39: =(S39-P39)/1.18 -> 0 | O39: =N39*0.18 -> 0 | P39: 10 | S39: 10 | AB39: S | AD39: 46038 | AE39: CRE | AF39: 6391094 | AH39: 4212 | AR39: 18 | AS39: POR LA COMISION BANCARIA
A40: 46039 | C40: 01 | D40: 00F001 | F40: 590 | G40: 6 | H40: 10733910921 | I40: =IF(H40="","",VLOOKUP(H40,ENTIDAD!$B$2:$C$613,2,0)) -> MADUEÑO HUAMAN LILI CLISSELY | N40: =(S40-P40)/1.18 -> 0 | O40: =N40*0.18 -> 0 | P40: 7 | R40: 0 | S40: 7 | AB40: S | AD40: 46039 | AE40: CON | AF40: 6560095 | AH40: 4212 | AR40: 18 | AS40: PINTURA SPRAY
A41: 46039 | C41: 01 | D41: 00F010 | F41: 4433 | G41: 6 | H41: 20601012261 | I41: =IF(H41="","",VLOOKUP(H41,ENTIDAD!$B$2:$C$613,2,0)) -> IMPORTADORA DE REPUESTOS LA ROCA E.I.R.L. | N41: =(S41-P41)/1.18 -> 0 | O41: =N41*0.18 -> 0 | P41: 5 | S41: 5 | AB41: S | AD41: 46039 | AE41: CRE | AF41: 6560095 | AH41: 4212 | AR41: 18 | AS41: JEBE DE TAPABARRA DE CHASIS
A42: 46041 | C42: 01 | D42: 00E001 | F42: 63 | G42: 6 | H42: 10733619207 | I42: =IF(H42="","",VLOOKUP(H42,ENTIDAD!$B$2:$C$613,2,0)) -> UNTIVEROS SOLDEVILLA MIGUEL COLIN | N42: =(S42-P42)/1.18 -> 0 | O42: =N42*0.18 -> 0 | P42: 1250 | R42: 0 | S42: 1250 | AB42: S | AD42: 46041 | AE42: CRE | AH42: 4212 | AR42: 18 | AS42: LETRERO LUMINISO
A43: 46041 | C43: 01 | D43: 00F002 | F43: 143 | G43: 6 | H43: 10209907327 | I43: =IF(H43="","",VLOOKUP(H43,ENTIDAD!$B$2:$C$613,2,0)) -> TORPOCO,MAYTA,HECTOR,ALFONSO | N43: =(S43-P43)/1.18 -> 0 | O43: =N43*0.18 -> 0 | P43: 10 | R43: 0 | S43: 10 | AB43: S | AD43: 46041 | AE43: CON | AF43: 656009501 | AH43: 4212 | AR43: 18 | AS43: POR LA COMPRA DE COMBUSTIBLE
A44: 46041 | C44: 01 | D44: 00F001 | F44: 5387 | G44: 6 | H44: 10421947665 | I44: =IF(H44="","",VLOOKUP(H44,ENTIDAD!$B$2:$C$613,2,0)) -> MAYTA,MADUEÑO,SAUL,JESUS | N44: =(S44-P44)/1.18 -> 0 | O44: =N44*0.18 -> 0 | P44: 94.5 | R44: 0 | S44: 94.5 | AB44: S | AD44: 46041 | AE44: CON | AF44: 656009502 | AH44: 4212 | AR44: 18 | AS44: POR LA COMPRA DE ARTICULOS DE LIMPIEZA
A45: 46042 | C45: 01 | D45: 00F001 | F45: 5133 | G45: 6 | H45: 10061702071 | I45: =IF(H45="","",VLOOKUP(H45,ENTIDAD!$B$2:$C$613,2,0)) -> CORAL FLORES IVAN MARTIN | N45: =(S45-P45)/1.18 -> 0 | O45: =N45*0.18 -> 0 | P45: 300 | R45: 0 | S45: 300 | AB45: S | AD45: 46042 | AE45: CRE | AF45: 6329095 | AG45: 1413 | AH45: 4212 | AR45: 18 | AS45: POR EL SERVICIO DE LEGALIZACION
A46: 46042 | C46: 01 | D46: 00F001 | F46: 116927 | G46: 6 | H46: 20568499043 | I46: =IF(H46="","",VLOOKUP(H46,ENTIDAD!$B$2:$C$613,2,0)) -> SURTIDORES SAN MIGUEL E.I.R.L. | N46: =(S46-P46)/1.18 -> 0 | O46: =N46*0.18 -> 0 | P46: 99.98 | S46: 99.98 | AB46: S | AD46: 46042 | AE46: CON | AF46: 656009401 | AH46: 4212 | AR46: 18 | AS46: POR LA COMPRA DE COMBUSTIBLE
A47: 46043 | C47: 01 | D47: 00E001 | F47: 641 | G47: 6 | H47: 10433685721 | I47: =IF(H47="","",VLOOKUP(H47,ENTIDAD!$B$2:$C$613,2,0)) -> MANDUJANO,SOLANO,JOSE,ELIAS | N47: =(S47-P47)/1.18 -> 0 | O47: =N47*0.18 -> 0 | P47: 11.8 | S47: 11.8 | AB47: S | AD47: 46043 | AE47: CON | AF47: 656009503 | AH47: 4212 | AR47: 18 | AS47: ALMOHADILLA DE HUELLA DACTILAR
A48: 46043 | C48: 01 | D48: 00F001 | F48: 5938 | G48: 6 | H48: 20486549328 | I48: =IF(H48="","",VLOOKUP(H48,ENTIDAD!$B$2:$C$613,2,0)) -> SANTISIMA TRINIDAD E.I.R.L. | N48: =(S48-P48)/1.18 -> 0 | O48: =N48*0.18 -> 0 | P48: 144 | S48: 144 | AB48: S | AD48: 46043 | AE48: CON | AF48: 656009503 | AH48: 4212 | AR48: 18 | AS48: POR LA COMPRA DE ARTICULOS DE ESCRITORIO
A49: 46044 | C49: 01 | D49: 00F002 | F49: 149 | G49: 6 | H49: 10209907327 | I49: =IF(H49="","",VLOOKUP(H49,ENTIDAD!$B$2:$C$613,2,0)) -> TORPOCO,MAYTA,HECTOR,ALFONSO | N49: =(S49-P49)/1.18 -> 0 | O49: =N49*0.18 -> 0 | P49: 5 | S49: 5 | AB49: S | AD49: 46044 | AE49: CON | AF49: 656009501 | AH49: 4212 | AR49: 18 | AS49: POR LA COMPRA DE COMBUSTIBLE
A50: 46044 | C50: 01 | D50: 00F011 | F50: 827 | G50: 6 | H50: 20601012261 | I50: =IF(H50="","",VLOOKUP(H50,ENTIDAD!$B$2:$C$613,2,0)) -> IMPORTADORA DE REPUESTOS LA ROCA E.I.R.L. | N50: =(S50-P50)/1.18 -> 0 | O50: =N50*0.18 -> 0 | P50: 30 | S50: 30 | AB50: S | AD50: 46044 | AE50: CRE | AF50: 6560095 | AH50: 4212 | AR50: 18 | AS50: LIMPIADOR DE MOTOR
A51: 46046 | C51: 01 | D51: 00F005 | F51: 16458 | G51: 6 | H51: 20493508645 | I51: =IF(H51="","",VLOOKUP(H51,ENTIDAD!$B$2:$C$613,2,0)) -> HONDA SELVA DEL PERU S.A. | N51: =(S51-P51)/1.18 -> -0.0011779661 | O51: =N51*0.18 -> -0.0002120339 | P51: 65284.82 | S51: =W51*AC51 -> 65284.819 | W51: 3.359 | AB51: D | AC51: 19435.79 | AD51: 46077 | AE51: CRE | AF51: 6011021 | AH51: 4212 | AR51: 18 | AS51: EXISTENCIAS POR RECIBIR
A52: 46046 | C52: 01 | D52: 00F005 | F52: 16461 | G52: 6 | H52: 20493508645 | I52: =IF(H52="","",VLOOKUP(H52,ENTIDAD!$B$2:$C$613,2,0)) -> HONDA SELVA DEL PERU S.A. | N52: =(S52-P52)/1.18 -> -0.0015508475 | O52: =N52*0.18 -> -0.00027915254 | P52: 52227.85 | S52: =W52*AC52 -> 52227.848 | W52: 3.359 | AB52: D | AC52: 15548.63 | AD52: 46077 | AE52: CRE | AF52: 6011021 | AH52: 4212 | AR52: 18 | AS52: EXISTENCIAS POR RECIBIR
A53: 46046 | C53: 01 | D53: 00F005 | F53: 16456 | G53: 6 | H53: 20493508645 | I53: =IF(H53="","",VLOOKUP(H53,ENTIDAD!$B$2:$C$613,2,0)) -> HONDA SELVA DEL PERU S.A. | N53: =(S53-P53)/1.18 -> -0.0011779661 | O53: =N53*0.18 -> -0.0002120339 | P53: 65284.82 | S53: =W53*AC53 -> 65284.819 | W53: 3.359 | AB53: D | AC53: 19435.79 | AD53: 46077 | AE53: CRE | AF53: 6011021 | AH53: 4212 | AR53: 18 | AS53: EXISTENCIAS POR RECIBIR
A54: 46048 | C54: 07 | D54: 00F017 | F54: 13092 | G54: 6 | H54: 20103733015 | I54: =IF(H54="","",VLOOKUP(H54,ENTIDAD!$B$2:$C$613,2,0)) -> HONDA DEL PERU S.A | N54: =(S54-P54)/1.18 -> -108.8168 | O54: =N54*0.18 -> -19.587024 | P54: 0 | S54: =-W54*AC54 -> -128.40383 | W54: 3.3835 | X54: 45989 | Y54: 01 | Z54: F005 | AA54: 76063 | AB54: D | AC54: 37.95 | AD54: 46048 | AE54: CRE | AF54: 7311 | AH54: 4212 | AR54: 18 | AS54: CUMPLIMIENTO DE CUOTA DE VENTAS
A55: 46049 | C55: 07 | D55: 00F005 | F55: 2216 | G55: 6 | H55: 20493508645 | I55: =IF(H55="","",VLOOKUP(H55,ENTIDAD!$B$2:$C$613,2,0)) -> HONDA SELVA DEL PERU S.A. | N55: =(S55-P55)/1.18 -> -101.97461 | O55: =N55*0.18 -> -18.35543 | P55: -6129.8 | S55: =-W55*AC55 -> -6250.13 | W55: 3.4218788 | X55: 46001 | Y55: 01 | Z55: F005 | AA55: 15898 | AB55: D | AC55: 1826.52 | AD55: 46049 | AE55: CRE | AF55: 7311 | AH55: 4212 | AR55: 18 | AS55: CUMPLIMIENTO DE CUOTA DE VENTAS
A56: 46049 | C56: 01 | D56: 00F005 | F56: 16482 | G56: 6 | H56: 20493508645 | I56: =IF(H56="","",VLOOKUP(H56,ENTIDAD!$B$2:$C$613,2,0)) -> HONDA SELVA DEL PERU S.A. | N56: =(S56-P56)/1.18 -> 0.0017288136 | O56: =N56*0.18 -> 0.00031118644 | P56: 19842.65 | S56: =W56*AC56 -> 19842.652 | W56: 3.356 | AB56: D | AC56: 5912.59 | AD56: 46080 | AE56: CRE | AF56: 6011021 | AH56: 4212 | AR56: 18 | AS56: EXISTENCIAS POR RECIBIR
A57: 46049 | C57: 07 | D57: 00F005 | F57: 2233 | G57: 6 | H57: 20493508645 | I57: =IF(H57="","",VLOOKUP(H57,ENTIDAD!$B$2:$C$613,2,0)) -> HONDA SELVA DEL PERU S.A. | N57: =(S57-P57)/1.18 -> 0.0021186441 | O57: =N57*0.18 -> 0.00038135593 | P57: -153.13 | S57: =-W57*AC57 -> -153.1275 | W57: 3.603 | X57: 45831 | Y57: 01 | Z57: F005 | AA57: 13340 | AB57: D | AC57: 42.5 | AD57: 46080 | AE57: CRE | AF57: 7311 | AH57: 4212 | AR57: 18 | AS57: BONO RECONOCIMIENTO
A58: 46050 | C58: 01 | D58: 00E001 | F58: 1455 | G58: 6 | H58: 20609448360 | I58: =IF(H58="","",VLOOKUP(H58,ENTIDAD!$B$2:$C$613,2,0)) -> L & E SAN FRANCISCO SOCIEDAD DE RESPONSABILIDAD LIMITADA | N58: =(S58-P58)/1.18 -> 0 | O58: =N58*0.18 -> 0 | P58: 45 | S58: 45 | AB58: S | AD58: 46050 | AE58: CON | AF58: 631509401 | AH58: 4212 | AR58: 18 | AS58: LAVADO Y ENGRASE
A59: 46050 | C59: 01 | D59: 00E001 | F59: 1484 | G59: 6 | H59: 10444483101 | I59: =IF(H59="","",VLOOKUP(H59,ENTIDAD!$B$2:$C$613,2,0)) -> MUCHA,HERRERA,DENISSE,PILAR | N59: =(S59-P59)/1.18 -> 0 | O59: =N59*0.18 -> 0 | P59: 25 | S59: 25 | AB59: S | AD59: 46050 | AE59: CRE | AF59: 6560095 | AH59: 4212 | AR59: 18 | AS59: TOMACORRIENTE
A60: 46050 | C60: 01 | D60: 00F001 | F60: 12577 | G60: 6 | H60: 10209907327 | I60: =IF(H60="","",VLOOKUP(H60,ENTIDAD!$B$2:$C$613,2,0)) -> TORPOCO,MAYTA,HECTOR,ALFONSO | N60: 0 | O60: =N60*0.18 -> 0 | P60: 5 | S60: 5 | AB60: S | AD60: 46050 | AE60: CON | AF60: 656009501 | AH60: 4212 | AR60: 18 | AS60: POR LA COMPRA DE COMBUSTIBLE
A61: 46050 | C61: 01 | D61: 00F005 | F61: 16539 | G61: 6 | H61: 20493508645 | I61: =IF(H61="","",VLOOKUP(H61,ENTIDAD!$B$2:$C$613,2,0)) -> HONDA SELVA DEL PERU S.A. | N61: =(S61-P61)/1.18 -> 0.0018983051 | O61: =N61*0.18 -> 0.00034169491 | P61: 56368.47 | S61: =W61*AC61 -> 56368.472 | W61: 3.352 | AB61: D | AC61: 16816.37 | AD61: 46081 | AE61: CRE | AF61: 6011021 | AH61: 4212 | AR61: 18 | AS61: EXISTENCIAS POR RECIBIR
A62: 46050 | C62: 01 | D62: 00F005 | F62: 16538 | G62: 6 | H62: 20493508645 | I62: =IF(H62="","",VLOOKUP(H62,ENTIDAD!$B$2:$C$613,2,0)) -> HONDA SELVA DEL PERU S.A. | N62: =(S62-P62)/1.18 -> 0.0031864407 | O62: =N62*0.18 -> 0.00057355932 | P62: 37677.75 | S62: =W62*AC62 -> 37677.754 | W62: 3.352 | AB62: D | AC62: 11240.38 | AD62: 46081 | AE62: CRE | AF62: 6011021 | AH62: 4212 | AR62: 18 | AS62: EXISTENCIAS POR RECIBIR
A63: 46050 | C63: 01 | D63: 00F017 | F63: 77810 | G63: 6 | H63: 20103733015 | I63: =IF(H63="","",VLOOKUP(H63,ENTIDAD!$B$2:$C$613,2,0)) -> HONDA DEL PERU S.A | N63: =(S63-P63)/1.18 -> 12483.388 | O63: =N63*0.18 -> 2247.0098 | P63: 0 | S63: =W63*AC63 -> 14730.398 | W63: 3.352 | AB63: D | AC63: 4394.51 | AD63: 46081 | AE63: CRE | AF63: 6011021 | AH63: 4212 | AR63: 18 | AS63: EXISTENCIAS POR RECIBIR
A64: 46050 | C64: 01 | D64: 00F005 | F64: 16540 | G64: 6 | H64: 20493508645 | I64: =IF(H64="","",VLOOKUP(H64,ENTIDAD!$B$2:$C$613,2,0)) -> HONDA SELVA DEL PERU S.A. | N64: 0 | O64: =N64*0.18 -> 0 | P64: 19819.04 | S64: =W64*AC64 -> 19819.035 | W64: 3.352 | AB64: D | AC64: 5912.6 | AD64: 46081 | AE64: CRE | AF64: 6011021 | AH64: 4212 | AR64: 18 | AS64: EXISTENCIAS POR RECIBIR
A65: 46050 | C65: 01 | D65: 00F001 | F65: 604 | G65: 6 | H65: 10733910921 | I65: =IF(H65="","",VLOOKUP(H65,ENTIDAD!$B$2:$C$613,2,0)) -> MADUEÑO HUAMAN LILI CLISSELY | N65: 0 | O65: =N65*0.18 -> 0 | P65: 42 | S65: 42 | AB65: S | AD65: 46050 | AE65: CRE | AF65: 6560095 | AH65: 4212 | AR65: 18 | AS65: POR LA COMPRA DE HERRAMIENTAS
A66: 46050 | C66: 01 | D66: 00E001 | F66: 595 | G66: 6 | H66: 20601358892 | I66: =IF(H66="","",VLOOKUP(H66,ENTIDAD!$B$2:$C$613,2,0)) -> ARAUCO CONDE SOLUCIONES INMOBILIARIAS S.A.C. | N66: =(S66-P66)/1.18 -> 0 | O66: =N66*0.18 -> 0 | P66: 1000 | S66: 1000 | AB66: S | AD66: 46050 | AE66: CRE | AF66: 6352095 | AH66: 4212 | AR66: 18 | AS66: POR EL SERVICIO DE ARRENDAMIENTO
A67: 46050 | C67: 01 | D67: 00F072 | F67: 6243862 | G67: 6 | H67: 20332970411 | I67: =IF(H67="","",VLOOKUP(H67,ENTIDAD!$B$2:$C$613,2,0)) -> PACIFICO COMPAÑIA DE SEGUROS Y REASEGUROS | N67: =(S67-P67)/1.18 -> 729.68495 | O67: =N67*0.18 -> 131.34329 | P67: 0 | S67: =W67*AC67 -> 861.02824 | W67: 3.352 | AB67: D | AC67: 256.87 | AD67: 46050 | AE67: CRE | AH67: 4212 | AR67: 18
A68: 46051 | C68: 01 | D68: 00E001 | F68: 503 | G68: 6 | H68: 10712058159 | I68: =IF(H68="","",VLOOKUP(H68,ENTIDAD!$B$2:$C$613,2,0)) -> HUAYTA BRAVO LEONOR LEONILDA | N68: =(S68-P68)/1.18 -> 0 | O68: =N68*0.18 -> 0 | P68: 614 | S68: 614 | AB68: S | AD68: 46051 | AE68: CRE | AF68: 6560094 | AH68: 4212 | AR68: 18 | AS68: POR LA COMPRA DE REPUESTOS
A69: 46051 | C69: 01 | D69: 00F001 | F69: 606 | G69: 6 | H69: 10733910921 | I69: =IF(H69="","",VLOOKUP(H69,ENTIDAD!$B$2:$C$613,2,0)) -> MADUEÑO HUAMAN LILI CLISSELY | N69: 0 | O69: =N69*0.18 -> 0 | P69: 10 | S69: 10 | AB69: S | AD69: 46051 | AE69: CON | AF69: 6560095 | AH69: 4212 | AR69: 18 | AS69: POR LA COMPRA DE PINTURA SPRAY
A70: 46051 | C70: 01 | D70: 00F003 | F70: 57767 | G70: 6 | H70: 20493508645 | I70: =IF(H70="","",VLOOKUP(H70,ENTIDAD!$B$2:$C$613,2,0)) -> HONDA SELVA DEL PERU S.A. | N70: =(S70-P70)/1.18 -> -0.0024576271 | O70: =N70*0.18 -> -0.00044237288 | P70: 39555.23 | S70: =W70*AC70 -> 39555.227 | W70: 3.345 | AB70: D | AC70: 11825.18 | AD70: 29/02/2026 | AE70: CRE | AF70: 6011021 | AH70: 4212 | AR70: 18 | AS70: EXISTENCIAS POR RECIBIR
A71: 46052 | C71: 01 | D71: 00F028 | F71: 14725 | G71: 6 | H71: 20493508645 | I71: =IF(H71="","",VLOOKUP(H71,ENTIDAD!$B$2:$C$613,2,0)) -> HONDA SELVA DEL PERU S.A. | N71: 0 | O71: =N71*0.18 -> 0 | P71: 12959.57 | S71: =W71*AC71 -> 12959.567 | W71: 3.345 | AB71: D | AC71: 3874.31 | AD71: 30/02/2026 | AE71: CRE | AF71: 6011021 | AH71: 4212 | AR71: 18 | AS71: EXISTENCIAS POR RECIBIR
A72: 46052 | C72: 01 | D72: 00F005 | F72: 16568 | G72: 6 | H72: 20493508645 | I72: =IF(H72="","",VLOOKUP(H72,ENTIDAD!$B$2:$C$613,2,0)) -> HONDA SELVA DEL PERU S.A. | N72: =(S72-P72)/1.18 -> -0.0013135593 | O72: =N72*0.18 -> -0.00023644068 | P72: 6994.43 | S72: =W72*AC72 -> 6994.4285 | W72: 3.345 | AB72: D | AC72: 2091.01 | AD72: 30/02/2026 | AE72: CRE | AF72: 6011021 | AH72: 4212 | AR72: 18 | AS72: EXISTENCIAS POR RECIBIR
A73: 46052 | C73: 01 | D73: 00F001 | F73: 117195 | G73: 6 | H73: 20568499043 | I73: =IF(H73="","",VLOOKUP(H73,ENTIDAD!$B$2:$C$613,2,0)) -> SURTIDORES SAN MIGUEL E.I.R.L. | N73: =(S73-P73)/1.18 -> 0 | O73: =N73*0.18 -> 0 | P73: 100 | S73: 100 | AB73: S | AD73: 46052 | AE73: CON | AF73: 656009401 | AH73: 4212 | AR73: 18 | AS73: POR LA COMPRA DE COMBUSTIBLE
A74: 46052 | C74: 01 | D74: 00FC03 | F74: 6368972 | G74: 6 | H74: 20100047218 | I74: =IF(H74="","",VLOOKUP(H74,ENTIDAD!$B$2:$C$613,2,0)) -> BANCO DE CREDITO DEL PERU | N74: =(S74-P74)/1.18 -> 0 | O74: =N74*0.18 -> 0 | P74: 10 | S74: 10 | AB74: S | AD74: 46052 | AE74: CRE | AF74: 6391094 | AH74: 4212 | AR74: 18 | AS74: POR LA COMISION BANCARIA
A75: 46052 | C75: 01 | D75: 00FB25 | F75: 25630457 | G75: 6 | H75: 20100130204 | I75: =IF(H75="","",VLOOKUP(H75,ENTIDAD!$B$2:$C$613,2,0)) -> BANCO BBVA PERU | N75: =(S75-P75)/1.18 -> 0 | O75: =N75*0.18 -> 0 | P75: 40 | S75: 40 | AB75: S | AD75: 46052 | AE75: CRE | AF75: 6391094 | AH75: 4212 | AR75: 18 | AS75: POR LA COMISION BANCARIA
A76: 46053 | C76: 01 | D76: 00F001 | F76: 1109919 | G76: 6 | H76: 20265681299 | I76: =IF(H76="","",VLOOKUP(H76,ENTIDAD!$B$2:$C$613,2,0)) -> EQUIFAX PERU S.A. | N76: =(S76-P76)/1.18 -> 252 | O76: =N76*0.18 -> 45.36 | P76: 0 | S76: 297.36 | AB76: S | AD76: 46053 | AE76: CRE | AF76: 6599095 | AH76: 4212 | AR76: 18 | AS76: POR EL SERVICIO DE COBRANZA BLANCA
A77: 46049 | C77: 01 | D77: 00E001 | F77: 149 | G77: 6 | H77: 20444327066 | I77: =IF(H77="","",VLOOKUP(H77,ENTIDAD!$B$2:$C$613,2,0)) -> CAMARA DE COMERCIO E INDUSTRIAS SATIPO | N77: =(S77-P77)/1.18 -> 0 | O77: =N77*0.18 -> 0 | P77: 31 | S77: 31 | AB77: S | AD77: 46049 | AE77: CRE | AF77: 6591094 | AH77: 4212 | AR77: 18 | AS77: DONACION POR APOYO Y EFICIENTE ATENCION AL CLIENTE
C78: 01 | G78: 6 | H78: 0 | I78: =IF(H78="","",VLOOKUP(H78,ENTIDAD!$B$2:$C$613,2,0)) -> #N/A | N78: =(S78-P78)/1.18 -> 0 | O78: =N78*0.18 -> 0 | P78: 0 | S78: 0 | AB78: S | AE78: CRE | AH78: 4212 | AR78: 18
J79: =SUM(J4:J78) -> 0 | K79: =SUM(K4:K78) -> 0 | L79: =SUM(L4:L78) -> 0 | M79: =SUM(M4:M78) -> 0 | N79: =SUM(N4:N78) -> 13340.723 | O79: =SUM(O4:O78) -> 2401.3301 | P79: =SUM(P4:P78) -> 491607.49 | Q79: =SUM(Q4:Q78) -> 0 | ... S79: =SUM(S4:S78) -> 507349.53

Sheet FEBRERO
A1: FECHA DE EMISION DEL COMPROBANTE DE PAGO O DOCUMENTO | B1: FECHA DE VENCIMIENTO O FECHA DE PAGO | C1: COMPROBANTE DE PAGO O DOCUMENTO | F1: N° COMPROBANTE PAGO | G1: INFORMACION PROVEEDOR | J1: ADQUISICIONES GRAVADAS DESTINADAS A OPERACIONES GRAVADAS Y/O EXPORTACION | L1: ADQUISICIONES GRAVADAS DESTINADAS A OPERACIONES GRAVADAS Y/O DE EXPORTACION Y A OPERACIONES NO GRAVADAS | N1: ADQUISICIONES GRAVADAS DESTINADAS A OPERACIONES NO GRAVADAS | P1: VALOR DE LAS ADQUISICIONES NO GRAVADAS | Q1: ISC | R1: OTROS TRIBUTOS Y CARGOS | S1: IMPORTE TOTAL | T1: N° COMPROBANTE DE PAGO EMITIDO POR SUJETO NO DOMICILIADO | U1: CONSTANCIA DE DEPOSITO DE DETRACCION | W1: TIPO DE CAMBIO | X1: REFERENCIA DEL COMPROBANTE DE PAGO O DOCUMENTO ORIGINAL QUE SE MODIFICA | AB1: MONEDA | AC1: EQUIVALENTE EN DOLARES AMERICANOS | AD1: FECHA VENCIMIENTO | AE1: CONDICION CONTADO/CREDITO | AF1: CUENTA CONTABLE BASE IMPONIBLE | AG1: CUENTA CONTABLE OTROS TRIBUTOS Y CARGOS | AH1: CUENTA CONTABLE TOTAL | AI1: CODIGO CENTRO DE COSTOS | AJ1: CODIGO CENTRO DE COSTOS 2 | AK1: REGIMEN ESPECIAL | AL1: PORCENTAJE REGIMEN ESPECIAL | AM1: IMPORTE REGIMEN ESPECIAL | AN1: SERIE DOCUMENTO REGIMEN ESPECIAL | AO1: NUMERO DOCUMENTO REGIMEN ESPECIAL | AP1: FECHA DOCUMENTO REGIMEN ESPECIAL | AQ1: CODIGO PRESUPUESTO | AR1: PORCENTAJE I.G.V. | AS1: GLOSA | AT1: CONDICIÓN DE PERCEPCIÓN | AU1: IMPORTE RÉGIMEN ESPECIAL | AV1: CLASIFICACIÓN DE BIENES Y SERVICIOS ADQUIRIDOS
G2: DOCUMENTO IDENTIDAD | I2: APELLIDOS Y NOMBRES, DENOMINACION O RAZON SOCIAL
C3: TIPO | D3: SERIE/CODIGO ADUANA | E3: AÑO EMISION DUA O DSI | G3: TIPO | H3: NUMERO | J3: BASE IMPONIBLE | K3: IGV | L3: BASE IMPONIBLE | M3: IGV | N3: BASE IMPONIBLE | O3: IGV | U3: NUMERO | V3: FECHA EMISION | X3: FECHA | Y3: TIPO | Z3: SERIE | AA3: N° COMPROBANTE PAGO O DOCUMENTO
A4: 46051 | C4: 14 | D4: 00S898 | F4: 5654883 | G4: 6 | H4: 20129646099 | I4: =IF(H4="","",VLOOKUP(H4,ENTIDAD!$B$2:$C$613,2,0)) -> ELECTROCENTRO S.A. | N4: =(S4-P4)/1.18 -> 0 | O4: =N4*0.18 -> 0 | P4: 93.5 | S4: 93.5 | AB4: S | AD4: 46067 | AE4: CRE | AF4: 6361095 | AH4: 4212 | AR4: 18 | AS4: POR EL SERVICIO DE ENERGIA ELECTRICA
A5: 46051 | C5: 14 | D5: 00S898 | F5: 5654878 | G5: 6 | H5: 20129646099 | I5: =IF(H5="","",VLOOKUP(H5,ENTIDAD!$B$2:$C$613,2,0)) -> ELECTROCENTRO S.A. | N5: =(S5-P5)/1.18 -> 0 | O5: =N5*0.18 -> 0 | P5: 440 | S5: 440 | AB5: S | AD5: 46067 | AE5: CRE | AF5: 6361095 | AH5: 4212 | AR5: 18 | AS5: POR EL SERVICIO DE ENERGIA ELECTRICA
A6: 46051 | C6: 14 | D6: 00S898 | F6: 5655102 | G6: 6 | H6: 20129646099 | I6: =IF(H6="","",VLOOKUP(H6,ENTIDAD!$B$2:$C$613,2,0)) -> ELECTROCENTRO S.A. | N6: =(S6-P6)/1.18 -> 0 | O6: =N6*0.18 -> 0 | P6: 534.7 | S6: 534.7 | AB6: S | AD6: 46067 | AE6: CRE | AF6: 6361095 | AH6: 4212 | AR6: 18 | AS6: POR EL SERVICIO DE ENERGIA ELECTRICA
A7: 46053 | C7: 14 | D7: 000060 | F7: 1051587 | G7: 6 | H7: 20121876290 | I7: =IF(H7="","",VLOOKUP(H7,ENTIDAD!$B$2:$C$613,2,0)) -> ENT.PREST.SERV.SANEAM.SELVA CENTRAL S.A | N7: =(S7-P7)/1.18 -> 0 | O7: =N7*0.18 -> 0 | P7: 46.76 | S7: 46.76 | AB7: S | AD7: 46081 | AE7: CRE | AF7: 6363095 | AH7: 4212 | AR7: 18 | AS7: POR EL SERVICIO DE AGUA POTABLE
A8: 46053 | C8: 14 | D8: 000060 | F8: 1050833 | G8: 6 | H8: 20121876290 | I8: =IF(H8="","",VLOOKUP(H8,ENTIDAD!$B$2:$C$613,2,0)) -> ENT.PREST.SERV.SANEAM.SELVA CENTRAL S.A | N8: =(S8-P8)/1.18 -> 0 | O8: =N8*0.18 -> 0 | P8: 46.76 | S8: 46.76 | AB8: S | AD8: 46081 | AE8: CRE | AF8: 6363095 | AH8: 4212 | AR8: 18 | AS8: POR EL SERVICIO DE AGUA POTABLE
A9: 46053 | C9: 14 | D9: 000060 | F9: 1052362 | G9: 6 | H9: 20121876290 | I9: =IF(H9="","",VLOOKUP(H9,ENTIDAD!$B$2:$C$613,2,0)) -> ENT.PREST.SERV.SANEAM.SELVA CENTRAL S.A | N9: =(S9-P9)/1.18 -> 0 | O9: =N9*0.18 -> 0 | P9: 45.8 | S9: 45.8 | AB9: S | AD9: 46081 | AE9: CRE | AF9: 6363095 | AH9: 4212 | AR9: 18 | AS9: POR EL SERVICIO DE AGUA POTABLE
A10: 46054 | C10: 14 | D10: 00SB01 | F10: 601019205 | G10: 6 | H10: 20467534026 | I10: =IF(H10="","",VLOOKUP(H10,ENTIDAD!$B$2:$C$613,2,0)) -> AMERICA MOVIL PERU S.A.C. | N10: =(S10-P10)/1.18 -> 75.177966 | O10: =N10*0.18 -> 13.532034 | P10: -0.01 | S10: 88.7 | AB10: S | AD10: 46072 | AE10: CRE | AF10: 6365095 | AH10: 4212 | AR10: 18 | AS10: POR EL SERVICIO DE INTERNET
A11: 46055 | C11: 01 | D11: 00FB25 | F11: 25807856 | G11: 6 | H11: 20100130204 | I11: =IF(H11="","",VLOOKUP(H11,ENTIDAD!$B$2:$C$613,2,0)) -> BANCO BBVA PERU | N11: =(S11-P11)/1.18 -> 0 | O11: =N11*0.18 -> 0 | P11: 10 | S11: 10 | AB11: S | AD11: 46083 | AE11: CRE | AF11: 6391094 | AH11: 4212 | AR11: 18 | AS11: POR LA COMISION BANCARIA
A12: 46056 | C12: 01 | D12: 00E001 | F12: 1855 | G12: 6 | H12: 20568570520 | I12: =IF(H12="","",VLOOKUP(H12,ENTIDAD!$B$2:$C$613,2,0)) -> INVERSIONES IRWIN E.I.R.L. | N12: =(S12-P12)/1.18 -> 0 | O12: =N12*0.18 -> 0 | P12: 36 | S12: 36 | AB12: S | AE12: CON | AF12: 656009504 | AH12: 4212 | AR12: 18 | AS12: BOYA DE BRONCE
A13: 46056 | C13: 01 | D13: 00F001 | F13: 619 | G13: 6 | H13: 10733910921 | I13: =IF(H13="","",VLOOKUP(H13,ENTIDAD!$B$2:$C$613,2,0)) -> MADUEÑO HUAMAN LILI CLISSELY | N13: =(S13-P13)/1.18 -> 0 | O13: =N13*0.18 -> 0 | P13: 22 | S13: 22 | AB13: S | AE13: CON | AF13: 656009504 | AH13: 4212 | AR13: 18 | AS13: DADO HEXAGONAL
A14: 46056 | C14: 01 | D14: 00FC04 | F14: 4782894 | G14: 6 | H14: 20100130204 | I14: =IF(H14="","",VLOOKUP(H14,ENTIDAD!$B$2:$C$613,2,0)) -> BANCO BBVA PERU | N14: =(S14-P14)/1.18 -> 0 | O14: =N14*0.18 -> 0 | P14: 40 | S14: 40 | AB14: S | AD14: 46084 | AE14: CRE | AF14: 6391094 | AH14: 4212 | AR14: 18 | AS14: POR LA COMISION BANCARIA
A15: 46057 | C15: 01 | D15: 00E001 | F15: 1773 | G15: 6 | H15: 20486339510 | I15: =IF(H15="","",VLOOKUP(H15,ENTIDAD!$B$2:$C$613,2,0)) -> SERVICIOS CONTABLES Y AUDITORIA INTERNA S.A. | N15: =(S15-P15)/1.18 -> 1694.9153 | O15: =N15*0.18 -> 305.08475 | S15: 2000 | AB15: S | AD15: 46085 | AE15: CRE | AF15: 6323094 | AH15: 4212 | AR15: 18 | AS15: SERVICIO CONTABLE
A16: 46057 | C16: 01 | D16: 00FE01 | F16: 2692474 | G16: 6 | H16: 20100047218 | I16: =IF(H16="","",VLOOKUP(H16,ENTIDAD!$B$2:$C$613,2,0)) -> BANCO DE CREDITO DEL PERU | N16: =(S16-P16)/1.18 -> -0.0042372881 | O16: =N16*0.18 -> -0.00076271186 | P16: 117.78 | S16: =W16*AC16 -> 117.775 | W16: 3.365 | AB16: D | AC16: 35 | AD16: 46085 | AE16: CRE | AF16: 6391094 | AH16: 4212 | AR16: 18 | AS16: POR LA COMISION BANCARIA
A17: 46057 | C17: 01 | D17: 00FF01 | F17: 61 | G17: 6 | H17: 10421947665 | I17: =IF(H17="","",VLOOKUP(H17,ENTIDAD!$B$2:$C$613,2,0)) -> MAYTA,MADUEÑO,SAUL,JESUS | N17: =(S17-P17)/1.18 -> 0 | O17: =N17*0.18 -> 0 | P17: 60 | S17: 60 | AB17: S | AE17: CON | AF17: 656009502 | AH17: 4212 | AR17: 18 | AS17: POR LA COMPRA DE ARTICULOS DE LIMPIEZA
A18: 46057 | C18: 01 | D18: 00E001 | F18: 152 | G18: 6 | H18: 10447422951 | I18: =IF(H18="","",VLOOKUP(H18,ENTIDAD!$B$2:$C$613,2,0)) -> ZEGARRA AZAÑERO JORGE KEY | N18: =(S18-P18)/1.18 -> 0 | O18: =N18*0.18 -> 0 | P18: 450 | S18: 450 | AB18: S | AD18: 46085 | AE18: CRE | AF18: 6329094 | AH18: 4212 | AR18: 18 | AS18: SOPORTE TECNICO
A19: 46058 | C19: 01 | D19: 00F001 | F19: 8322 | G19: 6 | H19: 20610959432 | I19: =IF(H19="","",VLOOKUP(H19,ENTIDAD!$B$2:$C$613,2,0)) -> SERVICENTRO CRISNEYA EMPRESA INDIVIDUAL DE RESPONSABILIDAD LIMITADA | N19: =(S19-P19)/1.18 -> 0 | O19: =N19*0.18 -> 0 | P19: 10 | S19: 10 | AB19: S | AE19: CON | AF19: 656009501 | AH19: 4212 | AR19: 18 | AS19: POR LA COMPRA DE COMBUSTIBLE
A20: 46058 | C20: 01 | D20: 00FF01 | F20: 64 | G20: 6 | H20: 10421947665 | I20: =IF(H20="","",VLOOKUP(H20,ENTIDAD!$B$2:$C$613,2,0)) -> MAYTA,MADUEÑO,SAUL,JESUS | N20: =(S20-P20)/1.18 -> 0 | O20: =N20*0.18 -> 0 | P20: 9.5 | S20: 9.5 | AB20: S | AE20: CON | AF20: 656009502 | AH20: 4212 | AR20: 18 | AS20: POR LA COMPRA DE LIMPIAVIDRIOS
A21: 46058 | C21: 01 | D21: 00F006 | F21: 3448 | G21: 6 | H21: 20568909128 | I21: =IF(H21="","",VLOOKUP(H21,ENTIDAD!$B$2:$C$613,2,0)) -> MESSENGER WORLD E.I.R.L | N21: =(S21-P21)/1.18 -> 12.711864 | O21: =N21*0.18 -> 2.2881356 | P21: 0 | S21: 15 | AB21: S | AD21: 46086 | AE21: CRE | AF21: 6311195 | AH21: 4212 | AR21: 18 | AS21: POR EL SERVICIO DE TRANSPORTE
A22: 46058 | C22: 01 | D22: 00F001 | F22: 5421 | G22: 6 | H22: 10421947665 | I22: =IF(H22="","",VLOOKUP(H22,ENTIDAD!$B$2:$C$613,2,0)) -> MAYTA,MADUEÑO,SAUL,JESUS | N22: =(S22-P22)/1.18 -> 0 | O22: =N22*0.18 -> 0 | P22: 36 | S22: 36 | AB22: S | AE22: CON | AF22: 656009502 | AH22: 4212 | AR22: 18 | AS22: POR LA COMPRA DE ARTICULOS DE LIMPIEZA
A23: 46058 | C23: 01 | D23: 00E001 | F23: 5998 | G23: 6 | H23: 20602783341 | I23: =IF(H23="","",VLOOKUP(H23,ENTIDAD!$B$2:$C$613,2,0)) -> CODISSER VRAEM E.I.R.L. | N23: =(S23-P23)/1.18 -> 0 | O23: =N23*0.18 -> 0 | P23: 8 | S23: 8 | AB23: S | AE23: CON | AF23: 6250095 | AH23: 4212 | AR23: 18 | AS23: POR LA COMPRA DE AGUA MESA
A24: 46058 | C24: 01 | D24: 00F002 | F24: 133 | G24: 6 | H24: 20600454065 | I24: =IF(H24="","",VLOOKUP(H24,ENTIDAD!$B$2:$C$613,2,0)) -> REPUESTOS Y SERVICIOS ARAUCO E.I.R.L. | N24: =(S24-P24)/1.18 -> 0 | O24: =N24*0.18 -> 0 | P24: 2670 | S24: 2670 | AB24: S | AE24: CRE | AF24: 6343095 | AH24: 4212 | AR24: 18 | AS24: MANTENIMIENTO DE MOTOS VENDIDAS - GARANTIA
A25: 46060 | C25: 01 | D25: 00FI01 | F25: 18308599 | G25: 6 | H25: 20100047218 | I25: =IF(H25="","",VLOOKUP(H25,ENTIDAD!$B$2:$C$613,2,0)) -> BANCO DE CREDITO DEL PERU | N25: =(S25-P25)/1.18 -> 0 | O25: =N25*0.18 -> 0 | P25: 987.48 | S25: 987.48 | AB25: S | AD25: 46088 | AE25: CRE | AF25: 6391094 | AH25: 4212 | AR25: 18 | AS25: POR LA COMISION BANCARIA
A26: 46060 | C26: 01 | D26: 00F001 | F26: 5167 | G26: 6 | H26: 10061702071 | I26: =IF(H26="","",VLOOKUP(H26,ENTIDAD!$B$2:$C$613,2,0)) -> CORAL FLORES IVAN MARTIN | N26: =(S26-P26)/1.18 -> 0 | O26: =N26*0.18 -> 0 | P26: 455 | S26: 455 | AB26: S | AD26: 46088 | AE26: CRE | AF26: 6599095 | AG26: 1413 | AH26: 4212 | AR26: 18 | AS26: POR EL SERVICIO DE LEGALIZACION
A27: 46060 | C27: 01 | D27: 00E001 | F27: 659 | G27: 6 | H27: 10433685721 | I27: =IF(H27="","",VLOOKUP(H27,ENTIDAD!$B$2:$C$613,2,0)) -> MANDUJANO,SOLANO,JOSE,ELIAS | N27: =(S27-P27)/1.18 -> 0 | O27: =N27*0.18 -> 0 | P27: 14 | S27: 14 | AB27: S | AE27: CON | AF27: 656009503 | AH27: 4212 | AR27: 18 | AS27: POR LA COMPRA DE VINIFAN
A28: 46060 | C28: 01 | D28: 00FV14 | F28: 1292611 | G28: 6 | H28: 20100047218 | I28: =IF(H28="","",VLOOKUP(H28,ENTIDAD!$B$2:$C$613,2,0)) -> BANCO DE CREDITO DEL PERU | N28: =(S28-P28)/1.18 -> 0 | O28: =N28*0.18 -> 0 | P28: 132.5 | S28: 132.5 | AB28: S | AE28: CRE | AF28: 6391094 | AH28: 4212 | AR28: 18 | AS28: OPERACIÓN POR EXCESO
A29: 46063 | C29: 01 | D29: 00F001 | F29: 117458 | G29: 6 | H29: 20568499043 | I29: =IF(H29="","",VLOOKUP(H29,ENTIDAD!$B$2:$C$613,2,0)) -> SURTIDORES SAN MIGUEL E.I.R.L. | N29: =(S29-P29)/1.18 -> 0 | O29: =N29*0.18 -> 0 | P29: 100 | S29: 100 | AB29: S | AE29: CON | AF29: 656009401 | AH29: 4212 | AR29: 18 | AS29: POR LA COMPRA DE COMBUSTIBLE
A30: 46063 | C30: 01 | D30: 00E001 | F30: 12000 | G30: 6 | H30: 20568968051 | I30: =IF(H30="","",VLOOKUP(H30,ENTIDAD!$B$2:$C$613,2,0)) -> AUTOMOVIL SATIPO TOURS S.A.C. | N30: =(S30-P30)/1.18 -> 0 | O30: =N30*0.18 -> 0 | P30: 40 | S30: 40 | AB30: S | AD30: 46091 | AE30: CRE | AF30: 6599095 | AG30: 1413 | AH30: 4212 | AR30: 18 | AS30: POR EL SERVICIO DE TRANSPORTE DE PASAJERO
A31: 46063 | C31: 01 | D31: 00F001 | F31: 15741 | G31: 6 | H31: 20444766906 | I31: =IF(H31="","",VLOOKUP(H31,ENTIDAD!$B$2:$C$613,2,0)) -> EMPRESA DE TRANSPORTES PROFAMSE SRL | N31: =(S31-P31)/1.18 -> 0 | O31: =N31*0.18 -> 0 | P31: 40 | S31: 40 | AB31: S | AD31: 46091 | AE31: CRE | AF31: 6599095 | AG31: 1413 | AH31: 4212 | AR31: 18 | AS31: POR EL SERVICIO DE TRANSPORTE DE PASAJERO
A32: 46065 | C32: 01 | D32: 00F002 | F32: 2133 | G32: 6 | H32: 20603851171 | I32: =IF(H32="","",VLOOKUP(H32,ENTIDAD!$B$2:$C$613,2,0)) -> J&J RENATO E.I.R.L. | N32: =(S32-P32)/1.18 -> 0 | O32: =N32*0.18 -> 0 | P32: 3 | S32: 3 | AB32: S | AE32: CON | AF32: 656009504 | AH32: 4212 | AR32: 18 | AS32: POR LA COMPRA DE JEBE
A33: 46065 | C33: 01 | D33: 00F002 | F33: 173 | G33: 6 | H33: 10209907327 | I33: =IF(H33="","",VLOOKUP(H33,ENTIDAD!$B$2:$C$613,2,0)) -> TORPOCO,MAYTA,HECTOR,ALFONSO | N33: =(S33-P33)/1.18 -> 0 | O33: =N33*0.18 -> 0 | P33: 5 | S33: 5 | AB33: S | AE33: CON | AF33: 656009501 | AH33: 4212 | AR33: 18 | AS33: POR LA COMPRA DE COMBUSTIBLE
A34: 46065 | C34: 01 | D34: 00F006 | F34: 425 | G34: 6 | H34: 20568369000 | I34: =IF(H34="","",VLOOKUP(H34,ENTIDAD!$B$2:$C$613,2,0)) -> INFORMATICA Y GRAFICA EMPRESA INDIVIDUAL DE RESPONSABILIDAD LIMITADA - INFOGRAFIC E.I.R.L. | N34: =(S34-P34)/1.18 -> 0 | O34: =N34*0.18 -> 0 | P34: 40 | S34: 40 | AB34: S | AE34: CON | AF34: 656009506 | AH34: 4212 | AR34: 18 | AS34: POR LA COMPRA DE TINTA DE IMPRESORA
A35: 46065 | C35: 01 | D35: 00F028 | F35: 14845 | G35: 6 | H35: 20493508645 | I35: =IF(H35="","",VLOOKUP(H35,ENTIDAD!$B$2:$C$613,2,0)) -> HONDA SELVA DEL PERU S.A. | N35: =(S35-P35)/1.18 -> 0.0038389831 | O35: =N35*0.18 -> 0.00069101695 | P35: 13029.3 | S35: =W35*AC35 -> 13029.305 | W35: 3.363 | AB35: D | AC35: 3874.31 | AD35: 46093 | AE35: CRE | AF35: 6011021 | AH35: 4212 | AR35: 18 | AS35: EXISTENCIAS POR RECIBIR
A36: 46066 | C36: 01 | D36: 00F003 | F36: 3637109 | G36: 6 | H36: 20101973922 | I36: =IF(H36="","",VLOOKUP(H36,ENTIDAD!$B$2:$C$613,2,0)) -> ASOCIACION AUTOMOTRIZ DEL PERU | N36: 0 | O36: =N36*0.18 -> 0 | P36: 0 | R36: 66.8 | S36: 66.8 | AB36: S | AD36: 46094 | AE36: CRE | AF36: 6599095 | AG36: 1413 | AH36: 4212 | AR36: 18 | AS36: POR DERECHO DE EMISION DE PLACA DE RODAJE
A37: 46066 | C37: 01 | D37: 00F003 | F37: 3637110 | G37: 6 | H37: 20101973922 | I37: =IF(H37="","",VLOOKUP(H37,ENTIDAD!$B$2:$C$613,2,0)) -> ASOCIACION AUTOMOTRIZ DEL PERU | N37: 0 | O37: =N37*0.18 -> 0 | P37: 0 | R37: 66.8 | S37: 66.8 | AB37: S | AD37: 46094 | AE37: CRE | AF37: 6599095 | AG37: 1413 | AH37: 4212 | AR37: 18 | AS37: POR DERECHO DE EMISION DE PLACA DE RODAJE
A38: 46066 | C38: 01 | D38: 00F003 | F38: 3637111 | G38: 6 | H38: 20101973922 | I38: =IF(H38="","",VLOOKUP(H38,ENTIDAD!$B$2:$C$613,2,0)) -> ASOCIACION AUTOMOTRIZ DEL PERU | N38: 0 | O38: =N38*0.18 -> 0 | P38: 0 | R38: 66.8 | S38: 66.8 | AB38: S | AD38: 46094 | AE38: CRE | AF38: 6599095 | AG38: 1413 | AH38: 4212 | AR38: 18 | AS38: POR DERECHO DE EMISION DE PLACA DE RODAJE
A39: 46066 | C39: 01 | D39: 00F003 | F39: 3637112 | G39: 6 | H39: 20101973922 | I39: =IF(H39="","",VLOOKUP(H39,ENTIDAD!$B$2:$C$613,2,0)) -> ASOCIACION AUTOMOTRIZ DEL PERU | N39: 0 | O39: =N39*0.18 -> 0 | P39: 0 | R39: 66.8 | S39: 66.8 | AB39: S | AD39: 46094 | AE39: CRE | AF39: 6599095 | AG39: 1413 | AH39: 4212 | AR39: 18 | AS39: POR DERECHO DE EMISION DE PLACA DE RODAJE
A40: 46066 | C40: 01 | D40: 00F003 | F40: 3637113 | G40: 6 | H40: 20101973922 | I40: =IF(H40="","",VLOOKUP(H40,ENTIDAD!$B$2:$C$613,2,0)) -> ASOCIACION AUTOMOTRIZ DEL PERU | N40: 0 | O40: =N40*0.18 -> 0 | P40: 0 | R40: 66.8 | S40: 66.8 | AB40: S | AD40: 46094 | AE40: CRE | AF40: 6599095 | AG40: 1413 | AH40: 4212 | AR40: 18 | AS40: POR DERECHO DE EMISION DE PLACA DE RODAJE
A41: 46066 | C41: 01 | D41: 00F003 | F41: 3637114 | G41: 6 | H41: 20101973922 | I41: =IF(H41="","",VLOOKUP(H41,ENTIDAD!$B$2:$C$613,2,0)) -> ASOCIACION AUTOMOTRIZ DEL PERU | N41: 0 | O41: =N41*0.18 -> 0 | P41: 0 | R41: 66.8 | S41: 66.8 | AB41: S | AD41: 46094 | AE41: CRE | AF41: 6599095 | AG41: 1413 | AH41: 4212 | AR41: 18 | AS41: POR DERECHO DE EMISION DE PLACA DE RODAJE
A42: 46066 | C42: 01 | D42: 00F003 | F42: 3637115 | G42: 6 | H42: 20101973922 | I42: =IF(H42="","",VLOOKUP(H42,ENTIDAD!$B$2:$C$613,2,0)) -> ASOCIACION AUTOMOTRIZ DEL PERU | N42: 0 | O42: =N42*0.18 -> 0 | P42: 0 | R42: 66.8 | S42: 66.8 | AB42: S | AD42: 46094 | AE42: CRE | AF42: 6599095 | AG42: 1413 | AH42: 4212 | AR42: 18 | AS42: POR DERECHO DE EMISION DE PLACA DE RODAJE
A43: 46066 | C43: 01 | D43: 00F003 | F43: 3637116 | G43: 6 | H43: 20101973922 | I43: =IF(H43="","",VLOOKUP(H43,ENTIDAD!$B$2:$C$613,2,0)) -> ASOCIACION AUTOMOTRIZ DEL PERU | N43: 0 | O43: =N43*0.18 -> 0 | P43: 0 | R43: 66.8 | S43: 66.8 | AB43: S | AD43: 46094 | AE43: CRE | AF43: 6599095 | AG43: 1413 | AH43: 4212 | AR43: 18 | AS43: POR DERECHO DE EMISION DE PLACA DE RODAJE
A44: 46066 | C44: 01 | D44: 00F003 | F44: 3637117 | G44: 6 | H44: 20101973922 | I44: =IF(H44="","",VLOOKUP(H44,ENTIDAD!$B$2:$C$613,2,0)) -> ASOCIACION AUTOMOTRIZ DEL PERU | N44: 0 | O44: =N44*0.18 -> 0 | P44: 0 | R44: 66.8 | S44: 66.8 | AB44: S | AD44: 46094 | AE44: CRE | AF44: 6599095 | AG44: 1413 | AH44: 4212 | AR44: 18 | AS44: POR DERECHO DE EMISION DE PLACA DE RODAJE
A45: 46066 | C45: 01 | D45: 00F003 | F45: 3637118 | G45: 6 | H45: 20101973922 | I45: =IF(H45="","",VLOOKUP(H45,ENTIDAD!$B$2:$C$613,2,0)) -> ASOCIACION AUTOMOTRIZ DEL PERU | N45: 0 | O45: =N45*0.18 -> 0 | P45: 0 | R45: 66.8 | S45: 66.8 | AB45: S | AD45: 46094 | AE45: CRE | AF45: 6599095 | AG45: 1413 | AH45: 4212 | AR45: 18 | AS45: POR DERECHO DE EMISION DE PLACA DE RODAJE
A46: 46066 | C46: 01 | D46: 00F003 | F46: 3637119 | G46: 6 | H46: 20101973922 | I46: =IF(H46="","",VLOOKUP(H46,ENTIDAD!$B$2:$C$613,2,0)) -> ASOCIACION AUTOMOTRIZ DEL PERU | N46: 0 | O46: =N46*0.18 -> 0 | P46: 0 | R46: 66.8 | S46: 66.8 | AB46: S | AD46: 46094 | AE46: CRE | AF46: 6599095 | AG46: 1413 | AH46: 4212 | AR46: 18 | AS46: POR DERECHO DE EMISION DE PLACA DE RODAJE
A47: 46066 | C47: 01 | D47: 00F003 | F47: 3637120 | G47: 6 | H47: 20101973922 | I47: =IF(H47="","",VLOOKUP(H47,ENTIDAD!$B$2:$C$613,2,0)) -> ASOCIACION AUTOMOTRIZ DEL PERU | N47: 0 | O47: =N47*0.18 -> 0 | P47: 0 | R47: 66.8 | S47: 66.8 | AB47: S | AD47: 46094 | AE47: CRE | AF47: 6599095 | AG47: 1413 | AH47: 4212 | AR47: 18 | AS47: POR DERECHO DE EMISION DE PLACA DE RODAJE
... A55: 46066 | C55: 01 | D55: 00F003 | F55: 3637128 | G55: 6 | H55: 20101973922 | I55: =IF(H55="","",VLOOKUP(H55,ENTIDAD!$B$2:$C$613,2,0)) -> ASOCIACION AUTOMOTRIZ DEL PERU | N55: 0 | O55: =N55*0.18 -> 0 | P55: 0 | R55: 66.8 | S55: 66.8 | AB55: S | AD55: 46094 | AE55: CRE | AF55: 6599095 | AG55: 1413 | AH55: 4212 | AR55: 18 | AS55: POR DERECHO DE EMISION DE PLACA DE RODAJE
A56: 46066 | C56: 01 | D56: 00F011 | F56: 14865 | G56: 6 | H56: 20508647311 | I56: =IF(H56="","",VLOOKUP(H56,ENTIDAD!$B$2:$C$613,2,0)) -> CAFE EL POLO S.A.C. | N56: =(S56-P56)/1.18 -> 98.813559 | O56: =N56*0.18 -> 17.786441 | P56: 0 | S56: 116.6 | AB56: S | AE56: CRE | AF56: 6314094 | AH56: 4212 | AR56: 18 | AS56: POR CONSUMO
A57: 46067 | C57: 01 | D57: 00F003 | F57: 3643318 | G57: 6 | H57: 20101973922 | I57: =IF(H57="","",VLOOKUP(H57,ENTIDAD!$B$2:$C$613,2,0)) -> ASOCIACION AUTOMOTRIZ DEL PERU | N57: 0 | O57: =N57*0.18 -> 0 | P57: 0 | R57: 66.8 | S57: 66.8 | AB57: S | AD57: 46095 | AE57: CRE | AF57: 6599095 | AG57: 1413 | AH57: 4212 | AR57: 18 | AS57: POR DERECHO DE EMISION DE PLACA DE RODAJE
A58: 46067 | C58: 01 | D58: 00F003 | F58: 3643319 | G58: 6 | H58: 20101973922 | I58: =IF(H58="","",VLOOKUP(H58,ENTIDAD!$B$2:$C$613,2,0)) -> ASOCIACION AUTOMOTRIZ DEL PERU | N58: 0 | O58: =N58*0.18 -> 0 | P58: 0 | R58: 66.8 | S58: 66.8 | AB58: S | AD58: 46095 | AE58: CRE | AF58: 6599095 | AG58: 1413 | AH58: 4212 | AR58: 18 | AS58: POR DERECHO DE EMISION DE PLACA DE RODAJE
A59: 46067 | C59: 01 | D59: 00F003 | F59: 3643320 | G59: 6 | H59: 20101973922 | I59: =IF(H59="","",VLOOKUP(H59,ENTIDAD!$B$2:$C$613,2,0)) -> ASOCIACION AUTOMOTRIZ DEL PERU | N59: 0 | O59: =N59*0.18 -> 0 | P59: 0 | R59: 66.8 | S59: 66.8 | AB59: S | AD59: 46095 | AE59: CRE | AF59: 6599095 | AG59: 1413 | AH59: 4212 | AR59: 18 | AS59: POR DERECHO DE EMISION DE PLACA DE RODAJE
A60: 46067 | C60: 01 | D60: 00F003 | F60: 3643321 | G60: 6 | H60: 20101973922 | I60: =IF(H60="","",VLOOKUP(H60,ENTIDAD!$B$2:$C$613,2,0)) -> ASOCIACION AUTOMOTRIZ DEL PERU | N60: 0 | O60: =N60*0.18 -> 0 | P60: 0 | R60: 66.8 | S60: 66.8 | AB60: S | AD60: 46095 | AE60: CRE | AF60: 6599095 | AG60: 1413 | AH60: 4212 | AR60: 18 | AS60: POR DERECHO DE EMISION DE PLACA DE RODAJE
A61: 46067 | C61: 01 | D61: 00F003 | F61: 3643322 | G61: 6 | H61: 20101973922 | I61: =IF(H61="","",VLOOKUP(H61,ENTIDAD!$B$2:$C$613,2,0)) -> ASOCIACION AUTOMOTRIZ DEL PERU | N61: 0 | O61: =N61*0.18 -> 0 | P61: 0 | R61: 66.8 | S61: 66.8 | AB61: S | AD61: 46095 | AE61: CRE | AF61: 6599095 | AG61: 1413 | AH61: 4212 | AR61: 18 | AS61: POR DERECHO DE EMISION DE PLACA DE RODAJE
A62: 46067 | C62: 01 | D62: 00F003 | F62: 3643323 | G62: 6 | H62: 20101973922 | I62: =IF(H62="","",VLOOKUP(H62,ENTIDAD!$B$2:$C$613,2,0)) -> ASOCIACION AUTOMOTRIZ DEL PERU | N62: 0 | O62: =N62*0.18 -> 0 | P62: 0 | R62: 66.8 | S62: 66.8 | AB62: S | AD62: 46095 | AE62: CRE | AF62: 6599095 | AG62: 1413 | AH62: 4212 | AR62: 18 | AS62: POR DERECHO DE EMISION DE PLACA DE RODAJE
A63: 46067 | C63: 01 | D63: 00F003 | F63: 3643324 | G63: 6 | H63: 20101973922 | I63: =IF(H63="","",VLOOKUP(H63,ENTIDAD!$B$2:$C$613,2,0)) -> ASOCIACION AUTOMOTRIZ DEL PERU | N63: 0 | O63: =N63*0.18 -> 0 | P63: 0 | R63: 66.8 | S63: 66.8 | AB63: S | AD63: 46095 | AE63: CRE | AF63: 6599095 | AG63: 1413 | AH63: 4212 | AR63: 18 | AS63: POR DERECHO DE EMISION DE PLACA DE RODAJE
A64: 46067 | C64: 01 | D64: 00F003 | F64: 3643325 | G64: 6 | H64: 20101973922 | I64: =IF(H64="","",VLOOKUP(H64,ENTIDAD!$B$2:$C$613,2,0)) -> ASOCIACION AUTOMOTRIZ DEL PERU | N64: 0 | O64: =N64*0.18 -> 0 | P64: 0 | R64: 66.8 | S64: 66.8 | AB64: S | AD64: 46095 | AE64: CRE | AF64: 6599095 | AG64: 1413 | AH64: 4212 | AR64: 18 | AS64: POR DERECHO DE EMISION DE PLACA DE RODAJE
A65: 46067 | C65: 01 | D65: 00F003 | F65: 3643326 | G65: 6 | H65: 20101973922 | I65: =IF(H65="","",VLOOKUP(H65,ENTIDAD!$B$2:$C$613,2,0)) -> ASOCIACION AUTOMOTRIZ DEL PERU | N65: 0 | O65: =N65*0.18 -> 0 | P65: 0 | R65: 66.8 | S65: 66.8 | AB65: S | AD65: 46095 | AE65: CRE | AF65: 6599095 | AG65: 1413 | AH65: 4212 | AR65: 18 | AS65: POR DERECHO DE EMISION DE PLACA DE RODAJE
A66: 46067 | C66: 01 | D66: 00F003 | F66: 3643327 | G66: 6 | H66: 20101973922 | I66: =IF(H66="","",VLOOKUP(H66,ENTIDAD!$B$2:$C$613,2,0)) -> ASOCIACION AUTOMOTRIZ DEL PERU | N66: 0 | O66: =N66*0.18 -> 0 | P66: 0 | R66: 66.8 | S66: 66.8 | AB66: S | AD66: 46095 | AE66: CRE | AF66: 6599095 | AG66: 1413 | AH66: 4212 | AR66: 18 | AS66: POR DERECHO DE EMISION DE PLACA DE RODAJE
A67: 46067 | C67: 01 | D67: 00F003 | F67: 3643328 | G67: 6 | H67: 20101973922 | I67: =IF(H67="","",VLOOKUP(H67,ENTIDAD!$B$2:$C$613,2,0)) -> ASOCIACION AUTOMOTRIZ DEL PERU | N67: 0 | O67: =N67*0.18 -> 0 | P67: 0 | R67: 66.8 | S67: 66.8 | AB67: S | AD67: 46095 | AE67: CRE | AF67: 6599095 | AG67: 1413 | AH67: 4212 | AR67: 18 | AS67: POR DERECHO DE EMISION DE PLACA DE RODAJE
A68: 46067 | C68: 01 | D68: 00F003 | F68: 3643329 | G68: 6 | H68: 20101973922 | I68: =IF(H68="","",VLOOKUP(H68,ENTIDAD!$B$2:$C$613,2,0)) -> ASOCIACION AUTOMOTRIZ DEL PERU | N68: 0 | O68: =N68*0.18 -> 0 | P68: 0 | R68: 66.8 | S68: 66.8 | AB68: S | AD68: 46095 | AE68: CRE | AF68: 6599095 | AG68: 1413 | AH68: 4212 | AR68: 18 | AS68: POR DERECHO DE EMISION DE PLACA DE RODAJE
... A116: 46067 | C116: 01 | D116: 00F003 | F116: 3645360 | G116: 6 | H116: 20101973922 | I116: =IF(H116="","",VLOOKUP(H116,ENTIDAD!$B$2:$C$613,2,0)) -> ASOCIACION AUTOMOTRIZ DEL PERU | N116: 0 | O116: =N116*0.18 -> 0 | P116: 0 | R116: 66.8 | S116: 66.8 | AB116: S | AD116: 46095 | AE116: CRE | AF116: 6599095 | AG116: 1413 | AH116: 4212 | AR116: 18 | AS116: POR DERECHO DE EMISION DE PLACA DE RODAJE
A117: 46067 | C117: 01 | D117: 00FB42 | F117: 10174 | G117: 6 | H117: 20555901179 | I117: =IF(H117="","",VLOOKUP(H117,ENTIDAD!$B$2:$C$613,2,0)) -> MOVIL BUS S.A.C | N117: =(S117-P117)/1.18 -> 0 | O117: =N117*0.18 -> 0 | P117: 95 | S117: 95 | AB117: S | AE117: CON | AF117: 6311295 | AH117: 4212 | AR117: 18 | AS117: POR EL SERVICIO DE TRANSPORTE DE PASAJERO
A118: 46067 | C118: 01 | D118: 00F002 | F118: 177 | G118: 6 | H118: 10209907327 | I118: =IF(H118="","",VLOOKUP(H118,ENTIDAD!$B$2:$C$613,2,0)) -> TORPOCO,MAYTA,HECTOR,ALFONSO | N118: =(S118-P118)/1.18 -> 0 | O118: =N118*0.18 -> 0 | P118: 10 | S118: 10 | AB118: S | AE118: CON | AF118: 656009501 | AH118: 4212 | AR118: 18 | AS118: POR LA COMPRA DE COMBUSTIBLE
A119: 46067 | C119: 01 | D119: 00F003 | F119: 3638906 | G119: 6 | H119: 20101973922 | I119: =IF(H119="","",VLOOKUP(H119,ENTIDAD!$B$2:$C$613,2,0)) -> ASOCIACION AUTOMOTRIZ DEL PERU | N119: 0 | O119: =N119*0.18 -> 0 | P119: 0 | R119: 66.8 | S119: 66.8 | AB119: S | AD119: 46095 | AE119: CRE | AF119: 6599095 | AG119: 1413 | AH119: 4212 | AR119: 18 | AS119: POR DERECHO DE EMISION DE PLACA DE RODAJE
A120: 46067 | C120: 01 | D120: 00F003 | F120: 3638907 | G120: 6 | H120: 20101973922 | I120: =IF(H120="","",VLOOKUP(H120,ENTIDAD!$B$2:$C$613,2,0)) -> ASOCIACION AUTOMOTRIZ DEL PERU | N120: 0 | O120: =N120*0.18 -> 0 | P120: 0 | R120: 66.8 | S120: 66.8 | AB120: S | AD120: 46095 | AE120: CRE | AF120: 6599095 | AG120: 1413 | AH120: 4212 | AR120: 18 | AS120: POR DERECHO DE EMISION DE PLACA DE RODAJE
A121: 46067 | C121: 01 | D121: 00F003 | F121: 3638908 | G121: 6 | H121: 20101973922 | I121: =IF(H121="","",VLOOKUP(H121,ENTIDAD!$B$2:$C$613,2,0)) -> ASOCIACION AUTOMOTRIZ DEL PERU | N121: 0 | O121: =N121*0.18 -> 0 | P121: 0 | R121: 66.8 | S121: 66.8 | AB121: S | AD121: 46095 | AE121: CRE | AF121: 6599095 | AG121: 1413 | AH121: 4212 | AR121: 18 | AS121: POR DERECHO DE EMISION DE PLACA DE RODAJE
A122: 46067 | C122: 01 | D122: 00F003 | F122: 3638909 | G122: 6 | H122: 20101973922 | I122: =IF(H122="","",VLOOKUP(H122,ENTIDAD!$B$2:$C$613,2,0)) -> ASOCIACION AUTOMOTRIZ DEL PERU | N122: 0 | O122: =N122*0.18 -> 0 | P122: 0 | R122: 66.8 | S122: 66.8 | AB122: S | AD122: 46095 | AE122: CRE | AF122: 6599095 | AG122: 1413 | AH122: 4212 | AR122: 18 | AS122: POR DERECHO DE EMISION DE PLACA DE RODAJE
A123: 46067 | C123: 01 | D123: 00F003 | F123: 3638910 | G123: 6 | H123: 20101973922 | I123: =IF(H123="","",VLOOKUP(H123,ENTIDAD!$B$2:$C$613,2,0)) -> ASOCIACION AUTOMOTRIZ DEL PERU | N123: 0 | O123: =N123*0.18 -> 0 | P123: 0 | R123: 66.8 | S123: 66.8 | AB123: S | AD123: 46095 | AE123: CRE | AF123: 6599095 | AG123: 1413 | AH123: 4212 | AR123: 18 | AS123: POR DERECHO DE EMISION DE PLACA DE RODAJE
A124: 46067 | C124: 01 | D124: 00F003 | F124: 3638911 | G124: 6 | H124: 20101973922 | I124: =IF(H124="","",VLOOKUP(H124,ENTIDAD!$B$2:$C$613,2,0)) -> ASOCIACION AUTOMOTRIZ DEL PERU | N124: 0 | O124: =N124*0.18 -> 0 | P124: 0 | R124: 66.8 | S124: 66.8 | AB124: S | AD124: 46095 | AE124: CRE | AF124: 6599095 | AG124: 1413 | AH124: 4212 | AR124: 18 | AS124: POR DERECHO DE EMISION DE PLACA DE RODAJE
A125: 46067 | C125: 01 | D125: 00F003 | F125: 3638912 | G125: 6 | H125: 20101973922 | I125: =IF(H125="","",VLOOKUP(H125,ENTIDAD!$B$2:$C$613,2,0)) -> ASOCIACION AUTOMOTRIZ DEL PERU | N125: 0 | O125: =N125*0.18 -> 0 | P125: 0 | R125: 66.8 | S125: 66.8 | AB125: S | AD125: 46095 | AE125: CRE | AF125: 6599095 | AG125: 1413 | AH125: 4212 | AR125: 18 | AS125: POR DERECHO DE EMISION DE PLACA DE RODAJE
A126: 46067 | C126: 01 | D126: 00F003 | F126: 3638913 | G126: 6 | H126: 20101973922 | I126: =IF(H126="","",VLOOKUP(H126,ENTIDAD!$B$2:$C$613,2,0)) -> ASOCIACION AUTOMOTRIZ DEL PERU | N126: 0 | O126: =N126*0.18 -> 0 | P126: 0 | R126: 66.8 | S126: 66.8 | AB126: S | AD126: 46095 | AE126: CRE | AF126: 6599095 | AG126: 1413 | AH126: 4212 | AR126: 18 | AS126: POR DERECHO DE EMISION DE PLACA DE RODAJE
A127: 46067 | C127: 01 | D127: 00F003 | F127: 3638914 | G127: 6 | H127: 20101973922 | I127: =IF(H127="","",VLOOKUP(H127,ENTIDAD!$B$2:$C$613,2,0)) -> ASOCIACION AUTOMOTRIZ DEL PERU | N127: 0 | O127: =N127*0.18 -> 0 | P127: 0 | R127: 66.8 | S127: 66.8 | AB127: S | AD127: 46095 | AE127: CRE | AF127: 6599095 | AG127: 1413 | AH127: 4212 | AR127: 18 | AS127: POR DERECHO DE EMISION DE PLACA DE RODAJE
A128: 46067 | C128: 01 | D128: 00F003 | F128: 3638915 | G128: 6 | H128: 20101973922 | I128: =IF(H128="","",VLOOKUP(H128,ENTIDAD!$B$2:$C$613,2,0)) -> ASOCIACION AUTOMOTRIZ DEL PERU | N128: 0 | O128: =N128*0.18 -> 0 | P128: 0 | R128: 66.8 | S128: 66.8 | AB128: S | AD128: 46095 | AE128: CRE | AF128: 6599095 | AG128: 1413 | AH128: 4212 | AR128: 18 | AS128: POR DERECHO DE EMISION DE PLACA DE RODAJE
A129: 46067 | C129: 01 | D129: 00F003 | F129: 3638916 | G129: 6 | H129: 20101973922 | I129: =IF(H129="","",VLOOKUP(H129,ENTIDAD!$B$2:$C$613,2,0)) -> ASOCIACION AUTOMOTRIZ DEL PERU | N129: 0 | O129: =N129*0.18 -> 0 | P129: 0 | R129: 66.8 | S129: 66.8 | AB129: S | AD129: 46095 | AE129: CRE | AF129: 6599095 | AG129: 1413 | AH129: 4212 | AR129: 18 | AS129: POR DERECHO DE EMISION DE PLACA DE RODAJE
A130: 46067 | C130: 01 | D130: 00F003 | F130: 3638917 | G130: 6 | H130: 20101973922 | I130: =IF(H130="","",VLOOKUP(H130,ENTIDAD!$B$2:$C$613,2,0)) -> ASOCIACION AUTOMOTRIZ DEL PERU | N130: 0 | O130: =N130*0.18 -> 0 | P130: 0 | R130: 66.8 | S130: 66.8 | AB130: S | AD130: 46095 | AE130: CRE | AF130: 6599095 | AG130: 1413 | AH130: 4212 | AR130: 18 | AS130: POR DERECHO DE EMISION DE PLACA DE RODAJE
... A191: 46067 | C191: 01 | D191: 00F003 | F191: 3641111 | G191: 6 | H191: 20101973922 | I191: =IF(H191="","",VLOOKUP(H191,ENTIDAD!$B$2:$C$613,2,0)) -> ASOCIACION AUTOMOTRIZ DEL PERU | N191: 0 | O191: =N191*0.18 -> 0 | P191: 0 | R191: 66.8 | S191: 66.8 | AB191: S | AD191: 46094 | AE191: CRE | AF191: 6599095 | AG191: 1413 | AH191: 4212 | AR191: 18 | AS191: POR DERECHO DE EMISION DE PLACA DE RODAJE
A192: 46068 | C192: 01 | D192: 00F155 | F192: 10599 | G192: 6 | H192: 20505365217 | I192: =IF(H192="","",VLOOKUP(H192,ENTIDAD!$B$2:$C$613,2,0)) -> EMPRESA DE TRANSPORTES Y TURISMO RARAZ S.A.C. | N192: =(S192-P192)/1.18 -> 0 | O192: =N192*0.18 -> 0 | P192: 120 | S192: 120 | AB192: S | AE192: CRE | AF192: 6311295 | AH192: 4212 | AR192: 18 | AS192: POR EL SERVICIO DE TRANSPORTE DE PASAJERO
A193: 46069 | C193: 01 | D193: 00F001 | F193: 2163 | G193: 6 | H193: 20604975159 | I193: =IF(H193="","",VLOOKUP(H193,ENTIDAD!$B$2:$C$613,2,0)) -> CORPORACION CARELI EMPRESA INDIVIDUAL DE RESPONSABILIDAD LIMITADA - CORPORACION CARELI E.I.R.L. | N193: =(S193-P193)/1.18 -> 0 | O193: =N193*0.18 -> 0 | P193: 130 | S193: 130 | AB193: S | AE193: CON | AF193: 656009506 | AH193: 4212 | AR193: 18 | AS193: POR LA COMPRA DE TINTA DE IMPRESORA
A194: 46070 | C194: 01 | D194: 00F005 | F194: 16737 | G194: 6 | H194: 20493508645 | I194: =IF(H194="","",VLOOKUP(H194,ENTIDAD!$B$2:$C$613,2,0)) -> HONDA SELVA DEL PERU S.A. | N194: =(S194-P194)/1.18 -> -0.0017627119 | O194: =N194*0.18 -> -0.00031728814 | P194: 26090.62 | S194: =W194*AC194 -> 26090.618 | W194: 3.356 | AB194: D | AC194: 7774.32 | AD194: 46098 | AE194: CRE | AF194: 6011021 | AH194: 4212 | AR194: 18 | AS194: EXISTENCIAS POR RECIBIR
A195: 46071 | C195: 01 | D195: 00F003 | F195: 3669081 | G195: 6 | H195: 20101973922 | I195: =IF(H195="","",VLOOKUP(H195,ENTIDAD!$B$2:$C$613,2,0)) -> ASOCIACION AUTOMOTRIZ DEL PERU | N195: 0 | O195: =N195*0.18 -> 0 | P195: 0 | R195: 66.8 | S195: 66.8 | AB195: S | AD195: 46099 | AE195: CRE | AF195: 6599095 | AG195: 1413 | AH195: 4212 | AR195: 18 | AS195: POR DERECHO DE EMISION DE PLACA DE RODAJE
A196: 46071 | C196: 01 | D196: 00F003 | F196: 3669082 | G196: 6 | H196: 20101973922 | I196: =IF(H196="","",VLOOKUP(H196,ENTIDAD!$B$2:$C$613,2,0)) -> ASOCIACION AUTOMOTRIZ DEL PERU | N196: 0 | O196: =N196*0.18 -> 0 | P196: 0 | R196: 66.8 | S196: 66.8 | AB196: S | AD196: 46099 | AE196: CRE | AF196: 6599095 | AG196: 1413 | AH196: 4212 | AR196: 18 | AS196: POR DERECHO DE EMISION DE PLACA DE RODAJE
A197: 46071 | C197: 01 | D197: 00F003 | F197: 3669083 | G197: 6 | H197: 20101973922 | I197: =IF(H197="","",VLOOKUP(H197,ENTIDAD!$B$2:$C$613,2,0)) -> ASOCIACION AUTOMOTRIZ DEL PERU | N197: 0 | O197: =N197*0.18 -> 0 | P197: 0 | R197: 66.8 | S197: 66.8 | AB197: S | AD197: 46099 | AE197: CRE | AF197: 6599095 | AG197: 1413 | AH197: 4212 | AR197: 18 | AS197: POR DERECHO DE EMISION DE PLACA DE RODAJE
A198: 46071 | C198: 01 | D198: 00F003 | F198: 3669084 | G198: 6 | H198: 20101973922 | I198: =IF(H198="","",VLOOKUP(H198,ENTIDAD!$B$2:$C$613,2,0)) -> ASOCIACION AUTOMOTRIZ DEL PERU | N198: 0 | O198: =N198*0.18 -> 0 | P198: 0 | R198: 66.8 | S198: 66.8 | AB198: S | AD198: 46099 | AE198: CRE | AF198: 6599095 | AG198: 1413 | AH198: 4212 | AR198: 18 | AS198: POR DERECHO DE EMISION DE PLACA DE RODAJE
A199: 46071 | C199: 01 | D199: 00F003 | F199: 3669085 | G199: 6 | H199: 20101973922 | I199: =IF(H199="","",VLOOKUP(H199,ENTIDAD!$B$2:$C$613,2,0)) -> ASOCIACION AUTOMOTRIZ DEL PERU | N199: 0 | O199: =N199*0.18 -> 0 | P199: 0 | R199: 66.8 | S199: 66.8 | AB199: S | AD199: 46099 | AE199: CRE | AF199: 6599095 | AG199: 1413 | AH199: 4212 | AR199: 18 | AS199: POR DERECHO DE EMISION DE PLACA DE RODAJE
A200: 46071 | C200: 01 | D200: 00F003 | F200: 3669086 | G200: 6 | H200: 20101973922 | I200: =IF(H200="","",VLOOKUP(H200,ENTIDAD!$B$2:$C$613,2,0)) -> ASOCIACION AUTOMOTRIZ DEL PERU | N200: 0 | O200: =N200*0.18 -> 0 | P200: 0 | R200: 66.8 | S200: 66.8 | AB200: S | AD200: 46099 | AE200: CRE | AF200: 6599095 | AG200: 1413 | AH200: 4212 | AR200: 18 | AS200: POR DERECHO DE EMISION DE PLACA DE RODAJE
A201: 46071 | C201: 01 | D201: 00F003 | F201: 3669087 | G201: 6 | H201: 20101973922 | I201: =IF(H201="","",VLOOKUP(H201,ENTIDAD!$B$2:$C$613,2,0)) -> ASOCIACION AUTOMOTRIZ DEL PERU | N201: 0 | O201: =N201*0.18 -> 0 | P201: 0 | R201: 66.8 | S201: 66.8 | AB201: S | AD201: 46099 | AE201: CRE | AF201: 6599095 | AG201: 1413 | AH201: 4212 | AR201: 18 | AS201: POR DERECHO DE EMISION DE PLACA DE RODAJE
A202: 46071 | C202: 01 | D202: 00F003 | F202: 3669088 | G202: 6 | H202: 20101973922 | I202: =IF(H202="","",VLOOKUP(H202,ENTIDAD!$B$2:$C$613,2,0)) -> ASOCIACION AUTOMOTRIZ DEL PERU | N202: 0 | O202: =N202*0.18 -> 0 | P202: 0 | R202: 66.8 | S202: 66.8 | AB202: S | AD202: 46099 | AE202: CRE | AF202: 6599095 | AG202: 1413 | AH202: 4212 | AR202: 18 | AS202: POR DERECHO DE EMISION DE PLACA DE RODAJE
A203: 46071 | C203: 01 | D203: 00F003 | F203: 3669089 | G203: 6 | H203: 20101973922 | I203: =IF(H203="","",VLOOKUP(H203,ENTIDAD!$B$2:$C$613,2,0)) -> ASOCIACION AUTOMOTRIZ DEL PERU | N203: 0 | O203: =N203*0.18 -> 0 | P203: 0 | R203: 66.8 | S203: 66.8 | AB203: S | AD203: 46099 | AE203: CRE | AF203: 6599095 | AG203: 1413 | AH203: 4212 | AR203: 18 | AS203: POR DERECHO DE EMISION DE PLACA DE RODAJE
A204: 46071 | C204: 01 | D204: 00F003 | F204: 3669090 | G204: 6 | H204: 20101973922 | I204: =IF(H204="","",VLOOKUP(H204,ENTIDAD!$B$2:$C$613,2,0)) -> ASOCIACION AUTOMOTRIZ DEL PERU | N204: 0 | O204: =N204*0.18 -> 0 | P204: 0 | R204: 66.8 | S204: 66.8 | AB204: S | AD204: 46099 | AE204: CRE | AF204: 6599095 | AG204: 1413 | AH204: 4212 | AR204: 18 | AS204: POR DERECHO DE EMISION DE PLACA DE RODAJE
A205: 46071 | C205: 01 | D205: 00F003 | F205: 3669091 | G205: 6 | H205: 20101973922 | I205: =IF(H205="","",VLOOKUP(H205,ENTIDAD!$B$2:$C$613,2,0)) -> ASOCIACION AUTOMOTRIZ DEL PERU | N205: 0 | O205: =N205*0.18 -> 0 | P205: 0 | R205: 66.8 | S205: 66.8 | AB205: S | AD205: 46099 | AE205: CRE | AF205: 6599095 | AG205: 1413 | AH205: 4212 | AR205: 18 | AS205: POR DERECHO DE EMISION DE PLACA DE RODAJE
A206: 46071 | C206: 01 | D206: 00F003 | F206: 3669092 | G206: 6 | H206: 20101973922 | I206: =IF(H206="","",VLOOKUP(H206,ENTIDAD!$B$2:$C$613,2,0)) -> ASOCIACION AUTOMOTRIZ DEL PERU | N206: 0 | O206: =N206*0.18 -> 0 | P206: 0 | R206: 66.8 | S206: 66.8 | AB206: S | AD206: 46099 | AE206: CRE | AF206: 6599095 | AG206: 1413 | AH206: 4212 | AR206: 18 | AS206: POR DERECHO DE EMISION DE PLACA DE RODAJE
... A222: 46071 | C222: 01 | D222: 00F003 | F222: 3669108 | G222: 6 | H222: 20101973922 | I222: =IF(H222="","",VLOOKUP(H222,ENTIDAD!$B$2:$C$613,2,0)) -> ASOCIACION AUTOMOTRIZ DEL PERU | N222: 0 | O222: =N222*0.18 -> 0 | P222: 0 | R222: 66.8 | S222: 66.8 | AB222: S | AD222: 46099 | AE222: CRE | AF222: 6599095 | AG222: 1413 | AH222: 4212 | AR222: 18 | AS222: POR DERECHO DE EMISION DE PLACA DE RODAJE
A223: 46071 | C223: 01 | D223: 00FN01 | F223: 42647056 | G223: 6 | H223: 20100047218 | I223: =IF(H223="","",VLOOKUP(H223,ENTIDAD!$B$2:$C$613,2,0)) -> BANCO DE CREDITO DEL PERU | N223: =(S223-P223)/1.18 -> 0 | O223: =N223*0.18 -> 0 | P223: 10 | S223: 10 | AB223: S | AD223: 46099 | AE223: CRE | AF223: 6391094 | AH223: 4212 | AR223: 18 | AS223: POR LA COMISION BANCARIA
A224: 46071 | C224: 01 | D224: 00FN01 | F224: 42647089 | G224: 6 | H224: 20100047218 | I224: =IF(H224="","",VLOOKUP(H224,ENTIDAD!$B$2:$C$613,2,0)) -> BANCO DE CREDITO DEL PERU | N224: =(S224-P224)/1.18 -> 0 | O224: =N224*0.18 -> 0 | P224: 10 | S224: 10 | AB224: S | AD224: 46099 | AE224: CRE | AF224: 6391094 | AH224: 4212 | AR224: 18 | AS224: POR LA COMISION BANCARIA
A225: 46071 | C225: 01 | D225: 00F001 | F225: 174 | G225: 6 | H225: 10733892469 | I225: =IF(H225="","",VLOOKUP(H225,ENTIDAD!$B$2:$C$613,2,0)) -> TAIPE AYLLON EMILY MARGORY | N225: =(S225-P225)/1.18 -> 0 | O225: =N225*0.18 -> 0 | P225: 107 | S225: 107 | AB225: S | AD225: 46099 | AE225: CRE | AF225: 656009504 | AH225: 4212 | AR225: 18 | AS225: POR LA COMPRA DE TUBO GALVANIZADO
A226: 46071 | C226: 01 | D226: 00F010 | F226: 4613 | G226: 6 | H226: 20601012261 | I226: =IF(H226="","",VLOOKUP(H226,ENTIDAD!$B$2:$C$613,2,0)) -> IMPORTADORA DE REPUESTOS LA ROCA E.I.R.L. | N226: =(S226-P226)/1.18 -> 0 | O226: =N226*0.18 -> 0 | P226: 52 | S226: 52 | AB226: S | AE226: CON | AF226: 6343095 | AH226: 4212 | AR226: 18 | AS226: POR LA COMPRA DE BATERIA
A227: 46071 | C227: 01 | D227: 00F005 | F227: 16761 | G227: 6 | H227: 20493508645 | I227: =IF(H227="","",VLOOKUP(H227,ENTIDAD!$B$2:$C$613,2,0)) -> HONDA SELVA DEL PERU S.A. | N227: =(S227-P227)/1.18 -> 0.0020338983 | O227: =N227*0.18 -> 0.00036610169 | P227: 9897.69 | S227: =W227*AC227 -> 9897.6924 | W227: 3.348 | AB227: D | AC227: 2956.3 | AD227: 46099 | AE227: CRE | AF227: 6011021 | AH227: 4212 | AR227: 18 | AS227: EXISTENCIAS POR RECIBIR
A228: 46071 | C228: 01 | D228: 00F005 | F228: 16762 | G228: 6 | H228: 20493508645 | I228: =IF(H228="","",VLOOKUP(H228,ENTIDAD!$B$2:$C$613,2,0)) -> HONDA SELVA DEL PERU S.A. | N228: =(S228-P228)/1.18 -> -0.0029491525 | O228: =N228*0.18 -> -0.00053084746 | P228: 8679.66 | S228: =W228*AC228 -> 8679.6565 | W228: 3.348 | AB228: D | AC228: 2592.49 | AD228: 46099 | AE228: CRE | AF228: 6011021 | AH228: 4212 | AR228: 18 | AS228: EXISTENCIAS POR RECIBIR
A229: 46071 | C229: 01 | D229: 00F005 | F229: 16763 | G229: 6 | H229: 20493508645 | I229: =IF(H229="","",VLOOKUP(H229,ENTIDAD!$B$2:$C$613,2,0)) -> HONDA SELVA DEL PERU S.A. | N229: =(S229-P229)/1.18 -> -0.0029491525 | O229: =N229*0.18 -> -0.00053084746 | P229: 8679.66 | S229: =W229*AC229 -> 8679.6565 | W229: 3.348 | AB229: D | AC229: 2592.49 | AD229: 46099 | AE229: CRE | AF229: 6011021 | AH229: 4212 | AR229: 18 | AS229: EXISTENCIAS POR RECIBIR
...

Sheet MARZO
A1: FECHA DE EMISION DEL COMPROBANTE DE PAGO O DOCUMENTO | B1: FECHA DE VENCIMIENTO O FECHA DE PAGO | C1: COMPROBANTE DE PAGO O DOCUMENTO | F1: N° COMPROBANTE PAGO | G1: INFORMACION PROVEEDOR | J1: ADQUISICIONES GRAVADAS DESTINADAS A OPERACIONES GRAVADAS Y/O EXPORTACION | L1: ADQUISICIONES GRAVADAS DESTINADAS A OPERACIONES GRAVADAS Y/O DE EXPORTACION Y A OPERACIONES NO GRAVADAS | N1: ADQUISICIONES GRAVADAS DESTINADAS A OPERACIONES NO GRAVADAS | P1: VALOR DE LAS ADQUISICIONES NO GRAVADAS | Q1: ISC | R1: OTROS TRIBUTOS Y CARGOS | S1: IMPORTE TOTAL | T1: N° COMPROBANTE DE PAGO EMITIDO POR SUJETO NO DOMICILIADO | U1: CONSTANCIA DE DEPOSITO DE DETRACCION | W1: TIPO DE CAMBIO | X1: REFERENCIA DEL COMPROBANTE DE PAGO O DOCUMENTO ORIGINAL QUE SE MODIFICA | AB1: MONEDA | AC1: EQUIVALENTE EN DOLARES AMERICANOS | AD1: FECHA VENCIMIENTO | AE1: CONDICION CONTADO/CREDITO | AF1: CUENTA CONTABLE BASE IMPONIBLE | AG1: CUENTA CONTABLE OTROS TRIBUTOS Y CARGOS | AH1: CUENTA CONTABLE TOTAL | AI1: CODIGO CENTRO DE COSTOS | AJ1: CODIGO CENTRO DE COSTOS 2 | AK1: REGIMEN ESPECIAL | AL1: PORCENTAJE REGIMEN ESPECIAL | AM1: IMPORTE REGIMEN ESPECIAL | AN1: SERIE DOCUMENTO REGIMEN ESPECIAL | AO1: NUMERO DOCUMENTO REGIMEN ESPECIAL | AP1: FECHA DOCUMENTO REGIMEN ESPECIAL | AQ1: CODIGO PRESUPUESTO | AR1: PORCENTAJE I.G.V. | AS1: GLOSA | AT1: CONDICIÓN DE PERCEPCIÓN | AU1: IMPORTE RÉGIMEN ESPECIAL | AV1: CLASIFICACIÓN DE BIENES Y SERVICIOS ADQUIRIDOS
G2: DOCUMENTO IDENTIDAD | I2: APELLIDOS Y NOMBRES, DENOMINACION O RAZON SOCIAL
C3: TIPO | D3: SERIE/CODIGO ADUANA | E3: AÑO EMISION DUA O DSI | G3: TIPO | H3: NUMERO | J3: BASE IMPONIBLE | K3: IGV | L3: BASE IMPONIBLE | M3: IGV | N3: BASE IMPONIBLE | O3: IGV | U3: NUMERO | V3: FECHA EMISION | X3: FECHA | Y3: TIPO | Z3: SERIE | AA3: N° COMPROBANTE PAGO O DOCUMENTO
A4: 46079 | C4: 14 | D4: 00S898 | F4: 5692682 | G4: 6 | H4: 20129646099 | I4: =IF(H4="","",VLOOKUP(H4,ENTIDAD!$B$2:$C$613,2,0)) -> ELECTROCENTRO S.A. | N4: 0 | O4: =N4*0.18 -> 0 | P4: 375.4 | S4: 375.4 | AB4: S | AD4: 46095 | AE4: CRE | AF4: 6361095 | AH4: 4212 | AR4: 18 | AS4: POR EL SERVICIO DE ENERGIA ELECTRICA
A5: 46079 | C5: 14 | D5: 00S898 | F5: 5692906 | G5: 6 | H5: 20129646099 | I5: =IF(H5="","",VLOOKUP(H5,ENTIDAD!$B$2:$C$613,2,0)) -> ELECTROCENTRO S.A. | N5: =(S5-P5)/1.18 -> 0 | O5: =N5*0.18 -> 0 | P5: 484.8 | S5: 484.8 | AB5: S | AD5: 46095 | AE5: CRE | AF5: 6361095 | AH5: 4212 | AR5: 18 | AS5: POR EL SERVICIO DE ENERGIA ELECTRICA
A6: 46079 | C6: 14 | D6: 00S898 | F6: 5692687 | G6: 6 | H6: 20129646099 | I6: =IF(H6="","",VLOOKUP(H6,ENTIDAD!$B$2:$C$613,2,0)) -> ELECTROCENTRO S.A. | N6: 0 | O6: =N6*0.18 -> 0 | P6: 83.2 | S6: 83.2 | AB6: S | AD6: 46095 | AE6: CRE | AF6: 6361095 | AH6: 4212 | AR6: 18 | AS6: POR EL SERVICIO DE ENERGIA ELECTRICA
A7: 46081 | C7: 14 | D7: 00S060 | F7: 1056363 | G7: 6 | H7: 20121876290 | I7: =IF(H7="","",VLOOKUP(H7,ENTIDAD!$B$2:$C$613,2,0)) -> ENT.PREST.SERV.SANEAM.SELVA CENTRAL S.A | N7: 0 | O7: =N7*0.18 -> 0 | P7: 46.8 | S7: 46.8 | AB7: S | AD7: 46112 | AE7: CRE | AF7: 6363095 | AH7: 4212 | AR7: 18 | AS7: POR EL SERVICIO DE AGUA POTABLE
A8: 46081 | C8: 14 | D8: 00S060 | F8: 1057146 | G8: 6 | H8: 20121876290 | I8: =IF(H8="","",VLOOKUP(H8,ENTIDAD!$B$2:$C$613,2,0)) -> ENT.PREST.SERV.SANEAM.SELVA CENTRAL S.A | N8: 0 | O8: =N8*0.18 -> 0 | P8: 46.8 | S8: 46.8 | AB8: S | AD8: 46112 | AE8: CRE | AF8: 6363095 | AH8: 4212 | AR8: 18 | AS8: POR EL SERVICIO DE AGUA POTABLE
A9: 46081 | C9: 14 | D9: 00S060 | F9: 1057941 | G9: 6 | H9: 20121876290 | I9: =IF(H9="","",VLOOKUP(H9,ENTIDAD!$B$2:$C$613,2,0)) -> ENT.PREST.SERV.SANEAM.SELVA CENTRAL S.A | N9: =(S9-P9)/1.18 -> 0 | O9: =N9*0.18 -> 0 | P9: 39.4 | S9: 39.4 | AB9: S | AD9: 46112 | AE9: CRE | AF9: 6363095 | AH9: 4212 | AR9: 18 | AS9: POR EL SERVICIO DE AGUA POTABLE
A10: 46082 | C10: 14 | D10: 00SB01 | F10: 608275570 | G10: 6 | H10: 20467534026 | I10: =IF(H10="","",VLOOKUP(H10,ENTIDAD!$B$2:$C$613,2,0)) -> AMERICA MOVIL PERU S.A.C. | N10: =(S10-P10)/1.18 -> 75.423729 | O10: =N10*0.18 -> 13.576271 | P10: 0 | S10: 89 | AB10: S | AD10: 46100 | AE10: CRE | AF10: 6365095 | AH10: 4212 | AR10: 18 | AS10: POR EL SERVICIO DE INTERNET
A11: 46083 | C11: 01 | D11: 00E001 | F11: 1805 | G11: 6 | H11: 20486339510 | I11: =IF(H11="","",VLOOKUP(H11,ENTIDAD!$B$2:$C$613,2,0)) -> SERVICIOS CONTABLES Y AUDITORIA INTERNA S.A. | N11: =(S11-P11)/1.18 -> 1694.9153 | O11: =N11*0.18 -> 305.08475 | P11: 0 | S11: 2000 | AB11: S | AD11: 46114 | AE11: CRE | AF11: 6323094 | AH11: 4212 | AR11: 18 | AS11: SERVICIO CONTABLE
A12: 46083 | C12: 01 | D12: 00E001 | F12: 174 | G12: 6 | H12: 10447422951 | I12: =IF(H12="","",VLOOKUP(H12,ENTIDAD!$B$2:$C$613,2,0)) -> ZEGARRA AZAÑERO JORGE KEY | N12: =(S12-P12)/1.18 -> 0 | O12: =N12*0.18 -> 0 | P12: 450 | S12: 450 | AB12: S | AD12: 46114 | AE12: CRE | AF12: 6329094 | AH12: 4212 | AR12: 18 | AS12: SOPORTE TECNICO
A13: 46083 | C13: 01 | D13: 00FB26 | F13: 26256669 | G13: 6 | H13: 20100130204 | I13: =IF(H13="","",VLOOKUP(H13,ENTIDAD!$B$2:$C$613,2,0)) -> BANCO BBVA PERU | N13: =(S13-P13)/1.18 -> 0 | O13: =N13*0.18 -> 0 | P13: 10 | S13: 10 | AB13: S | AD13: 46114 | AE13: CRE | AF13: 6391094 | AH13: 4212 | AR13: 18 | AS13: POR LA COMISION BANCARIA
A14: 46084 | C14: 01 | D14: 00F011 | F14: 880 | G14: 6 | H14: 20601012261 | I14: =IF(H14="","",VLOOKUP(H14,ENTIDAD!$B$2:$C$613,2,0)) -> IMPORTADORA DE REPUESTOS LA ROCA E.I.R.L. | N14: =(S14-P14)/1.18 -> 0 | O14: =N14*0.18 -> 0 | P14: 50 | S14: 50 | AB14: S | AE14: CON | AF14: 6360095 | AH14: 4212 | AR14: 18 | AS14: BATERIA
A15: 46084 | C15: 01 | D15: 00FC04 | F15: 4872628 | G15: 6 | H15: 20100130204 | I15: =IF(H15="","",VLOOKUP(H15,ENTIDAD!$B$2:$C$613,2,0)) -> BANCO BBVA PERU | N15: =(S15-P15)/1.18 -> 0 | O15: =N15*0.18 -> 0 | P15: 40 | S15: 40 | AB15: S | AD15: 46115 | AE15: CRE | AF15: 6391094 | AH15: 4212 | AR15: 18 | AS15: POR LA COMISION BANCARIA
A16: 46084 | C16: 01 | D16: 00F001 | F16: 5209 | G16: 6 | H16: 10061702071 | I16: =IF(H16="","",VLOOKUP(H16,ENTIDAD!$B$2:$C$613,2,0)) -> CORAL FLORES IVAN MARTIN | N16: =(S16-P16)/1.18 -> 0 | O16: =N16*0.18 -> 0 | P16: 190 | S16: 190 | AB16: S | AD16: 46115 | AE16: CRE | AF16: 6599095 | AG16: 1413 | AH16: 4212 | AR16: 18 | AS16: POR EL SERVICIO DE LEGALIZACION
A17: 46084 | C17: 01 | D17: 00F001 | F17: 5208 | G17: 6 | H17: 10061702071 | I17: =IF(H17="","",VLOOKUP(H17,ENTIDAD!$B$2:$C$613,2,0)) -> CORAL FLORES IVAN MARTIN | N17: 0 | O17: =N17*0.18 -> 0 | P17: 150 | S17: 150 | AB17: S | AD17: 46115 | AE17: CRE | AF17: 6599095 | AG17: 1413 | AH17: 4212 | AR17: 18 | AS17: POR EL SERVICIO DE LEGALIZACION
A18: 46085 | C18: 01 | D18: 00F003 | F18: 3712044 | G18: 6 | H18: 20101973922 | I18: =IF(H18="","",VLOOKUP(H18,ENTIDAD!$B$2:$C$613,2,0)) -> ASOCIACION AUTOMOTRIZ DEL PERU | N18: 0 | O18: =N18*0.18 -> 0 | P18: 0 | R18: 66.8 | S18: 66.8 | AB18: S | AD18: 46116 | AE18: CRE | AF18: 6599095 | AG18: 1413 | AH18: 4212 | AR18: 18 | AS18: POR DERECHO DE EMISION DE PLACA DE RODAJE
A19: 46085 | C19: 01 | D19: 00F003 | F19: 3712045 | G19: 6 | H19: 20101973922 | I19: =IF(H19="","",VLOOKUP(H19,ENTIDAD!$B$2:$C$613,2,0)) -> ASOCIACION AUTOMOTRIZ DEL PERU | N19: 0 | O19: =N19*0.18 -> 0 | P19: 0 | R19: 66.8 | S19: 66.8 | AB19: S | AD19: 46116 | AE19: CRE | AF19: 6599095 | AG19: 1413 | AH19: 4212 | AR19: 18 | AS19: POR DERECHO DE EMISION DE PLACA DE RODAJE
A20: 46085 | C20: 01 | D20: 00F003 | F20: 3712046 | G20: 6 | H20: 20101973922 | I20: =IF(H20="","",VLOOKUP(H20,ENTIDAD!$B$2:$C$613,2,0)) -> ASOCIACION AUTOMOTRIZ DEL PERU | N20: 0 | O20: =N20*0.18 -> 0 | P20: 0 | R20: 66.8 | S20: 66.8 | AB20: S | AD20: 46116 | AE20: CRE | AF20: 6599095 | AG20: 1413 | AH20: 4212 | AR20: 18 | AS20: POR DERECHO DE EMISION DE PLACA DE RODAJE
A21: 46085 | C21: 01 | D21: 00F003 | F21: 3712047 | G21: 6 | H21: 20101973922 | I21: =IF(H21="","",VLOOKUP(H21,ENTIDAD!$B$2:$C$613,2,0)) -> ASOCIACION AUTOMOTRIZ DEL PERU | N21: 0 | O21: =N21*0.18 -> 0 | P21: 0 | R21: 66.8 | S21: 66.8 | AB21: S | AD21: 46116 | AE21: CRE | AF21: 6599095 | AG21: 1413 | AH21: 4212 | AR21: 18 | AS21: POR DERECHO DE EMISION DE PLACA DE RODAJE
A22: 46085 | C22: 01 | D22: 00F003 | F22: 3712048 | G22: 6 | H22: 20101973922 | I22: =IF(H22="","",VLOOKUP(H22,ENTIDAD!$B$2:$C$613,2,0)) -> ASOCIACION AUTOMOTRIZ DEL PERU | N22: 0 | O22: =N22*0.18 -> 0 | P22: 0 | R22: 66.8 | S22: 66.8 | AB22: S | AD22: 46116 | AE22: CRE | AF22: 6599095 | AG22: 1413 | AH22: 4212 | AR22: 18 | AS22: POR DERECHO DE EMISION DE PLACA DE RODAJE
A23: 46085 | C23: 01 | D23: 00F003 | F23: 3712049 | G23: 6 | H23: 20101973922 | I23: =IF(H23="","",VLOOKUP(H23,ENTIDAD!$B$2:$C$613,2,0)) -> ASOCIACION AUTOMOTRIZ DEL PERU | N23: 0 | O23: =N23*0.18 -> 0 | P23: 0 | R23: 66.8 | S23: 66.8 | AB23: S | AD23: 46116 | AE23: CRE | AF23: 6599095 | AG23: 1413 | AH23: 4212 | AR23: 18 | AS23: POR DERECHO DE EMISION DE PLACA DE RODAJE
A24: 46085 | C24: 01 | D24: 00F003 | F24: 3712050 | G24: 6 | H24: 20101973922 | I24: =IF(H24="","",VLOOKUP(H24,ENTIDAD!$B$2:$C$613,2,0)) -> ASOCIACION AUTOMOTRIZ DEL PERU | N24: 0 | O24: =N24*0.18 -> 0 | P24: 0 | R24: 66.8 | S24: 66.8 | AB24: S | AD24: 46116 | AE24: CRE | AF24: 6599095 | AG24: 1413 | AH24: 4212 | AR24: 18 | AS24: POR DERECHO DE EMISION DE PLACA DE RODAJE
A25: 46085 | C25: 01 | D25: 00F003 | F25: 3712051 | G25: 6 | H25: 20101973922 | I25: =IF(H25="","",VLOOKUP(H25,ENTIDAD!$B$2:$C$613,2,0)) -> ASOCIACION AUTOMOTRIZ DEL PERU | N25: 0 | O25: =N25*0.18 -> 0 | P25: 0 | R25: 66.8 | S25: 66.8 | AB25: S | AD25: 46116 | AE25: CRE | AF25: 6599095 | AG25: 1413 | AH25: 4212 | AR25: 18 | AS25: POR DERECHO DE EMISION DE PLACA DE RODAJE
A26: 46085 | C26: 04893713 | D26: 00F003 | F26: 3712052 | G26: 6 | H26: 20101973922 | I26: =IF(H26="","",VLOOKUP(H26,ENTIDAD!$B$2:$C$613,2,0)) -> ASOCIACION AUTOMOTRIZ DEL PERU | N26: 0 | O26: =N26*0.18 -> 0 | P26: 0 | R26: 66.8 | S26: 66.8 | AB26: S | AD26: 46116 | AE26: CRE | AF26: 6599095 | AG26: 1413 | AH26: 4212 | AR26: 18 | AS26: POR DERECHO DE EMISION DE PLACA DE RODAJE
A27: 46085 | C27: 01 | D27: 00F003 | F27: 3712053 | G27: 6 | H27: 20101973922 | I27: =IF(H27="","",VLOOKUP(H27,ENTIDAD!$B$2:$C$613,2,0)) -> ASOCIACION AUTOMOTRIZ DEL PERU | N27: 0 | O27: =N27*0.18 -> 0 | P27: 0 | R27: 66.8 | S27: 66.8 | AB27: S | AD27: 46116 | AE27: CRE | AF27: 6599095 | AG27: 1413 | AH27: 4212 | AR27: 18 | AS27: POR DERECHO DE EMISION DE PLACA DE RODAJE
A28: 46085 | C28: 01 | D28: 00F003 | F28: 3712054 | G28: 6 | H28: 20101973922 | I28: =IF(H28="","",VLOOKUP(H28,ENTIDAD!$B$2:$C$613,2,0)) -> ASOCIACION AUTOMOTRIZ DEL PERU | N28: 0 | O28: =N28*0.18 -> 0 | P28: 0 | R28: 66.8 | S28: 66.8 | AB28: S | AD28: 46116 | AE28: CRE | AF28: 6599095 | AG28: 1413 | AH28: 4212 | AR28: 18 | AS28: POR DERECHO DE EMISION DE PLACA DE RODAJE
A29: 46085 | C29: 01 | D29: 00F003 | F29: 3712055 | G29: 6 | H29: 20101973922 | I29: =IF(H29="","",VLOOKUP(H29,ENTIDAD!$B$2:$C$613,2,0)) -> ASOCIACION AUTOMOTRIZ DEL PERU | N29: 0 | O29: =N29*0.18 -> 0 | P29: 0 | R29: 66.8 | S29: 66.8 | AB29: S | AD29: 46116 | AE29: CRE | AF29: 6599095 | AG29: 1413 | AH29: 4212 | AR29: 18 | AS29: POR DERECHO DE EMISION DE PLACA DE RODAJE
... A37: 46085 | C37: 01 | D37: 00F003 | F37: 3712063 | G37: 6 | H37: 20101973922 | I37: =IF(H37="","",VLOOKUP(H37,ENTIDAD!$B$2:$C$613,2,0)) -> ASOCIACION AUTOMOTRIZ DEL PERU | N37: 0 | O37: =N37*0.18 -> 0 | P37: 0 | R37: 66.8 | S37: 66.8 | AB37: S | AD37: 46116 | AE37: CRE | AF37: 6599095 | AG37: 1413 | AH37: 4212 | AR37: 18 | AS37: POR DERECHO DE EMISION DE PLACA DE RODAJE
A38: 46086 | C38: 01 | D38: 00FV19 | F38: 1325589 | G38: 6 | H38: 20100047218 | I38: =IF(H38="","",VLOOKUP(H38,ENTIDAD!$B$2:$C$613,2,0)) -> BANCO DE CREDITO DEL PERU | N38: =(S38-P38)/1.18 -> 0 | O38: =N38*0.18 -> 0 | P38: 143.5 | S38: 143.5 | AB38: S | AE38: CON | AH38: 4212 | AR38: 18
A39: 46086 | C39: 01 | D39: 00F001 | F39: 274 | G39: 6 | H39: 20613928830 | I39: =IF(H39="","",VLOOKUP(H39,ENTIDAD!$B$2:$C$613,2,0)) -> EE.SS. TORRES EMPRESA INDIVIDUAL DE RESPONSABILIDAD LIMITADA | N39: =(S39-P39)/1.18 -> 0 | O39: =N39*0.18 -> 0 | P39: 10 | S39: 10 | AB39: S | AE39: CON | AF39: 656009501 | AH39: 4212 | AR39: 18 | AS39: POR LA COMPRA DE COMBUSTIBLE
A40: 46087 | C40: 01 | D40: 00FE01 | F40: 2766087 | G40: 6 | H40: 20100047218 | I40: =IF(H40="","",VLOOKUP(H40,ENTIDAD!$B$2:$C$613,2,0)) -> BANCO DE CREDITO DEL PERU | N40: =(S40-P40)/1.18 -> 0 | O40: =N40*0.18 -> 0 | P40: 120.12 | S40: =W40*AC40 -> 120.12 | W40: 3.432 | AB40: D | AC40: 35 | AD40: 46118 | AE40: CRE | AF40: 6391094 | AH40: 4212 | AR40: 18 | AS40: POR LA COMISION BANCARIA
A41: 46088 | C41: 01 | D41: 00FI01 | F41: 18900536 | G41: 6 | H41: 20100047218 | I41: =IF(H41="","",VLOOKUP(H41,ENTIDAD!$B$2:$C$613,2,0)) -> BANCO DE CREDITO DEL PERU | N41: =(S41-P41)/1.18 -> 0 | O41: =N41*0.18 -> 0 | P41: 566.5 | S41: 566.5 | AB41: S | AD41: 46119 | AE41: CRE | AF41: 6391094 | AH41: 4212 | AR41: 18 | AS41: POR LA COMISION BANCARIA
A42: 46088 | C42: 01 | D42: 00F003 | F42: 3719364 | G42: 6 | H42: 20101973922 | I42: =IF(H42="","",VLOOKUP(H42,ENTIDAD!$B$2:$C$613,2,0)) -> ASOCIACION AUTOMOTRIZ DEL PERU | N42: 0 | O42: =N42*0.18 -> 0 | P42: 0 | R42: 66.8 | S42: 66.8 | AB42: S | AD42: 46119 | AE42: CRE | AF42: 6599095 | AG42: 1413 | AH42: 4212 | AR42: 18 | AS42: POR DERECHO DE EMISION DE PLACA DE RODAJE
A43: 46088 | C43: 01 | D43: 00F003 | F43: 3719365 | G43: 6 | H43: 20101973922 | I43: =IF(H43="","",VLOOKUP(H43,ENTIDAD!$B$2:$C$613,2,0)) -> ASOCIACION AUTOMOTRIZ DEL PERU | N43: 0 | O43: =N43*0.18 -> 0 | P43: 0 | R43: 66.8 | S43: 66.8 | AB43: S | AD43: 46119 | AE43: CRE | AF43: 6599095 | AG43: 1413 | AH43: 4212 | AR43: 18 | AS43: POR DERECHO DE EMISION DE PLACA DE RODAJE
A44: 46088 | C44: 01 | D44: 00F003 | F44: 3719366 | G44: 6 | H44: 20101973922 | I44: =IF(H44="","",VLOOKUP(H44,ENTIDAD!$B$2:$C$613,2,0)) -> ASOCIACION AUTOMOTRIZ DEL PERU | N44: 0 | O44: =N44*0.18 -> 0 | P44: 0 | R44: 66.8 | S44: 66.8 | AB44: S | AD44: 46119 | AE44: CRE | AF44: 6599095 | AG44: 1413 | AH44: 4212 | AR44: 18 | AS44: POR DERECHO DE EMISION DE PLACA DE RODAJE
A45: 46088 | C45: 01 | D45: 00F003 | F45: 3719367 | G45: 6 | H45: 20101973922 | I45: =IF(H45="","",VLOOKUP(H45,ENTIDAD!$B$2:$C$613,2,0)) -> ASOCIACION AUTOMOTRIZ DEL PERU | N45: 0 | O45: =N45*0.18 -> 0 | P45: 0 | R45: 66.8 | S45: 66.8 | AB45: S | AD45: 46119 | AE45: CRE | AF45: 6599095 | AG45: 1413 | AH45: 4212 | AR45: 18 | AS45: POR DERECHO DE EMISION DE PLACA DE RODAJE
A46: 46088 | C46: 01 | D46: 00F003 | F46: 3719368 | G46: 6 | H46: 20101973922 | I46: =IF(H46="","",VLOOKUP(H46,ENTIDAD!$B$2:$C$613,2,0)) -> ASOCIACION AUTOMOTRIZ DEL PERU | N46: 0 | O46: =N46*0.18 -> 0 | P46: 0 | R46: 66.8 | S46: 66.8 | AB46: S | AD46: 46119 | AE46: CRE | AF46: 6599095 | AG46: 1413 | AH46: 4212 | AR46: 18 | AS46: POR DERECHO DE EMISION DE PLACA DE RODAJE
A47: 46088 | C47: 01 | D47: 00F003 | F47: 3719369 | G47: 6 | H47: 20101973922 | I47: =IF(H47="","",VLOOKUP(H47,ENTIDAD!$B$2:$C$613,2,0)) -> ASOCIACION AUTOMOTRIZ DEL PERU | N47: 0 | O47: =N47*0.18 -> 0 | P47: 0 | R47: 66.8 | S47: 66.8 | AB47: S | AD47: 46119 | AE47: CRE | AF47: 6599095 | AG47: 1413 | AH47: 4212 | AR47: 18 | AS47: POR DERECHO DE EMISION DE PLACA DE RODAJE
A48: 46088 | C48: 01 | D48: 00F003 | F48: 3719370 | G48: 6 | H48: 20101973922 | I48: =IF(H48="","",VLOOKUP(H48,ENTIDAD!$B$2:$C$613,2,0)) -> ASOCIACION AUTOMOTRIZ DEL PERU | N48: 0 | O48: =N48*0.18 -> 0 | P48: 0 | R48: 66.8 | S48: 66.8 | AB48: S | AD48: 46119 | AE48: CRE | AF48: 6599095 | AG48: 1413 | AH48: 4212 | AR48: 18 | AS48: POR DERECHO DE EMISION DE PLACA DE RODAJE
A49: 46088 | C49: 01 | D49: 00F003 | F49: 3719371 | G49: 6 | H49: 20101973922 | I49: =IF(H49="","",VLOOKUP(H49,ENTIDAD!$B$2:$C$613,2,0)) -> ASOCIACION AUTOMOTRIZ DEL PERU | N49: 0 | O49: =N49*0.18 -> 0 | P49: 0 | R49: 66.8 | S49: 66.8 | AB49: S | AD49: 46119 | AE49: CRE | AF49: 6599095 | AG49: 1413 | AH49: 4212 | AR49: 18 | AS49: POR DERECHO DE EMISION DE PLACA DE RODAJE
A50: 46088 | C50: 01 | D50: 00F003 | F50: 3719372 | G50: 6 | H50: 20101973922 | I50: =IF(H50="","",VLOOKUP(H50,ENTIDAD!$B$2:$C$613,2,0)) -> ASOCIACION AUTOMOTRIZ DEL PERU | N50: 0 | O50: =N50*0.18 -> 0 | P50: 0 | R50: 66.8 | S50: 66.8 | AB50: S | AD50: 46119 | AE50: CRE | AF50: 6599095 | AG50: 1413 | AH50: 4212 | AR50: 18 | AS50: POR DERECHO DE EMISION DE PLACA DE RODAJE
A51: 46088 | C51: 01 | D51: 00F003 | F51: 3719373 | G51: 6 | H51: 20101973922 | I51: =IF(H51="","",VLOOKUP(H51,ENTIDAD!$B$2:$C$613,2,0)) -> ASOCIACION AUTOMOTRIZ DEL PERU | N51: 0 | O51: =N51*0.18 -> 0 | P51: 0 | R51: 66.8 | S51: 66.8 | AB51: S | AD51: 46119 | AE51: CRE | AF51: 6599095 | AG51: 1413 | AH51: 4212 | AR51: 18 | AS51: POR DERECHO DE EMISION DE PLACA DE RODAJE
A52: 46088 | C52: 01 | D52: 00F003 | F52: 3719374 | G52: 6 | H52: 20101973922 | I52: =IF(H52="","",VLOOKUP(H52,ENTIDAD!$B$2:$C$613,2,0)) -> ASOCIACION AUTOMOTRIZ DEL PERU | N52: 0 | O52: =N52*0.18 -> 0 | P52: 0 | R52: 66.8 | S52: 66.8 | AB52: S | AD52: 46119 | AE52: CRE | AF52: 6599095 | AG52: 1413 | AH52: 4212 | AR52: 18 | AS52: POR DERECHO DE EMISION DE PLACA DE RODAJE
A53: 46088 | C53: 01 | D53: 00F003 | F53: 3719375 | G53: 6 | H53: 20101973922 | I53: =IF(H53="","",VLOOKUP(H53,ENTIDAD!$B$2:$C$613,2,0)) -> ASOCIACION AUTOMOTRIZ DEL PERU | N53: 0 | O53: =N53*0.18 -> 0 | P53: 0 | R53: 66.8 | S53: 66.8 | AB53: S | AD53: 46119 | AE53: CRE | AF53: 6599095 | AG53: 1413 | AH53: 4212 | AR53: 18 | AS53: POR DERECHO DE EMISION DE PLACA DE RODAJE
... A66: 46088 | C66: 01 | D66: 00F003 | F66: 3719388 | G66: 6 | H66: 20101973922 | I66: =IF(H66="","",VLOOKUP(H66,ENTIDAD!$B$2:$C$613,2,0)) -> ASOCIACION AUTOMOTRIZ DEL PERU | N66: 0 | O66: =N66*0.18 -> 0 | P66: 0 | R66: 66.8 | S66: 66.8 | AB66: S | AD66: 46119 | AE66: CRE | AF66: 6599095 | AG66: 1413 | AH66: 4212 | AR66: 18 | AS66: POR DERECHO DE EMISION DE PLACA DE RODAJE
A67: 46090 | C67: 01 | D67: 00F002 | F67: 136 | G67: 6 | H67: 20600454065 | I67: =IF(H67="","",VLOOKUP(H67,ENTIDAD!$B$2:$C$613,2,0)) -> REPUESTOS Y SERVICIOS ARAUCO E.I.R.L. | N67: 0 | O67: =N67*0.18 -> 0 | P67: 1825 | S67: 1825 | AB67: S | AD67: 46121 | AE67: CRE | AF67: 6343095 | AH67: 4212 | AR67: 18 | AS67: MANTENIMIENTO DE MOTOS VENDIDAS - GARANTIA
A68: 46092 | C68: 01 | D68: 00F001 | F68: 5224 | G68: 6 | H68: 10061702071 | I68: =IF(H68="","",VLOOKUP(H68,ENTIDAD!$B$2:$C$613,2,0)) -> CORAL FLORES IVAN MARTIN | N68: =(S68-P68)/1.18 -> 0 | O68: =N68*0.18 -> 0 | P68: 280 | S68: 280 | AB68: S | AD68: 46123 | AE68: CRE | AF68: 6599095 | AG68: 1413 | AH68: 4212 | AR68: 18 | AS68: POR EL SERVICIO DE LEGALIZACION
A69: 46092 | C69: 01 | D69: 00E001 | F69: 251 | G69: 6 | H69: 10434454501 | I69: =IF(H69="","",VLOOKUP(H69,ENTIDAD!$B$2:$C$613,2,0)) -> PEREZ MARTICORENA LEO DAN | N69: =(S69-P69)/1.18 -> 0 | O69: =N69*0.18 -> 0 | P69: 170 | S69: 170 | AB69: S | AE69: CON | AF69: 656009506 | AH69: 4212 | AR69: 18 | AS69: POR LA IMPRESIÓN DE FOTOCHECK
A70: 46092 | C70: 01 | D70: 00F005 | F70: 17193 | G70: 6 | H70: 20493508645 | I70: =IF(H70="","",VLOOKUP(H70,ENTIDAD!$B$2:$C$613,2,0)) -> HONDA SELVA DEL PERU S.A. | N70: =(S70-P70)/1.18 -> 0.0013305085 | O70: =N70*0.18 -> 0.00023949153 | P70: 47244.43 | S70: =W70*AC70 -> 47244.432 | W70: 3.451 | AB70: D | AC70: 13690.07 | AD70: 46123 | AE70: CRE | AF70: 6011021 | AH70: 4212 | AR70: 18 | AS70: EXISTENCIAS POR RECIBIR
A71: 46092 | C71: 01 | D71: 00E001 | F71: 6053 | G71: 6 | H71: 20602783341 | I71: =IF(H71="","",VLOOKUP(H71,ENTIDAD!$B$2:$C$613,2,0)) -> CODISSER VRAEM E.I.R.L. | N71: =(S71-P71)/1.18 -> 0 | O71: =N71*0.18 -> 0 | P71: 8 | S71: 8 | AB71: S | AE71: CON | AF71: 6250095 | AH71: 4212 | AR71: 18 | AS71: POR LA COMPRA DE AGUA MESA
A72: 46093 | C72: 01 | D72: 00F001 | F72: 12640 | G72: 6 | H72: 10209907327 | I72: =IF(H72="","",VLOOKUP(H72,ENTIDAD!$B$2:$C$613,2,0)) -> TORPOCO,MAYTA,HECTOR,ALFONSO | N72: =(S72-P72)/1.18 -> 0 | O72: =N72*0.18 -> 0 | P72: 10 | S72: 10 | AB72: S | AE72: CON | AF72: 656009501 | AH72: 4212 | AR72: 18 | AS72: POR LA COMPRA DE COMBUSTIBLE
A73: 46093 | C73: 01 | D73: 00E001 | F73: 1271 | G73: 6 | H73: 20485903811 | I73: =IF(H73="","",VLOOKUP(H73,ENTIDAD!$B$2:$C$613,2,0)) -> EMPRESA DE TRANSPORTES ECO TURISTICO SA | N73: 0 | O73: =N73*0.18 -> 0 | P73: 40 | S73: 40 | AB73: S | AD73: 46124 | AE73: CRE | AF73: 6599095 | AG73: 1413 | AH73: 4212 | AR73: 18 | AS73: POR EL SERVICIO DE TRANSPORTE DE PASAJERO
A74: 46093 | C74: 01 | D74: 00F008 | F74: 11074 | G74: 6 | H74: 20485981536 | I74: =IF(H74="","",VLOOKUP(H74,ENTIDAD!$B$2:$C$613,2,0)) -> EMPRESA DE TRANSPORTES TURISMO Y SERVICIOS MULTIPLES SHIMA E.I.R.L. | N74: 0 | O74: =N74*0.18 -> 0 | P74: 40 | S74: 40 | AB74: S | AD74: 46124 | AE74: CRE | AF74: 6599095 | AG74: 1413 | AH74: 4212 | AR74: 18 | AS74: POR EL SERVICIO DE TRANSPORTE DE PASAJERO
A75: 46094 | C75: 01 | D75: 00F005 | F75: 17241 | G75: 6 | H75: 20493508645 | I75: =IF(H75="","",VLOOKUP(H75,ENTIDAD!$B$2:$C$613,2,0)) -> HONDA SELVA DEL PERU S.A. | N75: =(S75-P75)/1.18 -> -0.0010338983 | O75: =N75*0.18 -> -0.0001861017 | P75: 22384.77 | S75: =W75*AC75 -> 22384.769 | W75: 3.449 | AB75: D | AC75: 6490.22 | AD75: 46125 | AE75: CRE | AF75: 6011021 | AH75: 4212 | AR75: 18 | AS75: EXISTENCIAS POR RECIBIR
A76: 46094 | C76: 01 | D76: 00F005 | F76: 17240 | G76: 6 | H76: 20493508645 | I76: =IF(H76="","",VLOOKUP(H76,ENTIDAD!$B$2:$C$613,2,0)) -> HONDA SELVA DEL PERU S.A. | N76: =(S76-P76)/1.18 -> -0.00027118644 | O76: =N76*0.18 -> -4.881356e-05 | P76: 26813.63 | S76: =W76*AC76 -> 26813.63 | W76: 3.449 | AB76: D | AC76: 7774.32 | AD76: 46125 | AE76: CRE | AF76: 6011021 | AH76: 4212 | AR76: 18 | AS76: EXISTENCIAS POR RECIBIR
A77: 46095 | C77: 01 | D77: 00FFF1 | F77: 97 | G77: 6 | H77: 20611975491 | I77: =IF(H77="","",VLOOKUP(H77,ENTIDAD!$B$2:$C$613,2,0)) -> GRUPO VTA S.A.C. | N77: =(S77-P77)/1.18 -> 0 | O77: =N77*0.18 -> 0 | P77: 120 | S77: 120 | AB77: S | AD77: 46126 | AE77: CRE | AF77: 6343094 | AH77: 4212 | AR77: 18 | AS77: REVISION TECNICA
A78: 46095 | C78: 01 | D78: 00F809 | F78: 507880 | G78: 6 | H78: 20100210909 | I78: =IF(H78="","",VLOOKUP(H78,ENTIDAD!$B$2:$C$613,2,0)) -> LA POSITIVA SEGUROS Y REASEGUROS S.A.A. | N78: =(S78-P78)/1.18 -> 144.0678 | O78: =N78*0.18 -> 25.932203 | P78: 0 | S78: 170 | AB78: S | AD78: 46126 | AE78: CRE | AH78: 4212 | AR78: 18
A79: 46097 | C79: 01 | D79: 00F001 | F79: 6123 | G79: 6 | H79: 20486549328 | I79: =IF(H79="","",VLOOKUP(H79,ENTIDAD!$B$2:$C$613,2,0)) -> SANTISIMA TRINIDAD E.I.R.L. | N79: =(S79-P79)/1.18 -> 0 | O79: =N79*0.18 -> 0 | P79: 15 | S79: 15 | AB79: S | AD79: 46128 | AE79: CRE | AF79: 656009503 | AH79: 4212 | AR79: 18 | AS79: CINTA DE EMBALAJE
A80: 46097 | C80: 01 | D80: 00F001 | F80: 685 | G80: 6 | H80: 10733910921 | I80: =IF(H80="","",VLOOKUP(H80,ENTIDAD!$B$2:$C$613,2,0)) -> MADUEÑO HUAMAN LILI CLISSELY | N80: =(S80-P80)/1.18 -> 0 | O80: =N80*0.18 -> 0 | P80: 10 | S80: 10 | AB80: S | AE80: CON | AF80: 6360095 | AH80: 4212 | AR80: 18 | AS80: LLAVE MIXTA
A81: 46097 | C81: 01 | D81: 00F001 | F81: 683 | G81: 6 | H81: 10733910921 | I81: =IF(H81="","",VLOOKUP(H81,ENTIDAD!$B$2:$C$613,2,0)) -> MADUEÑO HUAMAN LILI CLISSELY | N81: =(S81-P81)/1.18 -> 0 | O81: =N81*0.18 -> 0 | P81: 7 | S81: 7 | AB81: S | AE81: CON | AF81: 6360095 | AH81: 4212 | AR81: 18 | AS81: CUTER
A82: 46097 | C82: 01 | D82: 00F001 | F82: 118245 | G82: 6 | H82: 20568499043 | I82: =IF(H82="","",VLOOKUP(H82,ENTIDAD!$B$2:$C$613,2,0)) -> SURTIDORES SAN MIGUEL E.I.R.L. | N82: =(S82-P82)/1.18 -> 0 | O82: =N82*0.18 -> 0 | P82: 100 | S82: 100 | AB82: S | AE82: CON | AF82: 656009401 | AH82: 4212 | AR82: 18 | AS82: POR LA COMPRA DE COMBUSTIBLE
A83: 46099 | C83: 01 | D83: 00F001 | F83: 32572 | G83: 6 | H83: 20573866909 | I83: =IF(H83="","",VLOOKUP(H83,ENTIDAD!$B$2:$C$613,2,0)) -> ESTACION DE SERVICIOS GASOCENTRO MISABEL E.I.R.L. | N83: =(S83-P83)/1.18 -> 0 | O83: =N83*0.18 -> 0 | P83: 10 | S83: 10 | AB83: S | AE83: CON | AF83: 656009501 | AH83: 4212 | AR83: 18 | AS83: POR LA COMPRA DE COMBUSTIBLE
A84: 46099 | C84: 01 | D84: 00F005 | F84: 556 | G84: 6 | H84: 20602109225 | I84: =IF(H84="","",VLOOKUP(H84,ENTIDAD!$B$2:$C$613,2,0)) -> SISTEMA ECOLÓGICO INTEGRAL DE TECNOLOGÍAS E INFORMÁTICA SOCIEDAD ANONIMA CERRADA - ECO SITI S.A.C. | N84: =(S84-P84)/1.18 -> 0 | O84: =N84*0.18 -> 0 | P84: 119.7 | S84: 119.7 | AB84: S | AE84: CON | AF84: 6364095 | AH84: 4212 | AR84: 18 | AS84: POR EL SERVICIO DE LLAMADAS
A85: 46099 | C85: 01 | D85: 00F005 | F85: 17300 | G85: 6 | H85: 20493508645 | I85: =IF(H85="","",VLOOKUP(H85,ENTIDAD!$B$2:$C$613,2,0)) -> HONDA SELVA DEL PERU S.A. | N85: =(S85-P85)/1.18 -> 0.002838983 | O85: =N85*0.18 -> 0.00051101695 | P85: 64931.71 | S85: =W85*AC85 -> 64931.713 | W85: 3.417 | AB85: D | AC85: 19002.55 | AD85: 46130 | AE85: CRE | AF85: 6011021 | AH85: 4212 | AR85: 18 | AS85: EXISTENCIAS POR RECIBIR
A86: 46099 | C86: 01 | D86: 00FN01 | F86: 44001063 | G86: 6 | H86: 20100047218 | I86: =IF(H86="","",VLOOKUP(H86,ENTIDAD!$B$2:$C$613,2,0)) -> BANCO DE CREDITO DEL PERU | N86: =(S86-P86)/1.18 -> 0 | O86: =N86*0.18 -> 0 | P86: 10 | S86: 10 | AB86: S | AD86: 46130 | AE86: CRE | AF86: 6391094 | AH86: 4212 | AR86: 18 | AS86: POR LA COMISION BANCARIA
A87: 46099 | C87: 01 | D87: 00FN01 | F87: 44001163 | G87: 6 | H87: 20100047218 | I87: =IF(H87="","",VLOOKUP(H87,ENTIDAD!$B$2:$C$613,2,0)) -> BANCO DE CREDITO DEL PERU | N87: 0 | O87: =N87*0.18 -> 0 | P87: 10 | S87: 10 | AB87: S | AD87: 46130 | AE87: CRE | AF87: 6391094 | AH87: 4212 | AR87: 18 | AS87: POR LA COMISION BANCARIA
A88: 46100 | C88: 01 | D88: 00FF01 | F88: 218 | G88: 6 | H88: 10421947665 | I88: =IF(H88="","",VLOOKUP(H88,ENTIDAD!$B$2:$C$613,2,0)) -> MAYTA,MADUEÑO,SAUL,JESUS | N88: =(S88-P88)/1.18 -> 0 | O88: =N88*0.18 -> 0 | P88: 45 | S88: 45 | AB88: S | AE88: CON | AF88: 656009502 | AH88: 4212 | AR88: 18 | AS88: POR LA COMPRA DE ARTICULOS DE LIMPIEZA
A89: 46100 | C89: 01 | D89: 00F005 | F89: 17318 | G89: 6 | H89: 20493508645 | I89: =IF(H89="","",VLOOKUP(H89,ENTIDAD!$B$2:$C$613,2,0)) -> HONDA SELVA DEL PERU S.A. | N89: =(S89-P89)/1.18 -> 0.001779661 | O89: =N89*0.18 -> 0.00032033898 | P89: 16720.41 | S89: =W89*AC89 -> 16720.412 | W89: 3.435 | AB89: D | AC89: 4867.66 | AD89: 46131 | AE89: CRE | AF89: 6011021 | AH89: 4212 | AR89: 18 | AS89: EXISTENCIAS POR RECIBIR
A90: 46100 | C90: 01 | D90: 00F005 | F90: 17317 | G90: 6 | H90: 20493508645 | I90: =IF(H90="","",VLOOKUP(H90,ENTIDAD!$B$2:$C$613,2,0)) -> HONDA SELVA DEL PERU S.A. | N90: =(S90-P90)/1.18 -> -0.0029661017 | O90: =N90*0.18 -> -0.0005338983 | P90: 33380.99 | S90: =W90*AC90 -> 33380.986 | W90: 3.435 | AB90: D | AC90: 9717.9 | AD90: 46131 | AE90: CRE | AF90: 6011021 | AH90: 4212 | AR90: 18 | AS90: EXISTENCIAS POR RECIBIR
A91: 46101 | C91: 01 | D91: 00F003 | F91: 3746869 | G91: 6 | H91: 20101973922 | I91: =IF(H91="","",VLOOKUP(H91,ENTIDAD!$B$2:$C$613,2,0)) -> ASOCIACION AUTOMOTRIZ DEL PERU | N91: 0 | O91: =N91*0.18 -> 0 | P91: 0 | R91: 66.8 | S91: 66.8 | AB91: S | AD91: 46116 | AE91: CRE | AF91: 6599095 | AG91: 1413 | AH91: 4212 | AR91: 18 | AS91: POR DERECHO DE EMISION DE PLACA DE RODAJE
A92: 46101 | C92: 01 | D92: 00F003 | F92: 3746870 | G92: 6 | H92: 20101973922 | I92: =IF(H92="","",VLOOKUP(H92,ENTIDAD!$B$2:$C$613,2,0)) -> ASOCIACION AUTOMOTRIZ DEL PERU | N92: 0 | O92: =N92*0.18 -> 0 | P92: 0 | R92: 66.8 | S92: 66.8 | AB92: S | AD92: 46116 | AE92: CRE | AF92: 6599095 | AG92: 1413 | AH92: 4212 | AR92: 18 | AS92: POR DERECHO DE EMISION DE PLACA DE RODAJE
A93: 46101 | C93: 01 | D93: 00F003 | F93: 3746871 | G93: 6 | H93: 20101973922 | I93: =IF(H93="","",VLOOKUP(H93,ENTIDAD!$B$2:$C$613,2,0)) -> ASOCIACION AUTOMOTRIZ DEL PERU | N93: 0 | O93: =N93*0.18 -> 0 | P93: 0 | R93: 66.8 | S93: 66.8 | AB93: S | AD93: 46116 | AE93: CRE | AF93: 6599095 | AG93: 1413 | AH93: 4212 | AR93: 18 | AS93: POR DERECHO DE EMISION DE PLACA DE RODAJE
A94: 46101 | C94: 01 | D94: 00F003 | F94: 3746872 | G94: 6 | H94: 20101973922 | I94: =IF(H94="","",VLOOKUP(H94,ENTIDAD!$B$2:$C$613,2,0)) -> ASOCIACION AUTOMOTRIZ DEL PERU | N94: 0 | O94: =N94*0.18 -> 0 | P94: 0 | R94: 66.8 | S94: 66.8 | AB94: S | AD94: 46116 | AE94: CRE | AF94: 6599095 | AG94: 1413 | AH94: 4212 | AR94: 18 | AS94: POR DERECHO DE EMISION DE PLACA DE RODAJE
A95: 46101 | C95: 01 | D95: 00F003 | F95: 3746873 | G95: 6 | H95: 20101973922 | I95: =IF(H95="","",VLOOKUP(H95,ENTIDAD!$B$2:$C$613,2,0)) -> ASOCIACION AUTOMOTRIZ DEL PERU | N95: 0 | O95: =N95*0.18 -> 0 | P95: 0 | R95: 66.8 | S95: 66.8 | AB95: S | AD95: 46116 | AE95: CRE | AF95: 6599095 | AG95: 1413 | AH95: 4212 | AR95: 18 | AS95: POR DERECHO DE EMISION DE PLACA DE RODAJE
A96: 46101 | C96: 01 | D96: 00F003 | F96: 3746874 | G96: 6 | H96: 20101973922 | I96: =IF(H96="","",VLOOKUP(H96,ENTIDAD!$B$2:$C$613,2,0)) -> ASOCIACION AUTOMOTRIZ DEL PERU | N96: 0 | O96: =N96*0.18 -> 0 | P96: 0 | R96: 66.8 | S96: 66.8 | AB96: S | AD96: 46116 | AE96: CRE | AF96: 6599095 | AG96: 1413 | AH96: 4212 | AR96: 18 | AS96: POR DERECHO DE EMISION DE PLACA DE RODAJE
A97: 46101 | C97: 01 | D97: 00F003 | F97: 3746875 | G97: 6 | H97: 20101973922 | I97: =IF(H97="","",VLOOKUP(H97,ENTIDAD!$B$2:$C$613,2,0)) -> ASOCIACION AUTOMOTRIZ DEL PERU | N97: 0 | O97: =N97*0.18 -> 0 | P97: 0 | R97: 66.8 | S97: 66.8 | AB97: S | AD97: 46116 | AE97: CRE | AF97: 6599095 | AG97: 1413 | AH97: 4212 | AR97: 18 | AS97: POR DERECHO DE EMISION DE PLACA DE RODAJE
A98: 46101 | C98: 01 | D98: 00F003 | F98: 3746876 | G98: 6 | H98: 20101973922 | I98: =IF(H98="","",VLOOKUP(H98,ENTIDAD!$B$2:$C$613,2,0)) -> ASOCIACION AUTOMOTRIZ DEL PERU | N98: 0 | O98: =N98*0.18 -> 0 | P98: 0 | R98: 66.8 | S98: 66.8 | AB98: S | AD98: 46116 | AE98: CRE | AF98: 6599095 | AG98: 1413 | AH98: 4212 | AR98: 18 | AS98: POR DERECHO DE EMISION DE PLACA DE RODAJE
A99: 46101 | C99: 01 | D99: 00F003 | F99: 3746877 | G99: 6 | H99: 20101973922 | I99: =IF(H99="","",VLOOKUP(H99,ENTIDAD!$B$2:$C$613,2,0)) -> ASOCIACION AUTOMOTRIZ DEL PERU | N99: 0 | O99: =N99*0.18 -> 0 | P99: 0 | R99: 66.8 | S99: 66.8 | AB99: S | AD99: 46116 | AE99: CRE | AF99: 6599095 | AG99: 1413 | AH99: 4212 | AR99: 18 | AS99: POR DERECHO DE EMISION DE PLACA DE RODAJE
A100: 46101 | C100: 01 | D100: 00F003 | F100: 3746878 | G100: 6 | H100: 20101973922 | I100: =IF(H100="","",VLOOKUP(H100,ENTIDAD!$B$2:$C$613,2,0)) -> ASOCIACION AUTOMOTRIZ DEL PERU | N100: 0 | O100: =N100*0.18 -> 0 | P100: 0 | R100: 66.8 | S100: 66.8 | AB100: S | AD100: 46116 | AE100: CRE | AF100: 6599095 | AG100: 1413 | AH100: 4212 | AR100: 18 | AS100: POR DERECHO DE EMISION DE PLACA DE RODAJE
A101: 46101 | C101: 01 | D101: 00F003 | F101: 3746879 | G101: 6 | H101: 20101973922 | I101: =IF(H101="","",VLOOKUP(H101,ENTIDAD!$B$2:$C$613,2,0)) -> ASOCIACION AUTOMOTRIZ DEL PERU | N101: 0 | O101: =N101*0.18 -> 0 | P101: 0 | R101: 66.8 | S101: 66.8 | AB101: S | AD101: 46116 | AE101: CRE | AF101: 6599095 | AG101: 1413 | AH101: 4212 | AR101: 18 | AS101: POR DERECHO DE EMISION DE PLACA DE RODAJE
A102: 46101 | C102: 01 | D102: 00F003 | F102: 3746880 | G102: 6 | H102: 20101973922 | I102: =IF(H102="","",VLOOKUP(H102,ENTIDAD!$B$2:$C$613,2,0)) -> ASOCIACION AUTOMOTRIZ DEL PERU | N102: 0 | O102: =N102*0.18 -> 0 | P102: 0 | R102: 66.8 | S102: 66.8 | AB102: S | AD102: 46116 | AE102: CRE | AF102: 6599095 | AG102: 1413 | AH102: 4212 | AR102: 18 | AS102: POR DERECHO DE EMISION DE PLACA DE RODAJE
... A112: 46101 | C112: 01 | D112: 00F003 | F112: 3746890 | G112: 6 | H112: 20101973922 | I112: =IF(H112="","",VLOOKUP(H112,ENTIDAD!$B$2:$C$613,2,0)) -> ASOCIACION AUTOMOTRIZ DEL PERU | N112: 0 | O112: =N112*0.18 -> 0 | P112: 0 | R112: 66.8 | S112: 66.8 | AB112: S | AD112: 46116 | AE112: CRE | AF112: 6599095 | AG112: 1413 | AH112: 4212 | AR112: 18 | AS112: POR DERECHO DE EMISION DE PLACA DE RODAJE
A113: 46102 | C113: 01 | D113: 00E001 | F113: 1053 | G113: 6 | H113: 20541377612 | I113: =IF(H113="","",VLOOKUP(H113,ENTIDAD!$B$2:$C$613,2,0)) -> SERVICIOS MULTIPLES NINA E.I.R.L. | N113: =(S113-P113)/1.18 -> 67.79661 | O113: =N113*0.18 -> 12.20339 | P113: 0 | S113: 80 | AB113: S | AE113: CON | AF113: 656009401 | AH113: 4212 | AR113: 18 | AS113: POR LA COMPRA DE COMBUSTIBLE
A114: 46102 | C114: 01 | D114: 00E001 | F114: 523 | G114: 6 | H114: 10469834986 | I114: =IF(H114="","",VLOOKUP(H114,ENTIDAD!$B$2:$C$613,2,0)) -> UNCHUPAICO LAUREANO DEISY LUZ | N114: 0 | O114: =N114*0.18 -> 0 | P114: 360 | S114: 360 | AB114: S | AD114: 46133 | AE114: CRE | AF114: 656009506 | AH114: 4212 | AR114: 18 | AS114: POR LA IMPRESIÓN DE VOLANTES
A115: 46104 | C115: 01 | D115: 00F001 | F115: 12651 | G115: 6 | H115: 10209907327 | I115: =IF(H115="","",VLOOKUP(H115,ENTIDAD!$B$2:$C$613,2,0)) -> TORPOCO,MAYTA,HECTOR,ALFONSO | N115: =(S115-P115)/1.18 -> 0 | O115: =N115*0.18 -> 0 | P115: 20 | S115: 20 | AB115: S | AE115: CON | AF115: 656009501 | AH115: 4212 | AR115: 18 | AS115: POR LA COMPRA DE COMBUSTIBLE
A116: 46104 | C116: 01 | D116: 00F001 | F116: 5239 | G116: 6 | H116: 10061702071 | I116: =IF(H116="","",VLOOKUP(H116,ENTIDAD!$B$2:$C$613,2,0)) -> CORAL FLORES IVAN MARTIN | N116: 0 | O116: =N116*0.18 -> 0 | P116: 445 | S116: 445 | AB116: S | AD116: 46135 | AE116: CRE | AF116: 6599095 | AG116: 1413 | AH116: 4212 | AR116: 18 | AS116: POR EL SERVICIO DE LEGALIZACION
A117: 46104 | C117: 01 | D117: 00FF02 | F117: 116 | G117: 6 | H117: 10446330441 | I117: =IF(H117="","",VLOOKUP(H117,ENTIDAD!$B$2:$C$613,2,0)) -> TELLO LIMACHE JUANA | N117: 0 | O117: =N117*0.18 -> 0 | P117: 224 | S117: 224 | AB117: S | AD117: 46135 | AE117: CRE | AF117: 656009504 | AH117: 4212 | AR117: 18 | AS117: POR LA COMPRA DE ARTICULOS DE FERRETERIA
A118: 46105 | C118: 01 | D118: 00F005 | F118: 17409 | G118: 6 | H118: 20493508645 | I118: =IF(H118="","",VLOOKUP(H118,ENTIDAD!$B$2:$C$613,2,0)) -> HONDA SELVA DEL PERU S.A. | N118: =(S118-P118)/1.18 -> -0.00057627119 | O118: =N118*0.18 -> -0.00010372881 | P118: 18512.15 | S118: =W118*AC118 -> 18512.149 | W118: 3.468 | AB118: D | AC118: 5337.99 | AD118: 46136 | AE118: CRE | AF118: 6011021 | AH118: 4212 | AR118: 18 | AS118: EXISTENCIAS POR RECIBIR
A119: 46105 | C119: 01 | D119: 00F005 | F119: 17421 | G119: 6 | H119: 20493508645 | I119: =IF(H119="","",VLOOKUP(H119,ENTIDAD!$B$2:$C$613,2,0)) -> HONDA SELVA DEL PERU S.A. | N119: =(S119-P119)/1.18 -> -0.00023728814 | O119: =N119*0.18 -> -4.2711864e-05 | P119: 20628.67 | S119: =W119*AC119 -> 20628.67 | W119: 3.468 | AB119: D | AC119: 5948.29 | AD119: 46136 | AE119: CRE | AF119: 6011021 | AH119: 4212 | AR119: 18 | AS119: EXISTENCIAS POR RECIBIR
A120: 46105 | C120: 01 | D120: 00F005 | F120: 17429 | G120: 6 | H120: 20493508645 | I120: =IF(H120="","",VLOOKUP(H120,ENTIDAD!$B$2:$C$613,2,0)) -> HONDA SELVA DEL PERU S.A. | N120: =(S120-P120)/1.18 -> 0.0034915254 | O120: =N120*0.18 -> 0.00062847458 | P120: 41257.37 | S120: =W120*AC120 -> 41257.374 | W120: 3.468 | AB120: D | AC120: 11896.59 | AD120: 46136 | AE120: CRE | AF120: 6011021 | AH120: 4212 | AR120: 18 | AS120: EXISTENCIAS POR RECIBIR
A121: 46105 | C121: 01 | D121: 00F005 | F121: 17422 | G121: 6 | H121: 20493508645 | I121: =IF(H121="","",VLOOKUP(H121,ENTIDAD!$B$2:$C$613,2,0)) -> HONDA SELVA DEL PERU S.A. | N121: =(S121-P121)/1.18 -> -0.00047457627 | O121: =N121*0.18 -> -8.5423729e-05 | P121: 41257.34 | S121: =W121*AC121 -> 41257.339 | W121: 3.468 | AB121: D | AC121: 11896.58 | AD121: 46136 | AE121: CRE | AF121: 6011021 | AH121: 4212 | AR121: 18 | AS121: EXISTENCIAS POR RECIBIR
A122: 46105 | C122: 01 | D122: 00F028 | F122: 15260 | G122: 6 | H122: 20493508645 | I122: =IF(H122="","",VLOOKUP(H122,ENTIDAD!$B$2:$C$613,2,0)) -> HONDA SELVA DEL PERU S.A. | N122: =(S122-P122)/1.18 -> 0 | O122: =N122*0.18 -> 0 | P122: 0 | S122: 0 | W122: 3.468 | AB122: D | AC122: 3874.31 | AD122: 46136 | AE122: CRE | AF122: 6011021 | AH122: 4212 | AR122: 18 | AS122: EXISTENCIAS POR RECIBIR
A123: 46106 | C123: 01 | D123: 00E001 | F123: 6085 | G123: 6 | H123: 20602783341 | I123: =IF(H123="","",VLOOKUP(H123,ENTIDAD!$B$2:$C$613,2,0)) -> CODISSER VRAEM E.I.R.L. | N123: 0 | O123: =N123*0.18 -> 0 | P123: 8 | S123: 8 | AB123: S | AE123: CON | AF123: 6250095 | AH123: 4212 | AR123: 18 | AS123: POR LA COMPRA DE AGUA MESA
A124: 46106 | C124: 01 | D124: 00F005 | F124: 17441 | G124: 6 | H124: 20493508645 | I124: =IF(H124="","",VLOOKUP(H124,ENTIDAD!$B$2:$C$613,2,0)) -> HONDA SELVA DEL PERU S.A. | N124: 0 | O124: =N124*0.18 -> 0 | P124: 51203.05 | S124: =W124*AC124 -> 51203.047 | W124: 3.464 | AB124: D | AC124: 14781.48 | AD124: 46137 | AE124: CRE | AF124: 6011021 | AH124: 4212 | AR124: 18 | AS124: EXISTENCIAS POR RECIBIR
A125: 46106 | C125: 01 | D125: 00F001 | F125: 16118 | G125: 6 | H125: 20444766906 | I125: =IF(H125="","",VLOOKUP(H125,ENTIDAD!$B$2:$C$613,2,0)) -> EMPRESA DE TRANSPORTES PROFAMSE SRL | N125: 0 | O125: =N125*0.18 -> 0 | P125: 40 | S125: 40 | AB125: S | AE125: CRE | AF125: 6599095 | AG125: 1413 | AH125: 4212 | AR125: 18 | AS125: POR EL SERVICIO DE TRANSPORTE DE PASAJERO
A126: 46106 | C126: 01 | D126: 00F008 | F126: 11230 | G126: 6 | H126: 20485981536 | I126: =IF(H126="","",VLOOKUP(H126,ENTIDAD!$B$2:$C$613,2,0)) -> EMPRESA DE TRANSPORTES TURISMO Y SERVICIOS MULTIPLES SHIMA E.I.R.L. | N126: =(S126-P126)/1.18 -> 0 | O126: =N126*0.18 -> 0 | P126: 40 | S126: 40 | AB126: S | AD126: 46137 | AE126: CRE | AF126: 6599095 | AG126: 1413 | AH126: 4212 | AR126: 18 | AS126: POR EL SERVICIO DE TRANSPORTE DE PASAJERO
A127: 46107 | C127: 01 | D127: 00F001 | F127: 12654 | G127: 6 | H127: 10209907327 | I127: =IF(H127="","",VLOOKUP(H127,ENTIDAD!$B$2:$C$613,2,0)) -> TORPOCO,MAYTA,HECTOR,ALFONSO | N127: =(S127-P127)/1.18 -> 0 | O127: =N127*0.18 -> 0 | P127: 10 | S127: 10 | AB127: S | AE127: CON | AF127: 656009501 | AH127: 4212 | AR127: 18 | AS127: POR LA COMPRA DE COMBUSTIBLE
A128: 46108 | C128: 01 | D128: 00E001 | F128: 718 | G128: 6 | H128: 20319194798 | I128: =IF(H128="","",VLOOKUP(H128,ENTIDAD!$B$2:$C$613,2,0)) -> EMPRESA RADIODIFUSION NUEVA SENAL EIRLTD | N128: 0 | O128: =N128*0.18 -> 0 | P128: 100 | S128: 100 | AB128: S | AD128: 46139 | AE128: CRE | AF128: 6371095 | AH128: 4212 | AR128: 18 | AS128: DIFUSION
...

Sheet ABRIL
A1: FECHA DE EMISION DEL COMPROBANTE DE PAGO O DOCUMENTO | B1: FECHA DE VENCIMIENTO O FECHA DE PAGO | C1: COMPROBANTE DE PAGO O DOCUMENTO | F1: N° COMPROBANTE PAGO | G1: INFORMACION PROVEEDOR | J1: ADQUISICIONES GRAVADAS DESTINADAS A OPERACIONES GRAVADAS Y/O EXPORTACION | L1: ADQUISICIONES GRAVADAS DESTINADAS A OPERACIONES GRAVADAS Y/O DE EXPORTACION Y A OPERACIONES NO GRAVADAS | N1: ADQUISICIONES GRAVADAS DESTINADAS A OPERACIONES NO GRAVADAS | P1: VALOR DE LAS ADQUISICIONES NO GRAVADAS | Q1: ISC | R1: OTROS TRIBUTOS Y CARGOS | S1: IMPORTE TOTAL | T1: N° COMPROBANTE DE PAGO EMITIDO POR SUJETO NO DOMICILIADO | U1: CONSTANCIA DE DEPOSITO DE DETRACCION | W1: TIPO DE CAMBIO | X1: REFERENCIA DEL COMPROBANTE DE PAGO O DOCUMENTO ORIGINAL QUE SE MODIFICA | AB1: MONEDA | AC1: EQUIVALENTE EN DOLARES AMERICANOS | AD1: FECHA VENCIMIENTO | AE1: CONDICION CONTADO/CREDITO | AF1: CUENTA CONTABLE BASE IMPONIBLE | AG1: CUENTA CONTABLE OTROS TRIBUTOS Y CARGOS | AH1: CUENTA CONTABLE TOTAL | AI1: CODIGO CENTRO DE COSTOS | AJ1: CODIGO CENTRO DE COSTOS 2 | AK1: REGIMEN ESPECIAL | AL1: PORCENTAJE REGIMEN ESPECIAL | AM1: IMPORTE REGIMEN ESPECIAL | AN1: SERIE DOCUMENTO REGIMEN ESPECIAL | AO1: NUMERO DOCUMENTO REGIMEN ESPECIAL | AP1: FECHA DOCUMENTO REGIMEN ESPECIAL | AQ1: CODIGO PRESUPUESTO | AR1: PORCENTAJE I.G.V. | AS1: GLOSA | AT1: CONDICIÓN DE PERCEPCIÓN | AU1: IMPORTE RÉGIMEN ESPECIAL | AV1: CLASIFICACIÓN DE BIENES Y SERVICIOS ADQUIRIDOS
G2: DOCUMENTO IDENTIDAD | I2: APELLIDOS Y NOMBRES, DENOMINACION O RAZON SOCIAL
C3: TIPO | D3: SERIE/CODIGO ADUANA | E3: AÑO EMISION DUA O DSI | G3: TIPO | H3: NUMERO | J3: BASE IMPONIBLE | K3: IGV | L3: BASE IMPONIBLE | M3: IGV | N3: BASE IMPONIBLE | O3: IGV | U3: NUMERO | V3: FECHA EMISION | X3: FECHA | Y3: TIPO | Z3: SERIE | AA3: N° COMPROBANTE PAGO O DOCUMENTO
A4: 46101 | B4: 46120 | C4: 14 | D4: 00SB02 | F4: 275541604 | G4: 6 | H4: 20467534026 | I4: AMERICA MOVIL PERU S.A.C. | N4: 25.338983 | O4: 4.5610169 | P4: 0 | S4: 29.9 | AB4: S | AD4: 46131 | AE4: CRE | AF4: 6365095 | AH4: 4212 | AR4: 18 | AS4: SERVICIO DE TELEFONICA
A5: 46109 | B5: 46125 | C5: 14 | D5: 00S898 | F5: 5730536 | G5: 6 | H5: 20129646099 | I5: ELECTROCENTRO S.A. | N5: 0 | O5: 0 | P5: 435.2 | S5: 435.2 | AB5: S | AD5: 46125 | AE5: CRE | AF5: 6361095 | AH5: 4212 | AR5: 18 | AS5: SERVICIO DE ENERGIA ELECTRICA
A6: 46109 | B6: 46125 | C6: 14 | D6: 00S898 | F6: 5730541 | G6: 6 | H6: 20129646099 | I6: ELECTROCENTRO S.A. | N6: 0 | O6: 0 | P6: 99.6 | S6: 99.6 | AB6: S | AD6: 46125 | AE6: CRE | AF6: 6361095 | AH6: 4212 | AR6: 18 | AS6: SERVICIO DE ENERGIA ELECTRICA
A7: 46109 | B7: 46125 | C7: 14 | D7: 00S898 | F7: 5730759 | G7: 6 | H7: 20129646099 | I7: ELECTROCENTRO S.A. | N7: 0 | O7: 0 | P7: 584.4 | S7: 584.4 | AB7: S | AD7: 46125 | AE7: CRE | AF7: 6361095 | AH7: 4212 | AR7: 18 | AS7: SERVICIO DE ENERGIA ELECTRICA
A8: 46112 | B8: 46142 | C8: 14 | D8: 00S060 | F8: 1061880 | G8: 6 | H8: 20121876290 | I8: ENT.PREST.SERV.SANEAM.SELVA CENTRAL S.A | N8: 0 | O8: 0 | P8: 23.4 | S8: 23.4 | AB8: S | AD8: 46142 | AE8: CRE | AF8: 6363095 | AH8: 4212 | AR8: 18 | AS8: SERVICIO DE AGUA
A9: 46112 | B9: 46142 | C9: 14 | D9: 00S060 | F9: 1063470 | G9: 6 | H9: 20121876290 | I9: ENT.PREST.SERV.SANEAM.SELVA CENTRAL S.A | N9: 0 | O9: 0 | P9: 44.2 | S9: 44.2 | AB9: S | AD9: 46142 | AE9: CRE | AF9: 6363095 | AH9: 4212 | AR9: 18 | AS9: SERVICIO DE AGUA
A10: 46112 | B10: 46142 | C10: 14 | D10: 00S060 | F10: 1062629 | G10: 6 | H10: 20121876290 | I10: ENT.PREST.SERV.SANEAM.SELVA CENTRAL S.A | N10: 0 | O10: 0 | P10: 31.4 | S10: 31.4 | AB10: S | AD10: 46142 | AE10: CRE | AF10: 6363095 | AH10: 4212 | AR10: 18 | AS10: SERVICIO DE AGUA
A11: 46113 | B11: 46142 | C11: 01 | D11: 00F020 | F11: 19570 | G11: 6 | H11: 20485981536 | I11: EMPRESA DE TRANSPORTES TURISMO Y SERVICIOS MULTIPLES SHIMA E.I.R.L. | N11: 0 | O11: 0 | P11: 0 | R11: 40 | S11: 40 | AB11: S | AD11: 46142 | AE11: CRE | AF11: 6599095 | AG11: 1413 | AH11: 4212 | AR11: 18 | AS11: POR EL SERVICIO DE TRANSPORTE DE PASAJERO
A12: 46113 | C12: 01 | D12: 00E001 | F12: 1675 | G12: 6 | H12: 20611910887 | I12: CORPORACION UNIVERSAL M&F SOCIEDAD ANONIMA CERRADA | N12: 0 | O12: 0 | P12: 24 | S12: 24 | AB12: S | AE12: CON | AF12: 656009503 | AH12: 4212 | AR12: 18 | AS12: SELLO DE MADERA
A13: 46113 | B13: 46132 | C13: 14 | D13: 00SB01 | F13: 615581813 | G13: 6 | H13: 20467534026 | I13: AMERICA MOVIL PERU S.A.C. | N13: 75.177966 | O13: 13.532034 | P13: -0.02 | S13: 88.69 | AB13: S | AD13: 46132 | AE13: CRE | AF13: 6365095 | AH13: 4212 | AR13: 18 | AS13: SERVICIO DE INTERNET Y TELEFONIA
A14: 46113 | B14: 46143 | C14: 01 | D14: 00F003 | F14: 3768125 | G14: 6 | H14: 20101973922 | I14: ASOCIACION AUTOMOTRIZ DEL PERU | N14: 0 | O14: 0 | P14: 0 | R14: 66.8 | S14: 66.8 | AB14: S | AD14: 46143 | AE14: CRE | AF14: 6599095 | AG14: 1413 | AH14: 4212 | AR14: 18 | AS14: POR DERECHO DE EMISION DE PLACA DE RODAJE
A15: 46113 | B15: 46143 | C15: 01 | D15: 00F003 | F15: 3768124 | G15: 6 | H15: 20101973922 | I15: ASOCIACION AUTOMOTRIZ DEL PERU | N15: 0 | O15: 0 | P15: 0 | R15: 66.8 | S15: 66.8 | AB15: S | AD15: 46143 | AE15: CRE | AF15: 6599095 | AG15: 1413 | AH15: 4212 | AR15: 18 | AS15: POR DERECHO DE EMISION DE PLACA DE RODAJE
A16: 46113 | B16: 46143 | C16: 01 | D16: 00F003 | F16: 3768123 | G16: 6 | H16: 20101973922 | I16: ASOCIACION AUTOMOTRIZ DEL PERU | N16: 0 | O16: 0 | P16: 0 | R16: 66.8 | S16: 66.8 | AB16: S | AD16: 46143 | AE16: CRE | AF16: 6599095 | AG16: 1413 | AH16: 4212 | AR16: 18 | AS16: POR DERECHO DE EMISION DE PLACA DE RODAJE
A17: 46113 | B17: 46143 | C17: 01 | D17: 00F003 | F17: 3768122 | G17: 6 | H17: 20101973922 | I17: ASOCIACION AUTOMOTRIZ DEL PERU | N17: 0 | O17: 0 | P17: 0 | R17: 66.8 | S17: 66.8 | AB17: S | AD17: 46143 | AE17: CRE | AF17: 6599095 | AG17: 1413 | AH17: 4212 | AR17: 18 | AS17: POR DERECHO DE EMISION DE PLACA DE RODAJE
A18: 46113 | B18: 46143 | C18: 01 | D18: 00F003 | F18: 3768121 | G18: 6 | H18: 20101973922 | I18: ASOCIACION AUTOMOTRIZ DEL PERU | N18: 0 | O18: 0 | P18: 0 | R18: 66.8 | S18: 66.8 | AB18: S | AD18: 46143 | AE18: CRE | AF18: 6599095 | AG18: 1413 | AH18: 4212 | AR18: 18 | AS18: POR DERECHO DE EMISION DE PLACA DE RODAJE
A19: 46113 | B19: 46143 | C19: 01 | D19: 00F003 | F19: 3768120 | G19: 6 | H19: 20101973922 | I19: ASOCIACION AUTOMOTRIZ DEL PERU | N19: 0 | O19: 0 | P19: 0 | R19: 66.8 | S19: 66.8 | AB19: S | AD19: 46143 | AE19: CRE | AF19: 6599095 | AG19: 1413 | AH19: 4212 | AR19: 18 | AS19: POR DERECHO DE EMISION DE PLACA DE RODAJE
A20: 46113 | B20: 46143 | C20: 01 | D20: 00F003 | F20: 3768119 | G20: 6 | H20: 20101973922 | I20: ASOCIACION AUTOMOTRIZ DEL PERU | N20: 0 | O20: 0 | P20: 0 | R20: 66.8 | S20: 66.8 | AB20: S | AD20: 46143 | AE20: CRE | AF20: 6599095 | AG20: 1413 | AH20: 4212 | AR20: 18 | AS20: POR DERECHO DE EMISION DE PLACA DE RODAJE
A21: 46113 | B21: 46143 | C21: 01 | D21: 00F003 | F21: 3768118 | G21: 6 | H21: 20101973922 | I21: ASOCIACION AUTOMOTRIZ DEL PERU | N21: 0 | O21: 0 | P21: 0 | R21: 66.8 | S21: 66.8 | AB21: S | AD21: 46143 | AE21: CRE | AF21: 6599095 | AG21: 1413 | AH21: 4212 | AR21: 18 | AS21: POR DERECHO DE EMISION DE PLACA DE RODAJE
A22: 46113 | B22: 46143 | C22: 01 | D22: 00F003 | F22: 3768117 | G22: 6 | H22: 20101973922 | I22: ASOCIACION AUTOMOTRIZ DEL PERU | N22: 0 | O22: 0 | P22: 0 | R22: 66.8 | S22: 66.8 | AB22: S | AD22: 46143 | AE22: CRE | AF22: 6599095 | AG22: 1413 | AH22: 4212 | AR22: 18 | AS22: POR DERECHO DE EMISION DE PLACA DE RODAJE
A23: 46113 | B23: 46143 | C23: 01 | D23: 00F003 | F23: 3768116 | G23: 6 | H23: 20101973922 | I23: ASOCIACION AUTOMOTRIZ DEL PERU | N23: 0 | O23: 0 | P23: 0 | R23: 66.8 | S23: 66.8 | AB23: S | AD23: 46143 | AE23: CRE | AF23: 6599095 | AG23: 1413 | AH23: 4212 | AR23: 18 | AS23: POR DERECHO DE EMISION DE PLACA DE RODAJE
A24: 46113 | B24: 46143 | C24: 01 | D24: 00F003 | F24: 3768115 | G24: 6 | H24: 20101973922 | I24: ASOCIACION AUTOMOTRIZ DEL PERU | N24: 0 | O24: 0 | P24: 0 | R24: 66.8 | S24: 66.8 | AB24: S | AD24: 46143 | AE24: CRE | AF24: 6599095 | AG24: 1413 | AH24: 4212 | AR24: 18 | AS24: POR DERECHO DE EMISION DE PLACA DE RODAJE
A25: 46113 | B25: 46143 | C25: 01 | D25: 00F003 | F25: 3768114 | G25: 6 | H25: 20101973922 | I25: ASOCIACION AUTOMOTRIZ DEL PERU | N25: 0 | O25: 0 | P25: 0 | R25: 66.8 | S25: 66.8 | AB25: S | AD25: 46143 | AE25: CRE | AF25: 6599095 | AG25: 1413 | AH25: 4212 | AR25: 18 | AS25: POR DERECHO DE EMISION DE PLACA DE RODAJE
... A34: 46113 | B34: 46143 | C34: 01 | D34: 00F003 | F34: 3768104 | G34: 6 | H34: 20101973922 | I34: ASOCIACION AUTOMOTRIZ DEL PERU | N34: 0 | O34: 0 | P34: 0 | R34: 66.8 | S34: 66.8 | AB34: S | AD34: 46143 | AE34: CRE | AF34: 6599095 | AG34: 1413 | AH34: 4212 | AR34: 18 | AS34: POR DERECHO DE EMISION DE PLACA DE RODAJE
A35: 46113 | C35: 01 | D35: 00F001 | F35: 12661 | G35: 6 | H35: 10209907327 | I35: TORPOCO,MAYTA,HECTOR,ALFONSO | N35: 0 | O35: 0 | P35: 10 | S35: 10 | AB35: S | AE35: CON | AF35: 656009501 | AH35: 4212 | AR35: 18 | AS35: POR LA COMPRA DE COMBUSTIBLE
A36: 46113 | B36: 46143 | C36: 01 | D36: 00F003 | F36: 3768113 | G36: 6 | H36: 20101973922 | I36: ASOCIACION AUTOMOTRIZ DEL PERU | N36: 56.610169 | O36: 10.189831 | P36: 0 | S36: 66.8 | AB36: S | AD36: 46143 | AE36: CRE | AF36: 6599095 | AG36: 1413 | AH36: 4212 | AR36: 18 | AS36: POR DERECHO DE EMISION DE PLACA DE RODAJE
A37: 46114 | C37: 01 | D37: 00F001 | F37: 118669 | G37: 6 | H37: 20568499043 | I37: SURTIDORES SAN MIGUEL E.I.R.L. | N37: 0 | O37: 0 | P37: 100 | S37: 100 | AB37: S | AE37: CON | AF37: 656009501 | AH37: 4212 | AR37: 18 | AS37: POR LA COMPRA DE COMBUSTIBLE
A38: 46116 | B38: 46146 | C38: 01 | D38: 00F010 | F38: 4817 | G38: 6 | H38: 20601012261 | I38: IMPORTADORA DE REPUESTOS LA ROCA E.I.R.L. | N38: 0 | O38: 0 | P38: 14 | S38: 14 | AB38: S | AD38: 46146 | AE38: CON | AF38: 656009507 | AH38: 4212 | AR38: 18 | AS38: SWITCH UNIVERSAL C/BASE P/TIMON 3C NG YANGZU D003022
A39: 46118 | B39: 46148 | C39: 01 | D39: 00FC04 | F39: 4964259 | G39: 6 | H39: 20100130204 | I39: BANCO BBVA PERU | N39: 0 | O39: 0 | P39: 40 | S39: 40 | AB39: S | AD39: 46148 | AE39: CRE | AF39: 6391094 | AH39: 4212 | AR39: 18 | AS39: POR LA COMISION BANCARIA
A40: 46118 | B40: 46148 | C40: 01 | D40: 00FB26 | F40: 26742968 | G40: 6 | H40: 20100130204 | I40: BANCO BBVA PERU | N40: 0 | O40: 0 | P40: 10 | S40: 10 | AB40: S | AD40: 46148 | AE40: CRE | AF40: 6391094 | AH40: 4212 | AR40: 18 | AS40: POR LA COMISION BANCARIA
A41: 46118 | C41: 01 | D41: 00F001 | F41: 118745 | G41: 6 | H41: 20568499043 | I41: SURTIDORES SAN MIGUEL E.I.R.L. | N41: 0 | O41: 0 | P41: 113.5 | S41: 113.5 | AB41: S | AE41: CON | AF41: 656009501 | AH41: 4212 | AR41: 18 | AS41: POR LA COMPRA DE COMBUSTIBLE
A42: 46119 | B42: 46149 | C42: 01 | D42: 00E001 | F42: 197 | G42: 6 | H42: 10447422951 | I42: ZEGARRA AZAÑERO JORGE KEY | N42: 0 | O42: 0 | P42: 450 | S42: 450 | AB42: S | AD42: 46149 | AE42: CRE | AF42: 6329094 | AH42: 4212 | AR42: 18 | AS42: SOPORTE TECNICO
A43: 46119 | B43: 46149 | C43: 01 | D43: 00E001 | F43: 3 | G43: 6 | H43: 20615490548 | I43: CORPORACION TOSCANO TECNOLOGY PERÚ SOCIEDAD ANONIMA CERRADA | N43: 0 | O43: 0 | P43: 270 | S43: 270 | AB43: S | AD43: 46149 | AE43: CRE | AF43: 6011020 | AH43: 4212 | AR43: 18 | AS43: PARABRIZA ESCHIZO TRIANGULO
A44: 46119 | B44: 46149 | C44: 01 | D44: 00F010 | F44: 4831 | G44: 6 | H44: 20601012261 | I44: IMPORTADORA DE REPUESTOS LA ROCA E.I.R.L. | N44: 0 | O44: 0 | P44: 3.5 | S44: 3.5 | AB44: S | AD44: 46149 | AE44: CRE | AF44: 656009507 | AH44: 4212 | AR44: 18 | AS44: PORTA FUSIBLE , FUSIBLE
A45: 46120 | B45: 46150 | C45: 01 | D45: 00FB26 | F45: 26812174 | G45: 6 | H45: 20100130204 | I45: BANCO BBVA PERU | N45: 0 | O45: 0 | P45: 7.91 | S45: 7.91 | AB45: S | AD45: 46150 | AE45: CRE | AF45: 6391094 | AH45: 4212 | AR45: 18 | AS45: POR LA COMISION BANCARIA
A46: 46120 | B46: 46150 | C46: 01 | D46: 00FE01 | F46: 2804050 | G46: 6 | H46: 20100047218 | I46: BANCO DE CREDITO DEL PERU | N46: 1.2043097e-14 | O46: 2.1677575e-15 | P46: 120.33 | S46: 120.33 | W46: 3.438 | AB46: D | AC46: 35 | AD46: 46150 | AE46: CRE | AF46: 6391094 | AH46: 4212 | AR46: 18 | AS46: POR COMISION DE TELECREDITO
A47: 46120 | B47: 46150 | C47: 01 | D47: 00F002 | F47: 140 | G47: 6 | H47: 20600454065 | I47: REPUESTOS Y SERVICIOS ARAUCO E.I.R.L. | N47: 0 | O47: 0 | P47: 2075 | S47: 2075 | AB47: S | AD47: 46150 | AE47: CRE | AF47: 6343095 | AH47: 4212 | AR47: 18 | AS47: MANTENIMIENTO DE MOTOS VENDIDAS - GARANTIA
A48: 46121 | B48: 46151 | C48: 01 | D48: 00FV12 | F48: 1345247 | G48: 6 | H48: 20100047218 | I48: BANCO DE CREDITO DEL PERU | N48: 0 | O48: 0 | P48: 138 | S48: 138 | AB48: S | AD48: 46151 | AE48: CRE | AF48: 6391094 | AH48: 4212 | AR48: 18 | AS48: POR MANTENIMIENTO,OPER.EXCESO,APORTE Y ESTADO
A49: 46121 | B49: 46151 | C49: 01 | D49: 00E001 | F49: 1840 | G49: 6 | H49: 20486339510 | I49: SERVICIOS CONTABLES Y AUDITORIA INTERNA S.A. | N49: 1694.9153 | O49: 305.08475 | P49: 0 | S49: 2000 | AB49: S | AD49: 46151 | AE49: CRE | AF49: 6323094 | AH49: 4212 | AR49: 18 | AS49: SERVICIO CONTABLE
A50: 46121 | B50: 46151 | C50: 01 | D50: 00E001 | F50: 6117 | G50: 6 | H50: 20602783341 | I50: CODISSER VRAEM E.I.R.L. | N50: 0 | O50: 0 | P50: 8 | S50: 8 | AB50: S | AD50: 46151 | AE50: CON | AF50: 6250095 | AH50: 4212 | AR50: 18 | AS50: AGUA DE MESA POR 20 LITROS
A51: 46122 | B51: 46152 | C51: 01 | D51: 00F001 | F51: 1066 | G51: 6 | H51: 20611936606 | I51: GAS VIVA EMPRESA INDIVIDUAL DE RESPONSABILIDAD LIMITADA | N51: 0 | O51: 0 | P51: 10 | S51: 10 | AB51: S | AD51: 46152 | AE51: CON | AF51: 656009501 | AH51: 4212 | AR51: 18 | AS51: POR LA COMPRA DE COMBUSTIBLE
A52: 46122 | B52: 46152 | C52: 01 | D52: 00F001 | F52: 6199 | G52: 6 | H52: 20486549328 | I52: SANTISIMA TRINIDAD E.I.R.L. | N52: 0 | O52: 0 | P52: 40 | S52: 40 | AB52: S | AD52: 46152 | AE52: CON | AF52: 656009503 | AH52: 4212 | AR52: 18 | AS52: ARTICULOS DE ESCRITORIO
A53: 46122 | B53: 46152 | C53: 01 | D53: 00E001 | F53: 528 | G53: 6 | H53: 10469834986 | I53: UNCHUPAICO LAUREANO DEISY LUZ | N53: 0 | O53: 0 | P53: 360 | S53: 360 | AB53: S | AD53: 46152 | AE53: CRE | AF53: 656009506 | AH53: 4212 | AR53: 18 | AS53: POR LA IMPRESIÓN DE VOLANTES
A54: 46123 | B54: 46153 | C54: 01 | D54: 00E001 | F54: 209 | G54: 6 | H54: 10447422951 | I54: ZEGARRA AZAÑERO JORGE KEY | N54: 0 | O54: 0 | P54: 700 | S54: 700 | AB54: S | AD54: 46153 | AE54: CRE | AF54: 6329094 | AH54: 4212 | AR54: 18 | AS54: FORMATEO E INSTA. DE WINDOWS SERVER,LICENCIA WINDOWS,ANTIVIRUS NOD 32
A55: 46123 | B55: 46153 | C55: 01 | D55: 00FI01 | F55: 19257831 | G55: 6 | H55: 20100047218 | I55: BANCO DE CREDITO DEL PERU | N55: -0.0021186441 | O55: -0.00038135593 | P55: 59.24 | S55: 59.2375 | W55: 3.385 | AB55: D | AC55: 17.5 | AD55: 46153 | AE55: CRE | AF55: 6391094 | AH55: 4212 | AR55: 18 | AS55: PAGO PORTES,PAGO CARGO COMISION
A56: 46123 | B56: 46153 | C56: 01 | D56: 00FI01 | F56: 19147938 | G56: 6 | H56: 20100047218 | I56: BANCO DE CREDITO DEL PERU | N56: 0 | O56: 0 | P56: 758.25 | S56: 758.25 | AB56: S | AD56: 46153 | AE56: CRE | AF56: 6391094 | AH56: 4212 | AR56: 18 | AS56: PAGO,APORTE,CARGO COMISION,EXCESO OPERA.ON LINE TRNF FDOS
A57: 46125 | C57: 01 | D57: 00F010 | F57: 4871 | G57: 6 | H57: 20601012261 | I57: IMPORTADORA DE REPUESTOS LA ROCA E.I.R.L. | N57: 0 | O57: 0 | P57: 13 | S57: 13 | AB57: S | AE57: CON | AF57: 656009507 | AH57: 4212 | AR57: 18 | AS57: LIMPIA CARBURADOR VISTONY
A58: 46125 | C58: 01 | D58: 00F001 | F58: 21595 | G58: 6 | H58: 20609711923 | I58: INVERSIONES TACZA CONTRATISTAS GENERALES SOCIEDAD ANONIMA CERRADA | N58: 0 | O58: 0 | P58: 20 | S58: 20 | AB58: S | AE58: CON | AF58: 656009501 | AH58: 4212 | AR58: 18 | AS58: POR LA COMPRA DE COMBUSTIBLE
A59: 46125 | C59: 01 | D59: 00F006 | F59: 466 | G59: 6 | H59: 20568369000 | I59: INFORMATICA Y GRAFICA EMPRESA INDIVIDUAL DE RESPONSABILIDAD LIMITADA - INFOGRAFIC E.I.R.L. | N59: 0 | O59: 0 | P59: 40 | S59: 40 | AB59: S | AE59: CON | AF59: 656009503 | AH59: 4212 | AR59: 18 | AS59: TINTA EPSON
A60: 46126 | B60: 46156 | C60: 01 | D60: 00F005 | F60: 17745 | G60: 6 | H60: 20493508645 | I60: HONDA SELVA DEL PERU S.A. | N60: -0.00058474576 | O60: -0.00010525424 | P60: 29967.98 | S60: 29967.979 | W60: 3.379 | AB60: D | AC60: 8868.89 | AD60: 46156 | AE60: CRE | AF60: 6011021 | AH60: 4212 | AR60: 18 | AS60: EXISTENCIAS POR RECIBIR
A61: 46126 | B61: 46156 | C61: 01 | D61: 00F001 | F61: 5272 | G61: 6 | H61: 10061702071 | I61: CORAL FLORES IVAN MARTIN | N61: 0 | O61: 0 | P61: 0 | R61: 495 | S61: 495 | AB61: S | AD61: 46156 | AE61: CRE | AF61: 6599095 | AG61: 1413 | AH61: 4212 | AR61: 18 | AS61: CERTIFICACION DE FIRMAS
A62: 46126 | C62: 01 | D62: 00F001 | F62: 20387 | G62: 6 | H62: 20605377115 | I62: CORPORACIÓN FERNANDO´S E.I.R.L. | N62: 0 | O62: 0 | P62: 10 | S62: 10 | AB62: S | AE62: CON | AF62: 656009501 | AH62: 4212 | AR62: 18 | AS62: POR LA COMPRA DE COMBUSTIBLE
A63: 46126 | B63: 46156 | C63: 01 | D63: 00F003 | F63: 3790519 | G63: 6 | H63: 20101973922 | I63: ASOCIACION AUTOMOTRIZ DEL PERU | N63: 0 | O63: 0 | P63: 0 | R63: 66.8 | S63: 66.8 | AB63: S | AD63: 46156 | AE63: CRE | AF63: 6599095 | AG63: 1413 | AH63: 4212 | AR63: 18 | AS63: POR DERECHO DE EMISION DE PLACA DE RODAJE
A64: 46126 | B64: 46156 | C64: 01 | D64: 00F003 | F64: 3790520 | G64: 6 | H64: 20101973922 | I64: ASOCIACION AUTOMOTRIZ DEL PERU | N64: 0 | O64: 0 | P64: 0 | R64: 66.8 | S64: 66.8 | AB64: S | AD64: 46156 | AE64: CRE | AF64: 6599095 | AG64: 1413 | AH64: 4212 | AR64: 18 | AS64: POR DERECHO DE EMISION DE PLACA DE RODAJE
A65: 46126 | B65: 46156 | C65: 01 | D65: 00F003 | F65: 3790521 | G65: 6 | H65: 20101973922 | I65: ASOCIACION AUTOMOTRIZ DEL PERU | N65: 0 | O65: 0 | P65: 0 | R65: 66.8 | S65: 66.8 | AB65: S | AD65: 46156 | AE65: CRE | AF65: 6599095 | AG65: 1413 | AH65: 4212 | AR65: 18 | AS65: POR DERECHO DE EMISION DE PLACA DE RODAJE
A66: 46126 | B66: 46156 | C66: 01 | D66: 00F003 | F66: 3790522 | G66: 6 | H66: 20101973922 | I66: ASOCIACION AUTOMOTRIZ DEL PERU | N66: 0 | O66: 0 | P66: 0 | R66: 66.8 | S66: 66.8 | AB66: S | AD66: 46156 | AE66: CRE | AF66: 6599095 | AG66: 1413 | AH66: 4212 | AR66: 18 | AS66: POR DERECHO DE EMISION DE PLACA DE RODAJE
A67: 46126 | B67: 46156 | C67: 01 | D67: 00F003 | F67: 3790523 | G67: 6 | H67: 20101973922 | I67: ASOCIACION AUTOMOTRIZ DEL PERU | N67: 0 | O67: 0 | P67: 0 | R67: 66.8 | S67: 66.8 | AB67: S | AD67: 46156 | AE67: CRE | AF67: 6599095 | AG67: 1413 | AH67: 4212 | AR67: 18 | AS67: POR DERECHO DE EMISION DE PLACA DE RODAJE
A68: 46126 | B68: 46156 | C68: 01 | D68: 00F003 | F68: 3790524 | G68: 6 | H68: 20101973922 | I68: ASOCIACION AUTOMOTRIZ DEL PERU | N68: 0 | O68: 0 | P68: 0 | R68: 66.8 | S68: 66.8 | AB68: S | AD68: 46156 | AE68: CRE | AF68: 6599095 | AG68: 1413 | AH68: 4212 | AR68: 18 | AS68: POR DERECHO DE EMISION DE PLACA DE RODAJE
A69: 46126 | B69: 46156 | C69: 01 | D69: 00F003 | F69: 3790525 | G69: 6 | H69: 20101973922 | I69: ASOCIACION AUTOMOTRIZ DEL PERU | N69: 0 | O69: 0 | P69: 0 | R69: 66.8 | S69: 66.8 | AB69: S | AD69: 46156 | AE69: CRE | AF69: 6599095 | AG69: 1413 | AH69: 4212 | AR69: 18 | AS69: POR DERECHO DE EMISION DE PLACA DE RODAJE
A70: 46126 | B70: 46156 | C70: 01 | D70: 00F003 | F70: 3790526 | G70: 6 | H70: 20101973922 | I70: ASOCIACION AUTOMOTRIZ DEL PERU | N70: 0 | O70: 0 | P70: 0 | R70: 66.8 | S70: 66.8 | AB70: S | AD70: 46156 | AE70: CRE | AF70: 6599095 | AG70: 1413 | AH70: 4212 | AR70: 18 | AS70: POR DERECHO DE EMISION DE PLACA DE RODAJE
A71: 46126 | B71: 46156 | C71: 01 | D71: 00F003 | F71: 3790527 | G71: 6 | H71: 20101973922 | I71: ASOCIACION AUTOMOTRIZ DEL PERU | N71: 0 | O71: 0 | P71: 0 | R71: 66.8 | S71: 66.8 | AB71: S | AD71: 46156 | AE71: CRE | AF71: 6599095 | AG71: 1413 | AH71: 4212 | AR71: 18 | AS71: POR DERECHO DE EMISION DE PLACA DE RODAJE
A72: 46126 | B72: 46156 | C72: 01 | D72: 00F003 | F72: 3790528 | G72: 6 | H72: 20101973922 | I72: ASOCIACION AUTOMOTRIZ DEL PERU | N72: 0 | O72: 0 | P72: 0 | R72: 66.8 | S72: 66.8 | AB72: S | AD72: 46156 | AE72: CRE | AF72: 6599095 | AG72: 1413 | AH72: 4212 | AR72: 18 | AS72: POR DERECHO DE EMISION DE PLACA DE RODAJE
A73: 46126 | B73: 46156 | C73: 01 | D73: 00F003 | F73: 3790529 | G73: 6 | H73: 20101973922 | I73: ASOCIACION AUTOMOTRIZ DEL PERU | N73: 0 | O73: 0 | P73: 0 | R73: 66.8 | S73: 66.8 | AB73: S | AD73: 46156 | AE73: CRE | AF73: 6599095 | AG73: 1413 | AH73: 4212 | AR73: 18 | AS73: POR DERECHO DE EMISION DE PLACA DE RODAJE
A74: 46126 | B74: 46156 | C74: 01 | D74: 00F003 | F74: 3790530 | G74: 6 | H74: 20101973922 | I74: ASOCIACION AUTOMOTRIZ DEL PERU | N74: 0 | O74: 0 | P74: 0 | R74: 66.8 | S74: 66.8 | AB74: S | AD74: 46156 | AE74: CRE | AF74: 6599095 | AG74: 1413 | AH74: 4212 | AR74: 18 | AS74: POR DERECHO DE EMISION DE PLACA DE RODAJE
... A80: 46126 | B80: 46156 | C80: 01 | D80: 00F003 | F80: 3790536 | G80: 6 | H80: 20101973922 | I80: ASOCIACION AUTOMOTRIZ DEL PERU | N80: 0 | O80: 0 | P80: 0 | R80: 66.8 | S80: 66.8 | AB80: S | AD80: 46156 | AE80: CRE | AF80: 6599095 | AG80: 1413 | AH80: 4212 | AR80: 18 | AS80: POR DERECHO DE EMISION DE PLACA DE RODAJE
A81: 46127 | B81: 46157 | C81: 01 | D81: 00FC01 | F81: 601369 | G81: 6 | H81: 20100047218 | I81: BANCO DE CREDITO DEL PERU | N81: 0 | O81: 0 | P81: 5503.5 | S81: 5503.5 | AB81: S | AD81: 46157 | AE81: CRE | AF81: 6391094 | AH81: 4212 | AR81: 18 | AS81: PAGO COMISION, GASTOS DE APORTES
A82: 46127 | B82: 46157 | C82: 01 | D82: 00F005 | F82: 566 | G82: 6 | H82: 20602109225 | I82: SISTEMA ECOLÓGICO INTEGRAL DE TECNOLOGÍAS E INFORMÁTICA SOCIEDAD ANONIMA CERRADA - ECO SITI S.A.C. | N82: 0 | O82: 0 | P82: 120 | S82: 120 | AB82: S | AD82: 46157 | AE82: CRE | AF82: 6364095 | AG82: 1413 | AH82: 4212 | AR82: 18 | AS82: PAGO DE SERVICIO DE TELEFONIA
A83: 46127 | C83: 01 | D83: 00FF08 | F83: 853 | G83: 6 | H83: 20611526572 | I83: GRUPO SUKKIE E.I.R.L. | N83: 0 | O83: 0 | P83: 90.9 | S83: 90.9 | AB83: S | AE83: CON | AF83: 656009502 | AH83: 4212 | AR83: 18 | AS83: ARTICULOS DE LIMPIEZA
A84: 46127 | B84: 46157 | C84: 01 | D84: 00F005 | F84: 17768 | G84: 6 | H84: 20493508645 | I84: HONDA SELVA DEL PERU S.A. | N84: -0.0011864407 | O84: -0.00021355932 | P84: 19766.21 | S84: 19766.209 | W84: 3.39 | AB84: D | AC84: 5830.74 | AD84: 46157 | AE84: CRE | AF84: 6011021 | AH84: 4212 | AR84: 18 | AS84: EXISTENCIAS POR RECIBIR
A85: 46127 | B85: 46157 | C85: 01 | D85: 00E001 | F85: 210 | G85: 6 | H85: 10447422951 | I85: ZEGARRA AZAÑERO JORGE KEY | N85: 0 | O85: 0 | P85: 300 | S85: 300 | AB85: S | AD85: 46157 | AE85: CRE | AF85: 33691 | AH85: 4212 | AR85: 18 | AS85: DISCO DURO
A86: 46127 | B86: 46157 | C86: 01 | D86: 00F008 | F86: 11447 | G86: 6 | H86: 20485981536 | I86: EMPRESA DE TRANSPORTES TURISMO Y SERVICIOS MULTIPLES SHIMA E.I.R.L. | N86: 0 | O86: 0 | P86: 0 | R86: 40 | S86: 40 | AB86: S | AD86: 46157 | AE86: CRE | AF86: 6599095 | AG86: 1413 | AH86: 4212 | AR86: 18 | AS86: SERVICIO DE TRANSPORTE DE PASAJERO
A87: 46127 | B87: 46157 | C87: 01 | D87: 00E001 | F87: 430 | G87: 6 | H87: 20402406161 | I87: SERVI TOURS EXPRESS S.A. | N87: 0 | O87: 0 | P87: 0 | R87: 40 | S87: 40 | AB87: S | AD87: 46157 | AE87: CRE | AF87: 6599095 | AG87: 1413 | AH87: 4212 | AR87: 18 | AS87: SERVICIO DE TRANSPORTE DE PASAJERO
A88: 46128 | B88: 46158 | C88: 01 | D88: 00F010 | F88: 4885 | G88: 6 | H88: 20601012261 | I88: IMPORTADORA DE REPUESTOS LA ROCA E.I.R.L. | N88: 0 | O88: 0 | P88: 3.4 | S88: 3.4 | AB88: S | AD88: 46158 | AE88: CRE | AF88: 656009507 | AH88: 4212 | AR88: 18 | AS88: TERMINAL HEMBRA Y MACHO,PERNO,TUERCA
A89: 46128 | B89: 46158 | C89: 01 | D89: 00F002 | F89: 2237 | G89: 6 | H89: 20603851171 | I89: J&J RENATO E.I.R.L. | N89: 0 | O89: 0 | P89: 6 | S89: 6 | AB89: S | AD89: 46158 | AE89: CRE | AF89: 656009507 | AH89: 4212 | AR89: 18 | AS89: JEBE TAPABARRO
A90: 46128 | C90: 01 | D90: 00F001 | F90: 740 | G90: 6 | H90: 10733910921 | I90: MADUEÑO HUAMAN LILI CLISSELY | N90: 0 | O90: 0 | P90: 15 | S90: 15 | AB90: S | AE90: CON | AF90: 656009503 | AH90: 4212 | AR90: 18 | AS90: CINTA AISLANTE NEGRO
A91: 46128 | B91: 46158 | C91: 01 | D91: 00E001 | F91: 1698 | G91: 6 | H91: 20611910887 | I91: CORPORACION UNIVERSAL M&F SOCIEDAD ANONIMA CERRADA | N91: 0 | O91: 0 | P91: 80 | S91: 80 | AB91: S | AD91: 46158 | AE91: CRE | AF91: 656009506 | AH91: 4212 | AR91: 18 | AS91: IMPRESIÓN DE FORMATO 1+1 COPIA
A92: 46128 | C92: 01 | D92: 00F010 | F92: 4886 | G92: 6 | H92: 20601012261 | I92: IMPORTADORA DE REPUESTOS LA ROCA E.I.R.L. | N92: 0 | O92: 0 | P92: 0.8 | S92: 0.8 | AB92: S | AE92: CON | AF92: 656009507 | AH92: 4212 | AR92: 18 | AS92: PERNO, TUERCA
A93: 46129 | B93: 46159 | C93: 01 | D93: 00FN01 | F93: 45011853 | G93: 6 | H93: 20100047218 | I93: BANCO DE CREDITO DEL PERU | N93: 0 | O93: 0 | P93: 10 | S93: 10 | AB93: S | AD93: 46159 | AE93: CRE | AF93: 6391094 | AH93: 4212 | AR93: 18 | AS93: PAGO COMISION
A94: 46129 | C94: 01 | D94: 00E001 | F94: 79 | G94: 6 | H94: 10733619207 | I94: UNTIVEROS SOLDEVILLA MIGUEL COLIN | N94: 0 | O94: 0 | P94: 20 | S94: 20 | AB94: S | AE94: CON | AF94: 656009506 | AH94: 4212 | AR94: 18 | AS94: GIGANTOGRAFIAS
A95: 46129 | B95: 46159 | C95: 01 | D95: 00F005 | F95: 17807 | G95: 6 | H95: 20493508645 | I95: HONDA SELVA DEL PERU S.A. | N95: -0.0017288136 | O95: -0.00031118644 | P95: 11150.2 | S95: 11150.198 | W95: 3.436 | AB95: D | AC95: 3245.11 | AD95: 46159 | AE95: CRE | AF95: 6011021 | AH95: 4212 | AR95: 18 | AS95: EXISTENCIAS POR RECIBIR
A96: 46129 | B96: 46159 | C96: 01 | D96: 00F005 | F96: 17808 | G96: 6 | H96: 20493508645 | I96: HONDA SELVA DEL PERU S.A. | N96: -0.0017288136 | O96: -0.00031118644 | P96: 11150.2 | S96: 11150.198 | W96: 3.436 | AB96: D | AC96: 3245.11 | AD96: 46159 | AE96: CRE | AF96: 6011021 | AH96: 4212 | AR96: 18 | AS96: EXISTENCIAS POR RECIBIR
A97: 46129 | B97: 46159 | C97: 01 | D97: 00FN01 | F97: 45011753 | G97: 6 | H97: 20100047218 | I97: BANCO DE CREDITO DEL PERU | N97: 0 | O97: 0 | P97: 10 | S97: 10 | AB97: S | AD97: 46159 | AE97: CRE | AF97: 6391094 | AH97: 4212 | AR97: 18 | AS97: PAGO COMISION
A98: 46129 | C98: 01 | D98: 00F001 | F98: 12686 | G98: 6 | H98: 10209907327 | I98: TORPOCO,MAYTA,HECTOR,ALFONSO | N98: 0 | O98: 0 | P98: 10 | S98: 10 | AB98: S | AE98: CON | AF98: 656009501 | AH98: 4212 | AR98: 18 | AS98: POR LA COMPRA DE COMBUSTIBLE
A99: 46129 | C99: 01 | D99: 00F001 | F99: 12687 | G99: 6 | H99: 10209907327 | I99: TORPOCO,MAYTA,HECTOR,ALFONSO | N99: 0 | O99: 0 | P99: 20 | S99: 20 | AB99: S | AE99: CON | AF99: 656009501 | AH99: 4212 | AR99: 18 | AS99: POR LA COMPRA DE COMBUSTIBLE
A100: 46129 | C100: 01 | D100: 00F001 | F100: 12688 | G100: 6 | H100: 10209907327 | I100: TORPOCO,MAYTA,HECTOR,ALFONSO | N100: 0 | O100: 0 | P100: 10 | S100: 10 | AB100: S | AE100: CON | AF100: 656009501 | AH100: 4212 | AR100: 18 | AS100: POR LA COMPRA DE COMBUSTIBLE
A101: 46130 | B101: 46160 | C101: 01 | D101: 00F001 | F101: 5277 | G101: 6 | H101: 10061702071 | I101: CORAL FLORES IVAN MARTIN | N101: 0 | O101: 0 | P101: 0 | R101: 410 | S101: 410 | AB101: S | AD101: 46160 | AE101: CRE | AF101: 6599095 | AG101: 1413 | AH101: 4212 | AR101: 18 | AS101: CERTIFICACION DE FIRMAS
A102: 46130 | C102: 01 | D102: 00F001 | F102: 119022 | G102: 6 | H102: 20568499043 | I102: SURTIDORES SAN MIGUEL E.I.R.L. | N102: 0 | O102: 0 | P102: 112 | S102: 112 | AB102: S | AE102: CON | AF102: 656009401 | AH102: 4212 | AR102: 18 | AS102: POR LA COMPRA DE COMBUSTIBLE
A103: 46132 | B103: 46162 | C103: 01 | D103: 00FF11 | F103: 17165 | G103: 6 | H103: 20487251985 | I103: CONTABILIDAD AUDITORIA, SISTEMAS, INNOVACION Y CONOCIMIENTO SOCIEDAD ANONIMA | N103: 847.45763 | O103: 152.54237 | P103: 0 | S103: 1000 | AB103: S | AD103: 46162 | AE103: CRE | AF103: 6329094 | AH103: 4212 | AR103: 18 | AS103: SISTEMA CONTABLE FINANCIERO,MIGRACION AL TERMINAL
A104: 46132 | C104: 01 | D104: 00F001 | F104: 119079 | G104: 6 | H104: 20568499043 | I104: SURTIDORES SAN MIGUEL E.I.R.L. | N104: 0 | O104: 0 | P104: 109.5 | S104: 109.5 | AB104: S | AE104: CON | AF104: 656009401 | AH104: 4212 | AR104: 18 | AS104: POR LA COMPRA DE COMBUSTIBLE
A105: 46133 | C105: 01 | D105: 00F010 | F105: 4908 | G105: 6 | H105: 20601012261 | I105: IMPORTADORA DE REPUESTOS LA ROCA E.I.R.L. | N105: 0 | O105: 0 | P105: 18 | S105: 18 | AB105: S | AE105: CON | AF105: 656009507 | AH105: 4212 | AR105: 18 | AS105: CALIBRADOR GAUGE TRUPER
A106: 46133 | B106: 46163 | C106: 01 | D106: 00FF01 | F106: 7462 | G106: 6 | H106: 20485976028 | I106: EMPRESA DE TRANSPORTES TROPICAL TOURS SCRL | N106: 0 | O106: 0 | P106: 0 | R106: 20 | S106: 20 | AB106: S | AD106: 46163 | AE106: CRE | AF106: 6599095 | AG106: 1413 | AH106: 4212 | AR106: 18 | AS106: SERVICIO DE TRANSPORTE DE PASAJERO
A107: 46133 | B107: 46163 | C107: 01 | D107: 00E001 | F107: 12550 | G107: 6 | H107: 20568968051 | I107: AUTOMOVIL SATIPO TOURS S.A.C. | N107: 0 | O107: 0 | P107: 0 | R107: 20 | S107: 20 | AB107: S | AD107: 46163 | AE107: CRE | AF107: 6599095 | AG107: 1413 | AH107: 4212 | AR107: 18 | AS107: SERVICIO DE TRANSPORTE DE PASAJERO
A108: 46133 | B108: 46163 | C108: 01 | D108: 00E001 | F108: 12545 | G108: 6 | H108: 20568968051 | I108: AUTOMOVIL SATIPO TOURS S.A.C. | N108: 0 | O108: 0 | P108: 0 | R108: 40 | S108: 40 | AB108: S | AD108: 46163 | AE108: CRE | AF108: 6599095 | AG108: 1413 | AH108: 4212 | AR108: 18 | AS108: SERVICIO DE TRANSPORTE DE PASAJERO
A109: 46134 | B109: 46164 | C109: 01 | D109: 00E001 | F109: 7182 | G109: 6 | H109: 10210648939 | I109: EGOAVIL,TORRES,EDITH,GINA | N109: 0 | O109: 0 | P109: 340 | S109: 340 | AB109: S | AD109: 46164 | AE109: CRE | AF109: 6322094 | AH109: 4212 | AR109: 18 | AS109: LEGALIZACION DE LIBRO INVENT.Y BALAN. ACTIVOS FIJOS,INVENT.
A110: 46134 | C110: 01 | D110: 00F001 | F110: 1087 | G110: 6 | H110: 20611936606 | I110: GAS VIVA EMPRESA INDIVIDUAL DE RESPONSABILIDAD LIMITADA | N110: 0 | O110: 0 | P110: 10 | S110: 10 | AB110: S | AE110: CON | AF110: 656009501 | AH110: 4212 | AR110: 18 | AS110: POR LA COMPRA DE COMBUSTIBLE
A111: 46134 | B111: 46164 | C111: 01 | D111: 00F005 | F111: 17866 | G111: 6 | H111: 20493508645 | I111: HONDA SELVA DEL PERU S.A. | N111: 0.0015254237 | O111: 0.00027457627 | P111: 33449.01 | S111: 33449.012 | W111: 3.442 | AB111: D | AC111: 9717.9 | AD111: 46164 | AE111: CRE | AF111: 6011021 | AH111: 4212 | AR111: 18 | AS111: EXISTENCIAS POR RECIBIR
A112: 46134 | B112: 46164 | C112: 01 | D112: 00F005 | F112: 17867 | G112: 6 | H112: 20493508645 | I112: HONDA SELVA DEL PERU S.A. | N112: 0.0015254237 | O112: 0.00027457627 | P112: 33449.01 | S112: 33449.012 | W112: 3.442 | AB112: D | AC112: 9717.9 | AD112: 46164 | AE112: CRE | AF112: 6011021 | AH112: 4212 | AR112: 18 | AS112: EXISTENCIAS POR RECIBIR
A113: 46134 | B113: 46164 | C113: 01 | D113: 00F005 | F113: 17864 | G113: 6 | H113: 20493508645 | I113: HONDA SELVA DEL PERU S.A. | N113: 0.0015254237 | O113: 0.00027457627 | P113: 33449.01 | S113: 33449.012 | W113: 3.442 | AB113: D | AC113: 9717.9 | AD113: 46164 | AE113: CRE | AF113: 6011021 | AH113: 4212 | AR113: 18 | AS113: EXISTENCIAS POR RECIBIR
...

Sheet MAYO
A1: FECHA DE EMISION DEL COMPROBANTE DE PAGO O DOCUMENTO | B1: FECHA DE VENCIMIENTO O FECHA DE PAGO | C1: COMPROBANTE DE PAGO O DOCUMENTO | F1: N° COMPROBANTE PAGO | G1: INFORMACION PROVEEDOR | J1: ADQUISICIONES GRAVADAS DESTINADAS A OPERACIONES GRAVADAS Y/O EXPORTACION | L1: ADQUISICIONES GRAVADAS DESTINADAS A OPERACIONES GRAVADAS Y/O DE EXPORTACION Y A OPERACIONES NO GRAVADAS | N1: ADQUISICIONES GRAVADAS DESTINADAS A OPERACIONES NO GRAVADAS | P1: VALOR DE LAS ADQUISICIONES NO GRAVADAS | Q1: ISC | R1: OTROS TRIBUTOS Y CARGOS | S1: IMPORTE TOTAL | T1: N° COMPROBANTE DE PAGO EMITIDO POR SUJETO NO DOMICILIADO | U1: CONSTANCIA DE DEPOSITO DE DETRACCION | W1: TIPO DE CAMBIO | X1: REFERENCIA DEL COMPROBANTE DE PAGO O DOCUMENTO ORIGINAL QUE SE MODIFICA | AB1: MONEDA | AC1: EQUIVALENTE EN DOLARES AMERICANOS | AD1: FECHA VENCIMIENTO | AE1: CONDICION CONTADO/CREDITO | AF1: CUENTA CONTABLE BASE IMPONIBLE | AG1: CUENTA CONTABLE OTROS TRIBUTOS Y CARGOS | AH1: CUENTA CONTABLE TOTAL | AI1: CODIGO CENTRO DE COSTOS | AJ1: CODIGO CENTRO DE COSTOS 2 | AK1: REGIMEN ESPECIAL | AL1: PORCENTAJE REGIMEN ESPECIAL | AM1: IMPORTE REGIMEN ESPECIAL | AN1: SERIE DOCUMENTO REGIMEN ESPECIAL | AO1: NUMERO DOCUMENTO REGIMEN ESPECIAL | AP1: FECHA DOCUMENTO REGIMEN ESPECIAL | AQ1: CODIGO PRESUPUESTO | AR1: PORCENTAJE I.G.V. | AS1: GLOSA | AT1: CONDICIÓN DE PERCEPCIÓN | AU1: IMPORTE RÉGIMEN ESPECIAL | AV1: CLASIFICACIÓN DE BIENES Y SERVICIOS ADQUIRIDOS
G2: DOCUMENTO IDENTIDAD | I2: APELLIDOS Y NOMBRES, DENOMINACION O RAZON SOCIAL
C3: TIPO | D3: SERIE/CODIGO ADUANA | E3: AÑO EMISION DUA O DSI | G3: TIPO | H3: NUMERO | J3: BASE IMPONIBLE | K3: IGV | L3: BASE IMPONIBLE | M3: IGV | N3: BASE IMPONIBLE | O3: IGV | U3: NUMERO | V3: FECHA EMISION | X3: FECHA | Y3: TIPO | Z3: SERIE | AA3: N° COMPROBANTE PAGO O DOCUMENTO
A4: 46132 | B4: 46162 | C4: 14 | D4: 00SB02 | F4: 281541476 | G4: 6 | H4: 20467534026 | I4: =IF(H4="","",VLOOKUP(H4,[1]ENTIDAD!$B$2:$C$605,2,0)) -> AMERICA MOVIL PERU S.A.C. | N4: =(S4-P4)/1.18 -> 25.338983 | O4: =N4*0.18 -> 4.5610169 | P4: 0 | S4: 29.9 | AB4: S | AD4: 46162 | AE4: CRE | AF4: 6365095 | AH4: 4212 | AR4: 18 | AS4: SERVICIO DE TELEFONICA
A5: 46140 | B5: 46170 | C5: 14 | D5: 00S898 | F5: 5768340 | G5: 6 | H5: 20129646099 | I5: =IF(H5="","",VLOOKUP(H5,[1]ENTIDAD!$B$2:$C$605,2,0)) -> ELECTROCENTRO S.A. | N5: =(S5-P5)/1.18 -> 0 | O5: =N5*0.18 -> 0 | P5: 406 | S5: 406 | AB5: S | AD5: 46170 | AE5: CRE | AF5: 6361095 | AH5: 4212 | AR5: 18 | AS5: SERVICIO DE ENERGIA ELECTRICA
A6: 46140 | B6: 46170 | C6: 14 | D6: 00S898 | F6: 5768345 | G6: 6 | H6: 20129646099 | I6: =IF(H6="","",VLOOKUP(H6,[1]ENTIDAD!$B$2:$C$605,2,0)) -> ELECTROCENTRO S.A. | N6: =(S6-P6)/1.18 -> 0 | O6: =N6*0.18 -> 0 | P6: 97.6 | S6: 97.6 | AB6: S | AD6: 46170 | AE6: CRE | AF6: 6361095 | AH6: 4212 | AR6: 18 | AS6: SERVICIO DE ENERGIA ELECTRICA
A7: 46140 | B7: 46156 | C7: 14 | D7: 0S898 | F7: 5768563 | G7: 6 | H7: 20129646099 | I7: =IF(H7="","",VLOOKUP(H7,ENTIDAD!$B$2:$C$613,2,0)) -> ELECTROCENTRO S.A. | N7: =(S7-P7)/1.18 -> 0 | O7: =N7*0.18 -> 0 | P7: 1215.2 | S7: 1215.2 | AB7: S | AD7: 46156 | AE7: CRE | AF7: 6361095 | AH7: 4212 | AR7: 18 | AS7: SERVICIO DE ENERGIA ELECTRICA
A8: 46142 | B8: 46172 | C8: 14 | D8: 00S060 | F8: 1067341 | G8: 6 | H8: 20121876290 | I8: =IF(H8="","",VLOOKUP(H8,[1]ENTIDAD!$B$2:$C$605,2,0)) -> ENT.PREST.SERV.SANEAM.SELVA CENTRAL S.A | N8: =(S8-P8)/1.18 -> 0 | O8: =N8*0.18 -> 0 | P8: 18.5 | S8: 18.5 | AB8: S | AD8: 46172 | AE8: CRE | AF8: 6363095 | AH8: 4212 | AR8: 18 | AS8: SERVICIO DE AGUA
A9: 46142 | B9: 46173 | C9: 14 | D9: 005060 | F9: 1068092 | G9: 6 | H9: 20121876290 | I9: =IF(H9="","",VLOOKUP(H9,ENTIDAD!$B$2:$C$613,2,0)) -> ENT.PREST.SERV.SANEAM.SELVA CENTRAL S.A | N9: =(S9-P9)/1.18 -> 0 | O9: =N9*0.18 -> 0 | P9: 50.6 | S9: 50.6 | AB9: S | AD9: 46173 | AE9: CRE | AF9: 6363095 | AH9: 4212 | AR9: 18 | AS9: SERVICIO DE AGUA
A10: 46143 | C10: 01 | D10: 00F001 | F10: 4440 | G10: 6 | H10: 20607418790 | I10: =IF(H10="","",VLOOKUP(H10,[1]ENTIDAD!$B$2:$C$605,2,0)) -> BROASTER SATIPO EMPRESA INDIVIDUAL DE RESP. LTDA | N10: =(S10-P10)/1.18 -> 0 | O10: =N10*0.18 -> 0 | P10: 174 | S10: 174 | AB10: S | AD10: 46143 | AE10: CON | AF10: 6250095 | AH10: 4212 | AR10: 18 | AS10: CONSUMO
A11: 46143 | B11: 46174 | C11: 14 | D11: 00SB01 | F11: 623010998 | G11: 6 | H11: 20467534026 | I11: =IF(H11="","",VLOOKUP(H11,[1]ENTIDAD!$B$2:$C$605,2,0)) -> AMERICA MOVIL PERU S.A.C. | N11: =(S11-P11)/1.18 -> 75.423729 | O11: =N11*0.18 -> 13.576271 | P11: 0 | S11: 89 | AB11: S | AD11: 46174 | AE11: CRE | AF11: 6365095 | AH11: 4212 | AR11: 18 | AS11: SERVICIO DE TELEFONICA
A12: 46143 | C12: 01 | D12: 00F001 | F12: 4985438 | G12: 6 | H12: 20432405525 | I12: =IF(H12="","",VLOOKUP(H12,ENTIDAD!$B$2:$C$613,2,0)) -> PROCESOS DE MEDIOS DE PAGO S.A. | N12: =(S12-P12)/1.18 -> 1 | O12: =N12*0.18 -> 0.18 | P12: 0 | S12: 1.18 | AB12: S | AD12: 46174 | AE12: CRE | AF12: 6391094 | AH12: 4212 | AR12: 18 | AS12: MANTE.POS-PERIODO 2026/4
A13: 46144 | B13: =AD13 -> 46174 | C13: 01 | D13: 00F003 | F13: 3828340 | G13: 6 | H13: 20101973922 | I13: =IF(H13="","",VLOOKUP(H13,[1]ENTIDAD!$B$2:$C$605,2,0)) -> ASOCIACION AUTOMOTRIZ DEL PERU | N13: =(S13-P13)/1.18 -> 56.610169 | O13: =N13*0.18 -> 10.189831 | P13: 0 | R13: 66.8 | S13: 66.8 | AB13: S | AD13: =A13+30 -> 46174 | AE13: CRE | AF13: 6599095 | AG13: 1413 | AH13: 4212 | AR13: 18 | AS13: POR DERECHO DE EMISION DE PLACA DE RODAJE
A14: 46144 | B14: =AD14 -> 46174 | C14: 01 | D14: 00F003 | F14: 3828339 | G14: 6 | H14: 20101973922 | I14: =IF(H14="","",VLOOKUP(H14,[1]ENTIDAD!$B$2:$C$605,2,0)) -> ASOCIACION AUTOMOTRIZ DEL PERU | N14: =(S14-P14)/1.18 -> 56.610169 | O14: =N14*0.18 -> 10.189831 | P14: 0 | R14: 66.8 | S14: 66.8 | AB14: S | AD14: =A14+30 -> 46174 | AE14: CRE | AF14: 6599095 | AG14: 1413 | AH14: 4212 | AR14: 18 | AS14: POR DERECHO DE EMISION DE PLACA DE RODAJE
A15: 46144 | B15: =AD15 -> 46174 | C15: 01 | D15: 00F003 | F15: 3828338 | G15: 6 | H15: 20101973922 | I15: =IF(H15="","",VLOOKUP(H15,[1]ENTIDAD!$B$2:$C$605,2,0)) -> ASOCIACION AUTOMOTRIZ DEL PERU | N15: =(S15-P15)/1.18 -> 56.610169 | O15: =N15*0.18 -> 10.189831 | P15: 0 | R15: 66.8 | S15: 66.8 | AB15: S | AD15: =A15+30 -> 46174 | AE15: CRE | AF15: 6599095 | AG15: 1413 | AH15: 4212 | AR15: 18 | AS15: POR DERECHO DE EMISION DE PLACA DE RODAJE
A16: 46144 | B16: =AD16 -> 46174 | C16: 01 | D16: 00F003 | F16: 3828337 | G16: 6 | H16: 20101973922 | I16: =IF(H16="","",VLOOKUP(H16,[1]ENTIDAD!$B$2:$C$605,2,0)) -> ASOCIACION AUTOMOTRIZ DEL PERU | N16: =(S16-P16)/1.18 -> 56.610169 | O16: =N16*0.18 -> 10.189831 | P16: 0 | R16: 66.8 | S16: 66.8 | AB16: S | AD16: =A16+30 -> 46174 | AE16: CRE | AF16: 6599095 | AG16: 1413 | AH16: 4212 | AR16: 18 | AS16: POR DERECHO DE EMISION DE PLACA DE RODAJE
A17: 46144 | B17: =AD17 -> 46174 | C17: 01 | D17: 00F003 | F17: 3828336 | G17: 6 | H17: 20101973922 | I17: =IF(H17="","",VLOOKUP(H17,[1]ENTIDAD!$B$2:$C$605,2,0)) -> ASOCIACION AUTOMOTRIZ DEL PERU | N17: =(S17-P17)/1.18 -> 56.610169 | O17: =N17*0.18 -> 10.189831 | P17: 0 | R17: 66.8 | S17: 66.8 | AB17: S | AD17: =A17+30 -> 46174 | AE17: CRE | AF17: 6599095 | AG17: 1413 | AH17: 4212 | AR17: 18 | AS17: POR DERECHO DE EMISION DE PLACA DE RODAJE
A18: 46144 | B18: =AD18 -> 46174 | C18: 01 | D18: 00F003 | F18: 3828335 | G18: 6 | H18: 20101973922 | I18: =IF(H18="","",VLOOKUP(H18,[1]ENTIDAD!$B$2:$C$605,2,0)) -> ASOCIACION AUTOMOTRIZ DEL PERU | N18: =(S18-P18)/1.18 -> 56.610169 | O18: =N18*0.18 -> 10.189831 | P18: 0 | R18: 66.8 | S18: 66.8 | AB18: S | AD18: =A18+30 -> 46174 | AE18: CRE | AF18: 6599095 | AG18: 1413 | AH18: 4212 | AR18: 18 | AS18: POR DERECHO DE EMISION DE PLACA DE RODAJE
A19: 46144 | B19: =AD19 -> 46174 | C19: 01 | D19: 00F003 | F19: 3828334 | G19: 6 | H19: 20101973922 | I19: =IF(H19="","",VLOOKUP(H19,[1]ENTIDAD!$B$2:$C$605,2,0)) -> ASOCIACION AUTOMOTRIZ DEL PERU | N19: =(S19-P19)/1.18 -> 56.610169 | O19: =N19*0.18 -> 10.189831 | P19: 0 | R19: 66.8 | S19: 66.8 | AB19: S | AD19: =A19+30 -> 46174 | AE19: CRE | AF19: 6599095 | AG19: 1413 | AH19: 4212 | AR19: 18 | AS19: POR DERECHO DE EMISION DE PLACA DE RODAJE
A20: 46144 | B20: =AD20 -> 46174 | C20: 01 | D20: 00F003 | F20: 3828333 | G20: 6 | H20: 20101973922 | I20: =IF(H20="","",VLOOKUP(H20,[1]ENTIDAD!$B$2:$C$605,2,0)) -> ASOCIACION AUTOMOTRIZ DEL PERU | N20: =(S20-P20)/1.18 -> 56.610169 | O20: =N20*0.18 -> 10.189831 | P20: 0 | R20: 66.8 | S20: 66.8 | AB20: S | AD20: =A20+30 -> 46174 | AE20: CRE | AF20: 6599095 | AG20: 1413 | AH20: 4212 | AR20: 18 | AS20: POR DERECHO DE EMISION DE PLACA DE RODAJE
A21: 46144 | B21: =AD21 -> 46174 | C21: 01 | D21: 00F003 | F21: 3828332 | G21: 6 | H21: 20101973922 | I21: =IF(H21="","",VLOOKUP(H21,[1]ENTIDAD!$B$2:$C$605,2,0)) -> ASOCIACION AUTOMOTRIZ DEL PERU | N21: =(S21-P21)/1.18 -> 56.610169 | O21: =N21*0.18 -> 10.189831 | P21: 0 | R21: 66.8 | S21: 66.8 | AB21: S | AD21: =A21+30 -> 46174 | AE21: CRE | AF21: 6599095 | AG21: 1413 | AH21: 4212 | AR21: 18 | AS21: POR DERECHO DE EMISION DE PLACA DE RODAJE
A22: 46144 | B22: =AD22 -> 46174 | C22: 01 | D22: 00F003 | F22: 3828331 | G22: 6 | H22: 20101973922 | I22: =IF(H22="","",VLOOKUP(H22,[1]ENTIDAD!$B$2:$C$605,2,0)) -> ASOCIACION AUTOMOTRIZ DEL PERU | N22: =(S22-P22)/1.18 -> 56.610169 | O22: =N22*0.18 -> 10.189831 | P22: 0 | R22: 66.8 | S22: 66.8 | AB22: S | AD22: =A22+30 -> 46174 | AE22: CRE | AF22: 6599095 | AG22: 1413 | AH22: 4212 | AR22: 18 | AS22: POR DERECHO DE EMISION DE PLACA DE RODAJE
A23: 46144 | B23: =AD23 -> 46174 | C23: 01 | D23: 00F003 | F23: 3828330 | G23: 6 | H23: 20101973922 | I23: =IF(H23="","",VLOOKUP(H23,[1]ENTIDAD!$B$2:$C$605,2,0)) -> ASOCIACION AUTOMOTRIZ DEL PERU | N23: =(S23-P23)/1.18 -> 56.610169 | O23: =N23*0.18 -> 10.189831 | P23: 0 | R23: 66.8 | S23: 66.8 | AB23: S | AD23: =A23+30 -> 46174 | AE23: CRE | AF23: 6599095 | AG23: 1413 | AH23: 4212 | AR23: 18 | AS23: POR DERECHO DE EMISION DE PLACA DE RODAJE
A24: 46144 | B24: =AD24 -> 46174 | C24: 01 | D24: 00F003 | F24: 3828329 | G24: 6 | H24: 20101973922 | I24: =IF(H24="","",VLOOKUP(H24,[1]ENTIDAD!$B$2:$C$605,2,0)) -> ASOCIACION AUTOMOTRIZ DEL PERU | N24: =(S24-P24)/1.18 -> 56.610169 | O24: =N24*0.18 -> 10.189831 | P24: 0 | R24: 66.8 | S24: 66.8 | AB24: S | AD24: =A24+30 -> 46174 | AE24: CRE | AF24: 6599095 | AG24: 1413 | AH24: 4212 | AR24: 18 | AS24: POR DERECHO DE EMISION DE PLACA DE RODAJE
... A38: 46144 | B38: =AD38 -> 46174 | C38: 01 | D38: 00F003 | F38: 3828315 | G38: 6 | H38: 20101973922 | I38: =IF(H38="","",VLOOKUP(H38,[1]ENTIDAD!$B$2:$C$605,2,0)) -> ASOCIACION AUTOMOTRIZ DEL PERU | N38: =(S38-P38)/1.18 -> 56.610169 | O38: =N38*0.18 -> 10.189831 | P38: 0 | R38: 66.8 | S38: 66.8 | AB38: S | AD38: =A38+30 -> 46174 | AE38: CRE | AF38: 6599095 | AG38: 1413 | AH38: 4212 | AR38: 18 | AS38: POR DERECHO DE EMISION DE PLACA DE RODAJE
A39: 46146 | B39: =AD39 -> 46177 | C39: 01 | D39: 00FC03 | F39: 6767109 | G39: 6 | H39: 20100047218 | I39: =IF(H39="","",VLOOKUP(H39,[1]ENTIDAD!$B$2:$C$605,2,0)) -> BANCO DE CREDITO DEL PERU | N39: =(S39-P39)/1.18 -> 0 | O39: =N39*0.18 -> 0 | P39: 10 | S39: 10 | AB39: S | AD39: 46177 | AE39: CRE | AF39: 6391094 | AH39: 4212 | AR39: 18 | AS39: PAGO GASTOS POR APORTE
A40: 46146 | B40: =AD40 -> 46177 | C40: 01 | D40: 00FB27 | F40: 27179760 | G40: 6 | H40: 20100130204 | I40: =IF(H40="","",VLOOKUP(H40,[1]ENTIDAD!$B$2:$C$605,2,0)) -> BANCO BBVA PERU | N40: =(S40-P40)/1.18 -> 0 | O40: =N40*0.18 -> 0 | P40: 10 | S40: 10 | AB40: S | AD40: 46177 | AE40: CRE | AF40: 6391094 | AH40: 4212 | AR40: 18 | AS40: POR COMISION Y MANTENIMIENTO
A41: 46146 | B41: =AD41 -> 46177 | C41: 01 | D41: 00E001 | F41: 1875 | G41: 6 | H41: 20486339510 | I41: =IF(H41="","",VLOOKUP(H41,[1]ENTIDAD!$B$2:$C$605,2,0)) -> SERVICIOS CONTABLES Y AUDITORIA INTERNA S.A. | N41: 0 | O41: =N41*0.18 -> 0 | P41: 2000 | S41: 2000 | AB41: S | AD41: 46177 | AE41: CRE | AF41: 6323094 | AH41: 4212 | AR41: 18 | AS41: SERVICIO CONTABLE
A42: 46146 | B42: =AD42 -> 46177 | C42: 01 | D42: 00E001 | F42: 194 | G42: 6 | H42: 20444327066 | I42: =IF(H42="","",VLOOKUP(H42,[1]ENTIDAD!$B$2:$C$605,2,0)) -> CAMARA DE COMERCIO E INDUSTRIAS SATIPO | N42: =(S42-P42)/1.18 -> 0 | O42: =N42*0.18 -> 0 | P42: 72 | S42: 72 | AB42: S | AD42: 46177 | AE42: CRE | AF42: 6591094 | AH42: 4212 | AR42: 18 | AS42: DONACION POR APOYO Y EFICIENTE ATENCION AL CLIENTE
A43: 46146 | B43: =AD43 -> 46177 | C43: 01 | D43: 00E001 | F43: 219 | G43: 6 | H43: 10447422951 | I43: =IF(H43="","",VLOOKUP(H43,[1]ENTIDAD!$B$2:$C$605,2,0)) -> ZEGARRA AZAÑERO JORGE KEY | N43: =(S43-P43)/1.18 -> 0 | O43: =N43*0.18 -> 0 | P43: 450 | S43: 450 | AB43: S | AD43: 46177 | AE43: CRE | AF43: 6329094 | AH43: 4212 | AR43: 18 | AS43: SORPORTE MENSUAL ABRIL 2026
A44: 46147 | B44: =AD44 -> 46178 | C44: 01 | D44: 00FE01 | F44: 2844202 | G44: 6 | H44: 20100047218 | I44: =IF(H44="","",VLOOKUP(H44,[1]ENTIDAD!$B$2:$C$605,2,0)) -> BANCO DE CREDITO DEL PERU | N44: =(S44-P44)/1.18 -> 0 | O44: =N44*0.18 -> 0 | P44: 123.27 | S44: =W44*AC44 -> 123.27 | W44: 3.522 | AB44: D | AC44: 35 | AD44: 46178 | AE44: CRE | AF44: 6391094 | AH44: 4212 | AR44: 18 | AS44: MANTENIMIENTO
A45: 46147 | C45: 01 | D45: 00F002 | F45: 38016 | G45: 6 | H45: 20510435452 | I45: =IF(H45="","",VLOOKUP(H45,[1]ENTIDAD!$B$2:$C$605,2,0)) -> MULTISERVICIOS SEÑOR DE LOS MILAGROS S.C.R.L. | N45: =(S45-P45)/1.18 -> 0 | O45: =N45*0.18 -> 0 | P45: 100 | S45: 100 | AB45: S | AD45: 46147 | AE45: CON | AF45: 656009501 | AH45: 4212 | AR45: 18 | AS45: COMBUSTIBLE
A46: 46147 | B46: =AD46 -> 46178 | C46: 01 | D46: 00FC05 | F46: 5057126 | G46: 6 | H46: 20100130204 | I46: =IF(H46="","",VLOOKUP(H46,[1]ENTIDAD!$B$2:$C$605,2,0)) -> BANCO BBVA PERU | N46: =(S46-P46)/1.18 -> 0 | O46: =N46*0.18 -> 0 | P46: 40 | S46: 40 | AB46: S | AD46: 46178 | AE46: CRE | AF46: 6391094 | AH46: 4212 | AR46: 18 | AS46: COMISION
A47: 46148 | B47: =AD47 -> 46179 | C47: 01 | D47: 00FV13 | F47: 1372737 | G47: 6 | H47: 20100047218 | I47: =IF(H47="","",VLOOKUP(H47,[1]ENTIDAD!$B$2:$C$605,2,0)) -> BANCO DE CREDITO DEL PERU | N47: 0 | O47: =N47*0.18 -> 0 | P47: 116 | S47: 116 | AB47: S | AD47: 46179 | AE47: CRE | AF47: 6391094 | AH47: 4212 | AR47: 18 | AS47: MANTENIMIENTO, PAGO POR EXCESO , APORT.XESTADO
A48: 46148 | B48: =AD48 -> 46179 | C48: 01 | D48: 00F002 | F48: 150 | G48: 6 | H48: 20600454065 | I48: =IF(H48="","",VLOOKUP(H48,[1]ENTIDAD!$B$2:$C$605,2,0)) -> REPUESTOS Y SERVICIOS ARAUCO E.I.R.L. | N48: =(S48-P48)/1.18 -> 0 | O48: =N48*0.18 -> 0 | P48: 1800 | S48: 1800 | AB48: S | AD48: 46179 | AE48: CRE | AF48: 6343095 | AG48: 1413 | AH48: 4212 | AR48: 18 | AS48: MANTENIMIENTO DE MOTOS VENDIDAS - GARANTIA
A49: 46148 | B49: =AD49 -> 46179 | C49: 01 | D49: 00F001 | F49: 177 | G49: 6 | H49: 20568818751 | I49: =IF(H49="","",VLOOKUP(H49,[1]ENTIDAD!$B$2:$C$605,2,0)) -> P & F ARTEFACTOS S.R.L. | N49: =(S49-P49)/1.18 -> 0 | O49: =N49*0.18 -> 0 | P49: 1250 | S49: 1250 | AB49: S | AD49: 46179 | AE49: CRE | AF49: 6560094 | AH49: 4212 | AR49: 18 | AS49: LAPTOP 14"INTEL CORE 3.4GB 128GB
A50: 46148 | B50: =AD50 -> 46179 | C50: 01 | D50: 00F001 | F50: 773 | G50: 6 | H50: 10733910921 | I50: =IF(H50="","",VLOOKUP(H50,[1]ENTIDAD!$B$2:$C$605,2,0)) -> MADUEÑO HUAMAN LILI CLISSELY | N50: =(S50-P50)/1.18 -> 0 | O50: =N50*0.18 -> 0 | P50: 12 | S50: 12 | AB50: S | AD50: 46179 | AE50: CRE | AF50: 6560095 | AH50: 4212 | AR50: 18 | AS50: DADO EXAGONAL TUBULAR ENC 12 X 11MM
A51: 46149 | C51: 01 | D51: 00F001 | F51: 2388 | G51: 6 | H51: 20604975159 | I51: =IF(H51="","",VLOOKUP(H51,[1]ENTIDAD!$B$2:$C$605,2,0)) -> CORPORACION CARELI EMPRESA INDIVIDUAL DE RESPONSABILIDAD LIMITADA - CORPORACION CARELI E.I.R.L. | N51: =(S51-P51)/1.18 -> 0 | O51: =N51*0.18 -> 0 | P51: 28 | S51: 28 | AB51: S | AD51: 46149 | AE51: CON | AF51: 656009503 | AH51: 4212 | AR51: 18 | AS51: COMPRA MAUSE , PAD PMOUSE
A52: 46149 | B52: =AD52 -> 46179 | C52: 01 | D52: 00F005 | F52: 18166 | G52: 6 | H52: 20493508645 | I52: =IF(H52="","",VLOOKUP(H52,[1]ENTIDAD!$B$2:$C$605,2,0)) -> HONDA SELVA DEL PERU S.A. | N52: 0 | O52: =N52*0.18 -> 0 | P52: 77264.96 | S52: =W52*AC52 -> 77264.963 | W52: 3.47 | AB52: D | AC52: 22266.56 | AD52: =A52+30 -> 46179 | AE52: CRE | AF52: 6011021 | AH52: 4212 | AR52: 18 | AS52: EXISTENCIAS POR RECIBIR
A53: 46149 | B53: =AD53 -> 46180 | C53: 01 | D53: 00FI01 | F53: 19377183 | G53: 6 | H53: 20100047218 | I53: =IF(H53="","",VLOOKUP(H53,[1]ENTIDAD!$B$2:$C$605,2,0)) -> BANCO DE CREDITO DEL PERU | N53: =(S53-P53)/1.18 -> 0 | O53: =N53*0.18 -> 0 | P53: 943.79 | S53: 943.79 | AB53: S | AD53: 46180 | AE53: CRE | AF53: 6391094 | AH53: 4212 | AR53: 18 | AS53: PORTES. COMISIONES
A54: 46149 | B54: =AD54 -> 46180 | C54: 01 | D54: 00E001 | F54: 14 | G54: 6 | H54: 10420868168 | I54: =IF(H54="","",VLOOKUP(H54,[1]ENTIDAD!$B$2:$C$605,2,0)) -> #N/A | N54: =(S54-P54)/1.18 -> 0 | O54: =N54*0.18 -> 0 | P54: 180 | S54: 180 | AB54: S | AD54: 46180 | AE54: CRE | AF54: 6341094 | AH54: 4212 | AR54: 18 | AS54: PLANCHADO Y RETOQUE DE TOLVA
A55: 46149 | C55: 01 | D55: 00E001 | F55: 6176 | G55: 6 | H55: 20602783341 | I55: =IF(H55="","",VLOOKUP(H55,[1]ENTIDAD!$B$2:$C$605,2,0)) -> CODISSER VRAEM E.I.R.L. | N55: =(S55-P55)/1.18 -> 0 | O55: =N55*0.18 -> 0 | P55: 8 | S55: 8 | AB55: S | AD55: 46149 | AE55: CON | AF55: 6250095 | AH55: 4212 | AR55: 18 | AS55: AGUA DE MESA
A56: 46149 | B56: =AD56 -> 46180 | C56: 01 | D56: 00E001 | F56: 232 | G56: 6 | H56: 10447422951 | I56: =IF(H56="","",VLOOKUP(H56,[1]ENTIDAD!$B$2:$C$605,2,0)) -> ZEGARRA AZAÑERO JORGE KEY | N56: =(S56-P56)/1.18 -> 0 | O56: =N56*0.18 -> 0 | P56: 450 | S56: 450 | AB56: S | AD56: 46180 | AE56: CRE | AF56: 6560094 | AH56: 4212 | AR56: 18 | AS56: DISCO DURO ,SOLIDO HIKSEN SATA 256 GB,FORMATEO
A57: 46150 | C57: 01 | D57: 00F002 | F57: 17842 | G57: 6 | H57: 20605377115 | I57: =IF(H57="","",VLOOKUP(H57,ENTIDAD!$B$2:$C$613,2,0)) -> CORPORACIÓN FERNANDO´S E.I.R.L. | N57: =(S57-P57)/1.18 -> 0 | O57: =N57*0.18 -> 0 | P57: 20 | S57: 20 | AB57: S | AD57: 46150 | AE57: CON | AF57: 656009501 | AH57: 4212 | AR57: 18 | AS57: COMBUSTIBLE
A58: 46153 | B58: =AD58 -> 46183 | C58: 01 | D58: 00F005 | F58: 18187 | G58: 6 | H58: 20493508645 | I58: =IF(H58="","",VLOOKUP(H58,[1]ENTIDAD!$B$2:$C$605,2,0)) -> HONDA SELVA DEL PERU S.A. | N58: 0 | O58: =N58*0.18 -> 0 | P58: 9073.72 | S58: =AC58*W58 -> 9073.715 | W58: 3.5 | AB58: D | AC58: 2592.49 | AD58: =A58+30 -> 46183 | AE58: CRE | AF58: 6011021 | AH58: 4212 | AR58: 18 | AS58: EXISTENCIAS POR RECIBIR
A59: 46153 | C59: 02 | D59: 00E001 | F59: 1762 | G59: 6 | H59: 10200832049 | I59: =IF(H59="","",VLOOKUP(H59,[1]ENTIDAD!$B$2:$C$605,2,0)) -> #N/A | N59: =(S59-P59)/1.18 -> 0 | O59: =N59*0.18 -> 0 | P59: 300 | S59: 300 | AB59: S | AD59: 46184 | AE59: CRE | AF59: 6314094 | AH59: 4212 | AR59: 18 | AS59: VIATICOS
A60: 46153 | B60: =AD60 -> 46184 | C60: 01 | D60: 00F005 | F60: 18179 | G60: 6 | H60: 20493508645 | I60: =IF(H60="","",VLOOKUP(H60,[1]ENTIDAD!$B$2:$C$605,2,0)) -> HONDA SELVA DEL PERU S.A. | N60: =(S60-P60)/1.18 -> 0.00042372882 | O60: =N60*0.18 -> 7.6271187e-05 | P60: 59102.26 | S60: =W60*AC60 -> 59102.261 | W60: 3.45 | AB60: D | AC60: 17131.09 | AD60: 46184 | AE60: CRE | AF60: 6011021 | AH60: 4212 | AR60: 18 | AS60: EXISTENCIAS POR RECIBIR
A61: 46153 | B61: =AD61 -> 46184 | C61: 01 | D61: 00F005 | F61: 18183 | G61: 6 | H61: 20493508645 | I61: =IF(H61="","",VLOOKUP(H61,[1]ENTIDAD!$B$2:$C$605,2,0)) -> HONDA SELVA DEL PERU S.A. | N61: =(S61-P61)/1.18 -> -0.0042372881 | O61: =N61*0.18 -> -0.00076271187 | P61: 33526.76 | S61: =W61*AC61 -> 33526.755 | W61: 3.45 | AB61: D | AC61: 9717.9 | AD61: 46184 | AE61: CRE | AF61: 6011021 | AH61: 4212 | AR61: 18 | AS61: EXISTENCIAS POR RECIBIR
A62: 46153 | B62: =AD62 -> 46184 | C62: 01 | D62: 00F003 | F62: 3846191 | G62: 6 | H62: 20101973922 | I62: =IF(H62="","",VLOOKUP(H62,[1]ENTIDAD!$B$2:$C$605,2,0)) -> ASOCIACION AUTOMOTRIZ DEL PERU | N62: =(S62-P62)/1.18 -> 56.610169 | O62: =N62*0.18 -> 10.189831 | P62: 0 | R62: 66.8 | S62: 66.8 | AB62: S | AD62: 46184 | AE62: CRE | AF62: 6599095 | AG62: 1413 | AH62: 4212 | AR62: 18 | AS62: POR DERECHO DE EMISION DE PLACA DE RODAJE
A63: 46153 | B63: =AD63 -> 46184 | C63: 01 | D63: 00F003 | F63: 3846192 | G63: 6 | H63: 20101973922 | I63: =IF(H63="","",VLOOKUP(H63,[1]ENTIDAD!$B$2:$C$605,2,0)) -> ASOCIACION AUTOMOTRIZ DEL PERU | N63: =(S63-P63)/1.18 -> 56.610169 | O63: =N63*0.18 -> 10.189831 | P63: 0 | R63: 66.8 | S63: 66.8 | AB63: S | AD63: 46184 | AE63: CRE | AF63: 6599095 | AG63: 1413 | AH63: 4212 | AR63: 18 | AS63: POR DERECHO DE EMISION DE PLACA DE RODAJE
A64: 46153 | B64: =AD64 -> 46184 | C64: 01 | D64: 00F003 | F64: 3846193 | G64: 6 | H64: 20101973922 | I64: =IF(H64="","",VLOOKUP(H64,[1]ENTIDAD!$B$2:$C$605,2,0)) -> ASOCIACION AUTOMOTRIZ DEL PERU | N64: =(S64-P64)/1.18 -> 56.610169 | O64: =N64*0.18 -> 10.189831 | P64: 0 | R64: 66.8 | S64: 66.8 | AB64: S | AD64: 46184 | AE64: CRE | AF64: 6599095 | AG64: 1413 | AH64: 4212 | AR64: 18 | AS64: POR DERECHO DE EMISION DE PLACA DE RODAJE
A65: 46153 | B65: =AD65 -> 46184 | C65: 01 | D65: 00F003 | F65: 3846194 | G65: 6 | H65: 20101973922 | I65: =IF(H65="","",VLOOKUP(H65,[1]ENTIDAD!$B$2:$C$605,2,0)) -> ASOCIACION AUTOMOTRIZ DEL PERU | N65: =(S65-P65)/1.18 -> 56.610169 | O65: =N65*0.18 -> 10.189831 | P65: 0 | R65: 66.8 | S65: 66.8 | AB65: S | AD65: 46184 | AE65: CRE | AF65: 6599095 | AG65: 1413 | AH65: 4212 | AR65: 18 | AS65: POR DERECHO DE EMISION DE PLACA DE RODAJE
A66: 46153 | B66: =AD66 -> 46184 | C66: 01 | D66: 00F003 | F66: 3846195 | G66: 6 | H66: 20101973922 | I66: =IF(H66="","",VLOOKUP(H66,[1]ENTIDAD!$B$2:$C$605,2,0)) -> ASOCIACION AUTOMOTRIZ DEL PERU | N66: =(S66-P66)/1.18 -> 56.610169 | O66: =N66*0.18 -> 10.189831 | P66: 0 | R66: 66.8 | S66: 66.8 | AB66: S | AD66: 46184 | AE66: CRE | AF66: 6599095 | AG66: 1413 | AH66: 4212 | AR66: 18 | AS66: POR DERECHO DE EMISION DE PLACA DE RODAJE
A67: 46153 | B67: =AD67 -> 46184 | C67: 01 | D67: 00F003 | F67: 3846196 | G67: 6 | H67: 20101973922 | I67: =IF(H67="","",VLOOKUP(H67,[1]ENTIDAD!$B$2:$C$605,2,0)) -> ASOCIACION AUTOMOTRIZ DEL PERU | N67: =(S67-P67)/1.18 -> 56.610169 | O67: =N67*0.18 -> 10.189831 | P67: 0 | R67: 66.8 | S67: 66.8 | AB67: S | AD67: 46184 | AE67: CRE | AF67: 6599095 | AG67: 1413 | AH67: 4212 | AR67: 18 | AS67: POR DERECHO DE EMISION DE PLACA DE RODAJE
A68: 46153 | B68: =AD68 -> 46184 | C68: 01 | D68: 00F003 | F68: 3846197 | G68: 6 | H68: 20101973922 | I68: =IF(H68="","",VLOOKUP(H68,[1]ENTIDAD!$B$2:$C$605,2,0)) -> ASOCIACION AUTOMOTRIZ DEL PERU | N68: =(S68-P68)/1.18 -> 56.610169 | O68: =N68*0.18 -> 10.189831 | P68: 0 | R68: 66.8 | S68: 66.8 | AB68: S | AD68: 46184 | AE68: CRE | AF68: 6599095 | AG68: 1413 | AH68: 4212 | AR68: 18 | AS68: POR DERECHO DE EMISION DE PLACA DE RODAJE
A69: 46153 | B69: =AD69 -> 46184 | C69: 01 | D69: 00F003 | F69: 3846198 | G69: 6 | H69: 20101973922 | I69: =IF(H69="","",VLOOKUP(H69,[1]ENTIDAD!$B$2:$C$605,2,0)) -> ASOCIACION AUTOMOTRIZ DEL PERU | N69: =(S69-P69)/1.18 -> 56.610169 | O69: =N69*0.18 -> 10.189831 | P69: 0 | R69: 66.8 | S69: 66.8 | AB69: S | AD69: 46184 | AE69: CRE | AF69: 6599095 | AG69: 1413 | AH69: 4212 | AR69: 18 | AS69: POR DERECHO DE EMISION DE PLACA DE RODAJE
A70: 46153 | B70: =AD70 -> 46184 | C70: 01 | D70: 00F003 | F70: 3846199 | G70: 6 | H70: 20101973922 | I70: =IF(H70="","",VLOOKUP(H70,[1]ENTIDAD!$B$2:$C$605,2,0)) -> ASOCIACION AUTOMOTRIZ DEL PERU | N70: =(S70-P70)/1.18 -> 56.610169 | O70: =N70*0.18 -> 10.189831 | P70: 0 | R70: 66.8 | S70: 66.8 | AB70: S | AD70: 46184 | AE70: CRE | AF70: 6599095 | AG70: 1413 | AH70: 4212 | AR70: 18 | AS70: POR DERECHO DE EMISION DE PLACA DE RODAJE
A71: 46153 | B71: =AD71 -> 46184 | C71: 01 | D71: 00F003 | F71: 3846200 | G71: 6 | H71: 20101973922 | I71: =IF(H71="","",VLOOKUP(H71,[1]ENTIDAD!$B$2:$C$605,2,0)) -> ASOCIACION AUTOMOTRIZ DEL PERU | N71: =(S71-P71)/1.18 -> 56.610169 | O71: =N71*0.18 -> 10.189831 | P71: 0 | R71: 66.8 | S71: 66.8 | AB71: S | AD71: 46184 | AE71: CRE | AF71: 6599095 | AG71: 1413 | AH71: 4212 | AR71: 18 | AS71: POR DERECHO DE EMISION DE PLACA DE RODAJE
A72: 46153 | B72: =AD72 -> 46184 | C72: 01 | D72: 00F003 | F72: 3846201 | G72: 6 | H72: 20101973922 | I72: =IF(H72="","",VLOOKUP(H72,[1]ENTIDAD!$B$2:$C$605,2,0)) -> ASOCIACION AUTOMOTRIZ DEL PERU | N72: =(S72-P72)/1.18 -> 56.610169 | O72: =N72*0.18 -> 10.189831 | P72: 0 | R72: 66.8 | S72: 66.8 | AB72: S | AD72: 46184 | AE72: CRE | AF72: 6599095 | AG72: 1413 | AH72: 4212 | AR72: 18 | AS72: POR DERECHO DE EMISION DE PLACA DE RODAJE
A73: 46153 | B73: =AD73 -> 46184 | C73: 01 | D73: 00F003 | F73: 3846202 | G73: 6 | H73: 20101973922 | I73: =IF(H73="","",VLOOKUP(H73,[1]ENTIDAD!$B$2:$C$605,2,0)) -> ASOCIACION AUTOMOTRIZ DEL PERU | N73: =(S73-P73)/1.18 -> 56.610169 | O73: =N73*0.18 -> 10.189831 | P73: 0 | R73: 66.8 | S73: 66.8 | AB73: S | AD73: 46184 | AE73: CRE | AF73: 6599095 | AG73: 1413 | AH73: 4212 | AR73: 18 | AS73: POR DERECHO DE EMISION DE PLACA DE RODAJE
... A86: 46153 | B86: =AD86 -> 46184 | C86: 01 | D86: 00F003 | F86: 3846215 | G86: 6 | H86: 20101973922 | I86: =IF(H86="","",VLOOKUP(H86,[1]ENTIDAD!$B$2:$C$605,2,0)) -> ASOCIACION AUTOMOTRIZ DEL PERU | N86: =(S86-P86)/1.18 -> 56.610169 | O86: =N86*0.18 -> 10.189831 | P86: 0 | R86: 66.8 | S86: 66.8 | AB86: S | AD86: 46184 | AE86: CRE | AF86: 6599095 | AG86: 1413 | AH86: 4212 | AR86: 18 | AS86: POR DERECHO DE EMISION DE PLACA DE RODAJE
A87: 46154 | B87: =AD87 -> 46185 | C87: 01 | D87: 00E001 | F87: 10 | G87: 6 | H87: 20615095142 | I87: =IF(H87="","",VLOOKUP(H87,[1]ENTIDAD!$B$2:$C$605,2,0)) -> #N/A | N87: =(S87-P87)/1.18 -> 955.94068 | O87: =N87*0.18 -> 172.06932 | P87: 0 | S87: 1128.01 | AB87: S | AD87: 46185 | AE87: CRE | AF87: 6591095 | AH87: 4212 | AR87: 18 | AS87: CASCO INTEGRAL DOBLE VISERA OBSEQUIO CLIENTE
A88: 46154 | B88: =AD88 -> 46188 | C88: 01 | D88: 00F005 | F88: 582 | G88: 6 | H88: 20602109225 | I88: =IF(H88="","",VLOOKUP(H88,[1]ENTIDAD!$B$2:$C$605,2,0)) -> SISTEMA ECOLÓGICO INTEGRAL DE TECNOLOGÍAS E INFORMÁTICA SOCIEDAD ANONIMA CERRADA - ECO SITI S.A.C. | N88: =(S88-P88)/1.18 -> 0 | O88: =N88*0.18 -> 0 | P88: 119.5 | S88: 119.5 | AB88: S | AD88: 46188 | AE88: CRE | AF88: 6364095 | AG88: 1413 | AH88: 4212 | AR88: 18 | AS88: SERVICIO DE TELEFONICA
A89: 46154 | B89: =AD89 -> 46185 | C89: 01 | D89: 00F005 | F89: 18203 | G89: 6 | H89: 20493508645 | I89: =IF(H89="","",VLOOKUP(H89,[1]ENTIDAD!$B$2:$C$605,2,0)) -> HONDA SELVA DEL PERU S.A. | N89: =(S89-P89)/1.18 -> -0.0040677966 | O89: =N89*0.18 -> -0.00073220339 | P89: 6685.92 | S89: =W89*AC89 -> 6685.9152 | W89: 3.44 | AB89: D | AC89: 1943.58 | AD89: 46185 | AE89: CRE | AF89: 6011021 | AH89: 4212 | AR89: 18 | AS89: EXISTENCIAS POR RECIBIR
A90: 46154 | B90: =AD90 -> 46185 | C90: 01 | D90: 00F005 | F90: 18198 | G90: 6 | H90: 20493508645 | I90: =IF(H90="","",VLOOKUP(H90,[1]ENTIDAD!$B$2:$C$605,2,0)) -> HONDA SELVA DEL PERU S.A. | N90: =(S90-P90)/1.18 -> -0.0037288136 | O90: =N90*0.18 -> -0.00067118644 | P90: 8918.17 | S90: =W90*AC90 -> 8918.1656 | W90: 3.44 | AB90: D | AC90: 2592.49 | AD90: 46185 | AE90: CRE | AF90: 6011021 | AH90: 4212 | AR90: 18 | AS90: EXISTENCIAS POR RECIBIR
A91: 46154 | C91: 01 | D91: 00F002 | F91: 110 | G91: 6 | H91: 20486549328 | I91: =IF(H91="","",VLOOKUP(H91,[1]ENTIDAD!$B$2:$C$605,2,0)) -> SANTISIMA TRINIDAD E.I.R.L. | N91: =(S91-P91)/1.18 -> 0 | O91: =N91*0.18 -> 0 | P91: 132 | S91: 132 | AB91: S | AD91: 46154 | AE91: CON | AF91: 656009503 | AH91: 4212 | AR91: 18 | AS91: ARTICULOS DE ESCRITORIO
A92: 46154 | B92: =AD92 -> 46185 | C92: 01 | D92: 00E001 | F92: 234 | G92: 6 | H92: 10447422951 | I92: =IF(H92="","",VLOOKUP(H92,[1]ENTIDAD!$B$2:$C$605,2,0)) -> ZEGARRA AZAÑERO JORGE KEY | N92: =(S92-P92)/1.18 -> 0 | O92: =N92*0.18 -> 0 | P92: 1000 | S92: 1000 | AB92: S | AD92: 46185 | AE92: CRE | AF92: 6329094 | AH92: 4212 | AR92: 18 | AS92: A CTA ACTUALIZACION DE MODULOS DE SISTEMA CRED Y COBR.
A93: 46155 | C93: 01 | D93: 00E001 | F93: 58 | G93: 6 | H93: 10417193150 | I93: =IF(H93="","",VLOOKUP(H93,[1]ENTIDAD!$B$2:$C$605,2,0)) -> VILA TORRES NILSON WILLIAM | N93: =(S93-P93)/1.18 -> 0 | O93: =N93*0.18 -> 0 | P93: 19 | S93: 19 | AB93: S | AD93: 46155 | AE93: CON | AF93: 656009503 | AH93: 4212 | AR93: 18 | AS93: POZIT, GOMA
A94: 46155 | B94: =AD94 -> 46186 | C94: 01 | D94: 00F005 | F94: 18230 | G94: 6 | H94: 20493508645 | I94: =IF(H94="","",VLOOKUP(H94,[1]ENTIDAD!$B$2:$C$605,2,0)) -> HONDA SELVA DEL PERU S.A. | N94: =(S94-P94)/1.18 -> 0.0011864407 | O94: =N94*0.18 -> 0.00021355932 | P94: 5562.1 | S94: =W94*AC94 -> 5562.1014 | W94: 3.428 | AB94: D | AC94: 1622.55 | AD94: 46186 | AE94: CRE | AF94: 6011021 | AH94: 4212 | AR94: 18 | AS94: EXISTENCIAS POR RECIBIR
A95: 46155 | B95: =AD95 -> 46186 | C95: 01 | D95: 00F005 | F95: 18222 | G95: 6 | H95: 20493508645 | I95: =IF(H95="","",VLOOKUP(H95,[1]ENTIDAD!$B$2:$C$605,2,0)) -> HONDA SELVA DEL PERU S.A. | N95: =(S95-P95)/1.18 -> -0.0033898305 | O95: =N95*0.18 -> -0.00061016949 | P95: 9165.35 | S95: =W95*AC95 -> 9165.346 | W95: 3.434 | AB95: D | AC95: 2669 | AD95: 46186 | AE95: CRE | AF95: 6011021 | AH95: 4212 | AR95: 18 | AS95: EXISTENCIAS POR RECIBIR
A96: 46155 | B96: =AD96 -> 46186 | C96: 01 | D96: 00F005 | F96: 18221 | G96: 6 | H96: 20493508645 | I96: =IF(H96="","",VLOOKUP(H96,[1]ENTIDAD!$B$2:$C$605,2,0)) -> HONDA SELVA DEL PERU S.A. | N96: =(S96-P96)/1.18 -> -0.0033898305 | O96: =N96*0.18 -> -0.00061016949 | P96: 9165.35 | S96: =W96*AC96 -> 9165.346 | W96: 3.434 | AB96: D | AC96: 2669 | AD96: 46186 | AE96: CRE | AF96: 6011021 | AH96: 4212 | AR96: 18 | AS96: EXISTENCIAS POR RECIBIR
A97: 46155 | B97: =AD97 -> 46186 | C97: 01 | D97: 00F005 | F97: 18220 | G97: 6 | H97: 20493508645 | I97: =IF(H97="","",VLOOKUP(H97,[1]ENTIDAD!$B$2:$C$605,2,0)) -> HONDA SELVA DEL PERU S.A. | N97: =(S97-P97)/1.18 -> 0.00055932203 | O97: =N97*0.18 -> 0.00010067797 | P97: 8902.61 | S97: =W97*AC97 -> 8902.6107 | W97: 3.434 | AB97: D | AC97: 2592.49 | AD97: 46186 | AE97: CRE | AF97: 6011021 | AH97: 4212 | AR97: 18 | AS97: EXISTENCIAS POR RECIBIR
A98: 46155 | B98: =AD98 -> 46186 | C98: 01 | D98: 00FI01 | F98: 19365129 | G98: 6 | H98: 20100047218 | I98: =IF(H98="","",VLOOKUP(H98,[1]ENTIDAD!$B$2:$C$605,2,0)) -> BANCO DE CREDITO DEL PERU | N98: =(S98-P98)/1.18 -> 0.0016949153 | O98: =N98*0.18 -> 0.00030508475 | P98: 61.81 | S98: =W98*AC98 -> 61.812 | W98: 3.434 | AB98: D | AC98: 18 | AD98: 46186 | AE98: CRE | AF98: 6391094 | AH98: 4212 | AR98: 18 | AS98: COMISION , PORTES
A99: 46155 | C99: 01 | D99: 00F001 | F99: 12727 | G99: 6 | H99: 10209907327 | I99: =IF(H99="","",VLOOKUP(H99,[1]ENTIDAD!$B$2:$C$605,2,0)) -> TORPOCO,MAYTA,HECTOR,ALFONSO | N99: =(S99-P99)/1.18 -> 0 | O99: =N99*0.18 -> 0 | P99: 10 | S99: 10 | AB99: S | AD99: 46155 | AE99: CON | AF99: 656009501 | AH99: 4212 | AR99: 18 | AS99: COMBUSTIBLE
A100: 46156 | C100: 01 | D100: 00FF08 | F100: 910 | G100: 6 | H100: 20611526572 | I100: =IF(H100="","",VLOOKUP(H100,[1]ENTIDAD!$B$2:$C$605,2,0)) -> GRUPO SUKKIE E.I.R.L. | N100: =(S100-P100)/1.18 -> 0 | O100: =N100*0.18 -> 0 | P100: 65 | S100: 65 | AB100: S | AD100: 46156 | AE100: CON | AF100: 656009502 | AH100: 4212 | AR100: 18 | AS100: ARTICULOS DE LIMPIEZA
A101: 46156 | C101: 01 | D101: 00F001 | F101: 119713 | G101: 6 | H101: 20568499043 | I101: =IF(H101="","",VLOOKUP(H101,[1]ENTIDAD!$B$2:$C$605,2,0)) -> SURTIDORES SAN MIGUEL E.I.R.L. | N101: =(S101-P101)/1.18 -> 0 | O101: =N101*0.18 -> 0 | P101: 103.5 | S101: 103.5 | AB101: S | AD101: 46156 | AE101: CON | AF101: 656009501 | AH101: 4212 | AR101: 18 | AS101: COMBUSTIBLE
A102: 46156 | B102: =AD102 -> 46187 | C102: 01 | D102: 00F028 | F102: 15744 | G102: 6 | H102: 20493508645 | I102: =IF(H102="","",VLOOKUP(H102,[1]ENTIDAD!$B$2:$C$605,2,0)) -> HONDA SELVA DEL PERU S.A. | N102: =(S102-P102)/1.18 -> -0.003559322 | O102: =N102*0.18 -> -0.00064067797 | P102: 17466.78 | S102: =W102*AC102 -> 17466.776 | W102: 3.426 | AB102: D | AC102: 5098.3 | AD102: 46187 | AE102: CRE | AF102: 6011021 | AH102: 4212 | AR102: 18 | AS102: EXISTENCIAS POR RECIBIR
A103: 46156 | B103: =AD103 -> 46187 | C103: 01 | D103: 00F005 | F103: 18249 | G103: 6 | H103: 20493508645 | I103: =IF(H103="","",VLOOKUP(H103,[1]ENTIDAD!$B$2:$C$605,2,0)) -> HONDA SELVA DEL PERU S.A. | N103: =(S103-P103)/1.18 -> -0.0026610169 | O103: =N103*0.18 -> -0.00047898305 | P103: 11117.75 | S103: =W103*AC103 -> 11117.747 | W103: 3.426 | AB103: D | AC103: 3245.11 | AD103: 46187 | AE103: CRE | AF103: 6011021 | AH103: 4212 | AR103: 18 | AS103: EXISTENCIAS POR RECIBIR
A104: 46156 | C104: 01 | D104: 00F003 | F104: 10445 | G104: 6 | H104: 20605377115 | I104: =IF(H104="","",VLOOKUP(H104,[1]ENTIDAD!$B$2:$C$605,2,0)) -> CORPORACIÓN FERNANDO´S E.I.R.L. | N104: =(S104-P104)/1.18 -> 0 | O104: =N104*0.18 -> 0 | P104: 10 | S104: 10 | AB104: S | AD104: 46156 | AE104: CON | AF104: 656009501 | AH104: 4212 | AR104: 18 | AS104: COMBUSTIBLE
A105: 46156 | B105: =AD105 -> 46187 | C105: 01 | D105: 00F001 | F105: 5330 | G105: 6 | H105: 10061702071 | I105: =IF(H105="","",VLOOKUP(H105,[1]ENTIDAD!$B$2:$C$605,2,0)) -> CORAL FLORES IVAN MARTIN | N105: =(S105-P105)/1.18 -> 0 | O105: =N105*0.18 -> 0 | P105: 535 | S105: 535 | AB105: S | AD105: 46187 | AE105: CRE | AF105: 6599095 | AG105: 1413 | AH105: 4212 | AR105: 18 | AS105: CERTIFICADO DE FIRMAS
A106: 46156 | B106: =AD106 -> 46187 | C106: 01 | D106: 00F003 | F106: 3854213 | G106: 6 | H106: 20101973922 | I106: =IF(H106="","",VLOOKUP(H106,[1]ENTIDAD!$B$2:$C$605,2,0)) -> ASOCIACION AUTOMOTRIZ DEL PERU | N106: =(S106-P106)/1.18 -> 56.610169 | O106: =N106*0.18 -> 10.189831 | P106: 0 | R106: 66.8 | S106: 66.8 | AB106: S | AD106: 46187 | AE106: CRE | AF106: 6599095 | AG106: 1413 | AH106: 4212 | AR106: 18 | AS106: POR DERECHO DE EMISION DE PLACA DE RODAJE
A107: 46156 | C107: 01 | D107: 00F001 | F107: 2147 | G107: 6 | H107: 20600220676 | I107: =IF(H107="","",VLOOKUP(H107,ENTIDAD!$B$2:$C$613,2,0)) -> INVERSIONES INGA & VICTORIO E.I.R.L. | N107: =(S107-P107)/1.18 -> 0 | O107: =N107*0.18 -> 0 | P107: 201 | S107: 201 | AB107: S | AD107: 46156 | AF107: 6591094 | AH107: 4212 | AR107: 18 | AS107: CANASTA CLIENTES X DIA DE LA MADRE
A108: 46157 | B108: =AD108 -> 46188 | C108: 01 | D108: 00F028 | F108: 15760 | G108: 6 | H108: 20493508645 | I108: =IF(H108="","",VLOOKUP(H108,[1]ENTIDAD!$B$2:$C$605,2,0)) -> HONDA SELVA DEL PERU S.A. | N108: =(S108-P108)/1.18 -> -0.0034830508 | O108: =N108*0.18 -> -0.00062694915 | P108: 13246.27 | S108: =W108*AC108 -> 13246.266 | W108: 3.419 | AB108: D | AC108: 3874.31 | AD108: 46188 | AE108: CRE | AF108: 6011021 | AH108: 4212 | AR108: 18 | AS108: EXISTENCIAS POR RECIBIR
A109: 46157 | B109: =AD109 -> 46188 | C109: 01 | D109: 00F020 | F109: 20104 | G109: 6 | H109: 20485981536 | I109: =IF(H109="","",VLOOKUP(H109,[1]ENTIDAD!$B$2:$C$605,2,0)) -> EMPRESA DE TRANSPORTES TURISMO Y SERVICIOS MULTIPLES SHIMA E.I.R.L. | N109: 0 | O109: =N109*0.18 -> 0 | P109: 0 | R109: 40 | S109: 40 | AB109: S | AD109: 46188 | AE109: CRE | AF109: 6599095 | AG109: 1413 | AH109: 4212 | AR109: 18 | AS109: POR EL SERVICIO DE TRANSPORTE DE PASAJERO
A110: 46157 | B110: =AD110 -> 46188 | C110: 01 | D110: 00E001 | F110: 805 | G110: 6 | H110: 20402406161 | I110: =IF(H110="","",VLOOKUP(H110,[1]ENTIDAD!$B$2:$C$605,2,0)) -> SERVI TOURS EXPRESS S.A. | N110: 0 | O110: =N110*0.18 -> 0 | P110: 0 | R110: 40 | S110: 40 | AB110: S | AD110: 46188 | AE110: CRE | AF110: 6599095 | AG110: 1413 | AH110: 4212 | AR110: 18 | AS110: POR EL SERVICIO DE TRANSPORTE DE PASAJERO
A111: 46160 | B111: =AD111 -> 46191 | C111: 01 | D111: 00FB27 | F111: 27321242 | G111: 6 | H111: 20100130204 | I111: =IF(H111="","",VLOOKUP(H111,[1]ENTIDAD!$B$2:$C$605,2,0)) -> BANCO BBVA PERU | N111: =(S111-P111)/1.18 -> 0 | O111: =N111*0.18 -> 0 | P111: 6.5 | S111: 6.5 | AB111: S | AD111: 46191 | AE111: CRE | AF111: 6391094 | AH111: 4212 | AR111: 18 | AS111: COMISION DEPOSITO
A112: 46161 | C112: 01 | D112: 00F002 | F112: 18077 | G112: 6 | H112: 20605377115 | I112: =IF(H112="","",VLOOKUP(H112,[1]ENTIDAD!$B$2:$C$605,2,0)) -> CORPORACIÓN FERNANDO´S E.I.R.L. | N112: =(S112-P112)/1.18 -> 0 | O112: =N112*0.18 -> 0 | P112: 10 | S112: 10 | AB112: S | AD112: 46161 | AE112: CON | AF112: 656009501 | AH112: 4212 | AR112: 18 | AS112: COMBUSTIBLE
A113: 46161 | B113: =AD113 -> 46192 | C113: 01 | D113: 00FN01 | F113: 46312838 | G113: 6 | H113: 20100047218 | I113: =IF(H113="","",VLOOKUP(H113,[1]ENTIDAD!$B$2:$C$605,2,0)) -> BANCO DE CREDITO DEL PERU | N113: =(S113-P113)/1.18 -> 0 | O113: =N113*0.18 -> 0 | P113: 10 | S113: 10 | AB113: S | AD113: 46192 | AE113: CRE | AF113: 6391094 | AH113: 4212 | AR113: 18 | AS113: PAGO DE COMISION
A114: 46161 | B114: =AD114 -> 46192 | C114: 01 | D114: 00FN01 | F114: 46312888 | G114: 6 | H114: 20100047218 | I114: =IF(H114="","",VLOOKUP(H114,[1]ENTIDAD!$B$2:$C$605,2,0)) -> BANCO DE CREDITO DEL PERU | N114: =(S114-P114)/1.18 -> 0 | O114: =N114*0.18 -> 0 | P114: 10 | S114: 10 | AB114: S | AD114: 46192 | AE114: CRE | AF114: 6391094 | AH114: 4212 | AR114: 18 | AS114: PAGO DE COMISION
A115: 46163 | B115: =AD115 -> 46194 | C115: 01 | D115: 00F001 | F115: 5348 | G115: 6 | H115: 10061702071 | I115: =IF(H115="","",VLOOKUP(H115,[1]ENTIDAD!$B$2:$C$605,2,0)) -> CORAL FLORES IVAN MARTIN | N115: =(S115-P115)/1.18 -> 0 | O115: =N115*0.18 -> 0 | P115: 410 | S115: 410 | AB115: S | AD115: 46194 | AE115: CRE | AF115: 6599095 | AG115: 1413 | AH115: 4212 | AR115: 18 | AS115: CERTIFICADO DE FIRMAS
A116: 46163 | B116: =AD116 -> 46194 | C116: 01 | D116: 00F001 | F116: 5347 | G116: 6 | H116: 10061702071 | I116: =IF(H116="","",VLOOKUP(H116,[1]ENTIDAD!$B$2:$C$605,2,0)) -> CORAL FLORES IVAN MARTIN | N116: =(S116-P116)/1.18 -> 0 | O116: =N116*0.18 -> 0 | P116: 505 | S116: 505 | AB116: S | AD116: 46194 | AE116: CRE | AF116: 6599095 | AG116: 1413 | AH116: 4212 | AR116: 18 | AS116: CERTIFICADO DE FIRMAS
A117: 46163 | B117: =AD117 -> 46194 | C117: 01 | D117: 00FQ07 | F117: 9709 | G117: 6 | H117: 20100047218 | I117: =IF(H117="","",VLOOKUP(H117,[1]ENTIDAD!$B$2:$C$605,2,0)) -> BANCO DE CREDITO DEL PERU | N117: =(S117-P117)/1.18 -> 66.949153 | O117: =N117*0.18 -> 12.050847 | P117: 0 | S117: 79 | AB117: S | AD117: 46194 | AE117: CRE | AF117: 6391094 | AH117: 4212 | AR117: 18 | AS117: MEMBRESIA QCLQUI
A118: 46163 | B118: =AD118 -> 46194 | C118: 01 | D118: 00FE01 | F118: 1532633 | G118: 6 | H118: 20130200789 | I118: =IF(H118="","",VLOOKUP(H118,[1]ENTIDAD!$B$2:$C$605,2,0)) -> CMAC - HUANCAYO S.A. | N118: =(S118-P118)/1.18 -> 0 | O118: =N118*0.18 -> 0 | P118: 32.32 | S118: 32.32 | AB118: S | AD118: 46194 | AE118: CRE | AF118: 6391094 | AH118: 4212 | AR118: 18 | AS118: COMISION DE OPERACIÓN
A119: 46164 | B119: =AD119 -> 46164 | C119: 01 | D119: 00F003 | F119: 60284 | G119: 6 | H119: 20493508645 | I119: =IF(H119="","",VLOOKUP(H119,[1]ENTIDAD!$B$2:$C$605,2,0)) -> HONDA SELVA DEL PERU S.A. | N119: =(S119-P119)/1.18 -> 0.0016949153 | O119: =N119*0.18 -> 0.00030508475 | P119: 235.84 | S119: =W119*AC119 -> 235.842 | W119: 3.418 | AB119: D | AC119: 69 | AD119: 46164 | AE119: CRE | AF119: 6011021 | AH119: 4212 | AR119: 18 | AS119: EXISTENCIAS POR RECIBIR
A120: 46164 | B120: =AD120 -> 46195 | C120: 01 | D120: 00E001 | F120: 7295 | G120: 6 | H120: 10210648939 | I120: =IF(H120="","",VLOOKUP(H120,[1]ENTIDAD!$B$2:$C$605,2,0)) -> EGOAVIL,TORRES,EDITH,GINA | N120: =(S120-P120)/1.18 -> 0 | O120: =N120*0.18 -> 0 | P120: 45 | S120: 45 | AB120: S | AD120: 46195 | AE120: CRE | AF120: 6322094 | AH120: 4212 | AR120: 18 | AS120: LEGALIZACION DE FIRMAS
A121: 46164 | B121: =AD121 -> 46173 | C121: 14 | D121: 00S060 | F121: 1068907 | G121: 6 | H121: 20121876290 | I121: =IF(H121="","",VLOOKUP(H121,[1]ENTIDAD!$B$2:$C$605,2,0)) -> ENT.PREST.SERV.SANEAM.SELVA CENTRAL S.A | N121: =(S121-P121)/1.18 -> 0 | O121: =N121*0.18 -> 0 | P121: 50.5 | S121: 50.5 | AB121: S | AD121: 46173 | AE121: CRE | AF121: 6363095 | AH121: 4212 | AR121: 18 | AS121: SERVICIO DE AGUA Y DESAGUIE
A122: 46164 | C122: 01 | D122: 00E001 | F122: 6207 | G122: 6 | H122: 20602783341 | I122: =IF(H122="","",VLOOKUP(H122,[1]ENTIDAD!$B$2:$C$605,2,0)) -> CODISSER VRAEM E.I.R.L. | N122: =(S122-P122)/1.18 -> 0 | O122: =N122*0.18 -> 0 | P122: 8 | S122: 8 | AB122: S | AD122: 46164 | AE122: CON | AF122: 6250095 | AH122: 4212 | AR122: 18 | AS122: AGUA DE MESA
A123: 46164 | C123: 01 | D123: 00F002 | F123: 163 | G123: 6 | H123: 20486549328 | I123: =IF(H123="","",VLOOKUP(H123,[1]ENTIDAD!$B$2:$C$605,2,0)) -> SANTISIMA TRINIDAD E.I.R.L. | N123: =(S123-P123)/1.18 -> 6.779661 | O123: =N123*0.18 -> 1.220339 | P123: 0 | S123: 8 | AB123: S | AD123: 46164 | AE123: CON | AF123: 656009503 | AH123: 4212 | AR123: 18 | AS123: PLUMON INDELEBLE
A124: 46164 | C124: 01 | D124: 00F002 | F124: 284 | G124: 6 | H124: 10209907327 | I124: =IF(H124="","",VLOOKUP(H124,ENTIDAD!$B$2:$C$613,2,0)) -> TORPOCO,MAYTA,HECTOR,ALFONSO | N124: =(S124-P124)/1.18 -> 0 | O124: =N124*0.18 -> 0 | P124: 20 | S124: 20 | AB124: S | AD124: 46164 | AE124: CON | AF124: 656009501 | AH124: 4212 | AR124: 18 | AS124: COMBUSTIBLE
A125: 46165 | B125: 46196 | C125: 01 | D125: 00E001 | F125: 1586 | G125: 6 | H125: 20609448360 | I125: =IF(H125="","",VLOOKUP(H125,[1]ENTIDAD!$B$2:$C$605,2,0)) -> L & E SAN FRANCISCO SOCIEDAD DE RESPONSABILIDAD LIMITADA | N125: =(S125-P125)/1.18 -> 0 | O125: =N125*0.18 -> 0 | P125: 45 | S125: 45 | AB125: S | AD125: 46196 | AE125: CRE | AF125: 6341094 | AH125: 4212 | AR125: 18 | AS125: LAVADO Y ENGRASE CAMIONETA PLACA B9Q-769
...

Sheet JUNIO
A1: FECHA DE EMISION DEL COMPROBANTE DE PAGO O DOCUMENTO | B1: FECHA DE VENCIMIENTO O FECHA DE PAGO | C1: COMPROBANTE DE PAGO O DOCUMENTO | F1: N° COMPROBANTE PAGO | G1: INFORMACION PROVEEDOR | J1: ADQUISICIONES GRAVADAS DESTINADAS A OPERACIONES GRAVADAS Y/O EXPORTACION | L1: ADQUISICIONES GRAVADAS DESTINADAS A OPERACIONES GRAVADAS Y/O DE EXPORTACION Y A OPERACIONES NO GRAVADAS | N1: ADQUISICIONES GRAVADAS DESTINADAS A OPERACIONES NO GRAVADAS | P1: VALOR DE LAS ADQUISICIONES NO GRAVADAS | Q1: ISC | R1: OTROS TRIBUTOS Y CARGOS | S1: IMPORTE TOTAL | T1: N° COMPROBANTE DE PAGO EMITIDO POR SUJETO NO DOMICILIADO | U1: CONSTANCIA DE DEPOSITO DE DETRACCION | W1: TIPO DE CAMBIO | X1: REFERENCIA DEL COMPROBANTE DE PAGO O DOCUMENTO ORIGINAL QUE SE MODIFICA | AB1: MONEDA | AC1: EQUIVALENTE EN DOLARES AMERICANOS | AD1: FECHA VENCIMIENTO | AE1: CONDICION CONTADO/CREDITO | AF1: CUENTA CONTABLE BASE IMPONIBLE | AG1: CUENTA CONTABLE OTROS TRIBUTOS Y CARGOS | AH1: CUENTA CONTABLE TOTAL | AI1: CODIGO CENTRO DE COSTOS | AJ1: CODIGO CENTRO DE COSTOS 2 | AK1: REGIMEN ESPECIAL | AL1: PORCENTAJE REGIMEN ESPECIAL | AM1: IMPORTE REGIMEN ESPECIAL | AN1: SERIE DOCUMENTO REGIMEN ESPECIAL | AO1: NUMERO DOCUMENTO REGIMEN ESPECIAL | AP1: FECHA DOCUMENTO REGIMEN ESPECIAL | AQ1: CODIGO PRESUPUESTO | AR1: PORCENTAJE I.G.V. | AS1: GLOSA | AT1: CONDICIÓN DE PERCEPCIÓN | AU1: IMPORTE RÉGIMEN ESPECIAL | AV1: CLASIFICACIÓN DE BIENES Y SERVICIOS ADQUIRIDOS
G2: DOCUMENTO IDENTIDAD | I2: APELLIDOS Y NOMBRES, DENOMINACION O RAZON SOCIAL
C3: TIPO | D3: SERIE/CODIGO ADUANA | E3: AÑO EMISION DUA O DSI | G3: TIPO | H3: NUMERO | J3: BASE IMPONIBLE | K3: IGV | L3: BASE IMPONIBLE | M3: IGV | N3: BASE IMPONIBLE | O3: IGV | U3: NUMERO | V3: FECHA EMISION | X3: FECHA | Y3: TIPO | Z3: SERIE | AA3: N° COMPROBANTE PAGO O DOCUMENTO
A4: 46162 | C4: 14 | D4: 00SB02 | F4: 287645658 | G4: 6 | H4: 20467534026 | I4: =IF(H4="","",VLOOKUP(H4,[1]ENTIDAD!$B$2:$C$605,2,0)) -> AMERICA MOVIL PERU S.A.C. | N4: =(S4-P4)/1.18 -> 25.338983 | O4: =N4*0.18 -> 4.5610169 | P4: 0 | S4: 29.9 | AB4: S | AD4: 46181 | AE4: CRE | AF4: 6365095 | AH4: 4212 | AR4: 18 | AS4: SERVICIO TELEFONICO
A5: 46171 | C5: 14 | D5: 00S898 | F5: 5806423 | G5: 6 | H5: 20129646099 | I5: =IF(H5="","",VLOOKUP(H5,[1]ENTIDAD!$B$2:$C$605,2,0)) -> ELECTROCENTRO S.A. | N5: =(S5-P5)/1.18 -> 0 | O5: =N5*0.18 -> 0 | P5: 550.6 | S5: 550.6 | AB5: S | AD5: 46188 | AE5: CRE | AF5: 6361095 | AH5: 4212 | AR5: 18 | AS5: FLUIDO ELECTRICO 1RO DE NOVIEMBRE 341
A6: 46171 | C6: 14 | D6: 00S898 | F6: 5806205 | G6: 6 | H6: 20129646099 | I6: =IF(H6="","",VLOOKUP(H6,[1]ENTIDAD!$B$2:$C$605,2,0)) -> ELECTROCENTRO S.A. | N6: 0 | O6: =N6*0.18 -> 0 | P6: 118.1 | S6: 118.1 | AB6: S | AD6: 46188 | AE6: CRE | AF6: 6361095 | AH6: 4212 | AR6: 18 | AS6: FLUIDO ELECTRICO JR.LOS INCAS 385
A7: 46171 | C7: 14 | D7: 00S898 | F7: 5806200 | G7: 6 | H7: 20129646099 | I7: =IF(H7="","",VLOOKUP(H7,[1]ENTIDAD!$B$2:$C$605,2,0)) -> ELECTROCENTRO S.A. | N7: =(S7-P7)/1.18 -> 0 | O7: =N7*0.18 -> 0 | P7: 392.6 | S7: 392.6 | AB7: S | AD7: 46188 | AE7: CRE | AF7: 6361095 | AH7: 4212 | AR7: 18 | AS7: FLUIDO ELECTRICO JR.FCO.IRAZOLA 377
A8: 46173 | C8: 14 | D8: 00S060 | F8: 1073625 | G8: 6 | H8: 20121876290 | I8: =IF(H8="","",VLOOKUP(H8,[1]ENTIDAD!$B$2:$C$605,2,0)) -> ENT.PREST.SERV.SANEAM.SELVA CENTRAL S.A | N8: =(S8-P8)/1.18 -> 0 | O8: =N8*0.18 -> 0 | P8: 89.4 | S8: 89.4 | AB8: S | AD8: 46188 | AE8: CRE | AF8: 6363095 | AH8: 4212 | AR8: 18 | AS8: CONSUMO DE AGUA Y DESAGUE JR. 1RO DE NOVIEMBRE
A9: 46173 | C9: 14 | D9: 00S060 | F9: 1074436 | G9: 6 | H9: 20121876290 | I9: =IF(H9="","",VLOOKUP(H9,[1]ENTIDAD!$B$2:$C$605,2,0)) -> ENT.PREST.SERV.SANEAM.SELVA CENTRAL S.A | N9: =(S9-P9)/1.18 -> 0 | O9: =N9*0.18 -> 0 | P9: 45.7 | S9: 45.7 | AB9: S | AD9: 46203 | AE9: CRE | AF9: 6363095 | AH9: 4212 | AR9: 18 | AS9: CONSUMO DE AGUA Y DESAGUE JR.FCO IRAZOLA 377
A10: 46173 | C10: 14 | D10: 00S060 | F10: 1072890 | G10: 6 | H10: 20121876290 | I10: =IF(H10="","",VLOOKUP(H10,[1]ENTIDAD!$B$2:$C$605,2,0)) -> ENT.PREST.SERV.SANEAM.SELVA CENTRAL S.A | N10: =(S10-P10)/1.18 -> 0 | O10: =N10*0.18 -> 0 | P10: 29.7 | S10: 29.7 | AB10: S | AD10: 46203 | AE10: CRE | AF10: 6363095 | AH10: 4212 | AR10: 18 | AS10: CONSUMO DE AGUA Y DESAGUE JR. LOS INCAS 364
A11: 46174 | C11: 01 | D11: 00F001 | F11: 810 | G11: 6 | H11: 10733910921 | I11: =IF(H11="","",VLOOKUP(H11,[1]ENTIDAD!$B$2:$C$605,2,0)) -> MADUEÑO HUAMAN LILI CLISSELY | N11: =(S11-P11)/1.18 -> 0 | O11: =N11*0.18 -> 0 | P11: 7 | S11: 7 | AB11: S | AD11: 46204 | AE11: CRE | AF11: 6560095 | AH11: 4212 | AR11: 18 | AS11: PINTURA SPRAY NEGRO BRILLANTE
A12: 46174 | C12: 01 | D12: 00FC03 | F12: 6899281 | G12: 6 | H12: 20100047218 | I12: =IF(H12="","",VLOOKUP(H12,[1]ENTIDAD!$B$2:$C$605,2,0)) -> BANCO DE CREDITO DEL PERU | N12: =(S12-P12)/1.18 -> 0 | O12: =N12*0.18 -> 0 | P12: 3175.41 | S12: 3175.41 | AB12: S | AD12: 46204 | AE12: CRE | AF12: 6391094 | AH12: 4212 | AR12: 18 | AS12: PAGO POR INTERES, PAGO POR APORTES
A13: 46174 | C13: 01 | D13: 00FB27 | F13: 27627852 | G13: 6 | H13: 20100130204 | I13: =IF(H13="","",VLOOKUP(H13,[1]ENTIDAD!$B$2:$C$605,2,0)) -> BANCO BBVA PERU | N13: =(S13-P13)/1.18 -> 0 | O13: =N13*0.18 -> 0 | P13: 10 | S13: 10 | AB13: S | AD13: 46204 | AE13: CRE | AF13: 6391094 | AH13: 4212 | AR13: 18 | AS13: COMISIONES , MANTENIMIENTO
A14: 46174 | C14: 01 | D14: 00F001 | F14: 186456 | G14: 6 | H14: 20101973922 | I14: =IF(H14="","",VLOOKUP(H14,[1]ENTIDAD!$B$2:$C$605,2,0)) -> ASOCIACION AUTOMOTRIZ DEL PERU | N14: 0 | O14: =N14*0.18 -> 0 | P14: 0 | R14: 25 | S14: 25 | AB14: S | AD14: 46205 | AE14: CRE | AF14: 6599095 | AG14: 1413 | AH14: 4212 | AR14: 18 | AS14: POR DERECHO DE EMISION DE PLACA DE RODAJE
A15: 46174 | C15: 01 | D15: 00F003 | F15: 3894913 | G15: 6 | H15: 20101973922 | I15: =IF(H15="","",VLOOKUP(H15,[1]ENTIDAD!$B$2:$C$605,2,0)) -> ASOCIACION AUTOMOTRIZ DEL PERU | N15: 0 | O15: =N15*0.18 -> 0 | P15: 0 | R15: 66.8 | S15: 66.8 | AB15: S | AD15: 46205 | AE15: CRE | AF15: 6599095 | AG15: 1413 | AH15: 4212 | AR15: 18 | AS15: POR DERECHO DE EMISION DE PLACA DE RODAJE
A16: 46174 | C16: 01 | D16: 00F003 | F16: 3894912 | G16: 6 | H16: 20101973922 | I16: =IF(H16="","",VLOOKUP(H16,[1]ENTIDAD!$B$2:$C$605,2,0)) -> ASOCIACION AUTOMOTRIZ DEL PERU | N16: 0 | O16: =N16*0.18 -> 0 | P16: 0 | R16: 66.8 | S16: 66.8 | AB16: S | AD16: 46205 | AE16: CRE | AF16: 6599095 | AG16: 1413 | AH16: 4212 | AR16: 18 | AS16: POR DERECHO DE EMISION DE PLACA DE RODAJE
A17: 46174 | C17: 01 | D17: 00F003 | F17: 3894911 | G17: 6 | H17: 20101973922 | I17: =IF(H17="","",VLOOKUP(H17,ENTIDAD!$B$2:$C$613,2,0)) -> ASOCIACION AUTOMOTRIZ DEL PERU | N17: 0 | O17: =N17*0.18 -> 0 | P17: 0 | R17: 66.8 | S17: 66.8 | AB17: S | AD17: 46205 | AE17: CRE | AF17: 6599095 | AG17: 1413 | AH17: 4212 | AR17: 18 | AS17: POR DERECHO DE EMISION DE PLACA DE RODAJE
A18: 46174 | C18: 01 | D18: 00F003 | F18: 3894910 | G18: 6 | H18: 20101973922 | I18: =IF(H18="","",VLOOKUP(H18,[1]ENTIDAD!$B$2:$C$605,2,0)) -> ASOCIACION AUTOMOTRIZ DEL PERU | N18: 0 | O18: =N18*0.18 -> 0 | P18: 0 | R18: 66.8 | S18: 66.8 | AB18: S | AD18: 46205 | AE18: CRE | AF18: 6599095 | AG18: 1413 | AH18: 4212 | AR18: 18 | AS18: POR DERECHO DE EMISION DE PLACA DE RODAJE
A19: 46174 | C19: 01 | D19: 00F003 | F19: 3894909 | G19: 6 | H19: 20101973922 | I19: =IF(H19="","",VLOOKUP(H19,[1]ENTIDAD!$B$2:$C$605,2,0)) -> ASOCIACION AUTOMOTRIZ DEL PERU | N19: 0 | O19: =N19*0.18 -> 0 | P19: 0 | R19: 66.8 | S19: 66.8 | AB19: S | AD19: 46205 | AE19: CRE | AF19: 6599095 | AG19: 1413 | AH19: 4212 | AR19: 18 | AS19: POR DERECHO DE EMISION DE PLACA DE RODAJE
A20: 46174 | C20: 01 | D20: 00F003 | F20: 3894908 | G20: 6 | H20: 20101973922 | I20: =IF(H20="","",VLOOKUP(H20,[1]ENTIDAD!$B$2:$C$605,2,0)) -> ASOCIACION AUTOMOTRIZ DEL PERU | N20: 0 | O20: =N20*0.18 -> 0 | P20: 0 | R20: 66.8 | S20: 66.8 | AB20: S | AD20: 46205 | AE20: CRE | AF20: 6599095 | AG20: 1413 | AH20: 4212 | AR20: 18 | AS20: POR DERECHO DE EMISION DE PLACA DE RODAJE
A21: 46174 | C21: 01 | D21: 00F003 | F21: 3894907 | G21: 6 | H21: 20101973922 | I21: =IF(H21="","",VLOOKUP(H21,[1]ENTIDAD!$B$2:$C$605,2,0)) -> ASOCIACION AUTOMOTRIZ DEL PERU | N21: 0 | O21: =N21*0.18 -> 0 | P21: 0 | R21: 66.8 | S21: 66.8 | AB21: S | AD21: 46205 | AE21: CRE | AF21: 6599095 | AG21: 1413 | AH21: 4212 | AR21: 18 | AS21: POR DERECHO DE EMISION DE PLACA DE RODAJE
A22: 46174 | C22: 01 | D22: 00F003 | F22: 3894906 | G22: 6 | H22: 20101973922 | I22: =IF(H22="","",VLOOKUP(H22,[1]ENTIDAD!$B$2:$C$605,2,0)) -> ASOCIACION AUTOMOTRIZ DEL PERU | N22: 0 | O22: =N22*0.18 -> 0 | P22: 0 | R22: 66.8 | S22: 66.8 | AB22: S | AD22: 46205 | AE22: CRE | AF22: 6599095 | AG22: 1413 | AH22: 4212 | AR22: 18 | AS22: POR DERECHO DE EMISION DE PLACA DE RODAJE
A23: 46174 | C23: 01 | D23: 00F003 | F23: 3894905 | G23: 6 | H23: 20101973922 | I23: =IF(H23="","",VLOOKUP(H23,[1]ENTIDAD!$B$2:$C$605,2,0)) -> ASOCIACION AUTOMOTRIZ DEL PERU | N23: 0 | O23: =N23*0.18 -> 0 | P23: 0 | R23: 66.8 | S23: 66.8 | AB23: S | AD23: 46205 | AE23: CRE | AF23: 6599095 | AG23: 1413 | AH23: 4212 | AR23: 18 | AS23: POR DERECHO DE EMISION DE PLACA DE RODAJE
A24: 46174 | C24: 01 | D24: 00F003 | F24: 3894904 | G24: 6 | H24: 20101973922 | I24: =IF(H24="","",VLOOKUP(H24,[1]ENTIDAD!$B$2:$C$605,2,0)) -> ASOCIACION AUTOMOTRIZ DEL PERU | N24: 0 | O24: =N24*0.18 -> 0 | P24: 0 | R24: 66.8 | S24: 66.8 | AB24: S | AD24: 46205 | AE24: CRE | AF24: 6599095 | AG24: 1413 | AH24: 4212 | AR24: 18 | AS24: POR DERECHO DE EMISION DE PLACA DE RODAJE
A25: 46174 | C25: 01 | D25: 00F003 | F25: 3894903 | G25: 6 | H25: 20101973922 | I25: =IF(H25="","",VLOOKUP(H25,[1]ENTIDAD!$B$2:$C$605,2,0)) -> ASOCIACION AUTOMOTRIZ DEL PERU | N25: 0 | O25: =N25*0.18 -> 0 | P25: 0 | R25: 66.8 | S25: 66.8 | AB25: S | AD25: 46205 | AE25: CRE | AF25: 6599095 | AG25: 1413 | AH25: 4212 | AR25: 18 | AS25: POR DERECHO DE EMISION DE PLACA DE RODAJE
A26: 46174 | C26: 01 | D26: 00F003 | F26: 3894902 | G26: 6 | H26: 20101973922 | I26: =IF(H26="","",VLOOKUP(H26,[1]ENTIDAD!$B$2:$C$605,2,0)) -> ASOCIACION AUTOMOTRIZ DEL PERU | N26: 0 | O26: =N26*0.18 -> 0 | P26: 0 | R26: 66.8 | S26: 66.8 | AB26: S | AD26: 46205 | AE26: CRE | AF26: 6599095 | AG26: 1413 | AH26: 4212 | AR26: 18 | AS26: POR DERECHO DE EMISION DE PLACA DE RODAJE
A27: 46174 | C27: 01 | D27: 00F003 | F27: 3894901 | G27: 6 | H27: 20101973922 | I27: =IF(H27="","",VLOOKUP(H27,[1]ENTIDAD!$B$2:$C$605,2,0)) -> ASOCIACION AUTOMOTRIZ DEL PERU | N27: 0 | O27: =N27*0.18 -> 0 | P27: 0 | R27: 66.8 | S27: 66.8 | AB27: S | AD27: 46205 | AE27: CRE | AF27: 6599095 | AG27: 1413 | AH27: 4212 | AR27: 18 | AS27: POR DERECHO DE EMISION DE PLACA DE RODAJE
A28: 46174 | C28: 01 | D28: 00F003 | F28: 3894900 | G28: 6 | H28: 20101973922 | I28: =IF(H28="","",VLOOKUP(H28,[1]ENTIDAD!$B$2:$C$605,2,0)) -> ASOCIACION AUTOMOTRIZ DEL PERU | N28: 0 | O28: =N28*0.18 -> 0 | P28: 0 | R28: 66.8 | S28: 66.8 | AB28: S | AD28: 46205 | AE28: CRE | AF28: 6599095 | AG28: 1413 | AH28: 4212 | AR28: 18 | AS28: POR DERECHO DE EMISION DE PLACA DE RODAJE
A29: 46174 | C29: 01 | D29: 00F003 | F29: 3894899 | G29: 6 | H29: 20101973922 | I29: =IF(H29="","",VLOOKUP(H29,[1]ENTIDAD!$B$2:$C$605,2,0)) -> ASOCIACION AUTOMOTRIZ DEL PERU | N29: 0 | O29: =N29*0.18 -> 0 | P29: 0 | R29: 66.8 | S29: 66.8 | AB29: S | AD29: 46205 | AE29: CRE | AF29: 6599095 | AG29: 1413 | AH29: 4212 | AR29: 18 | AS29: POR DERECHO DE EMISION DE PLACA DE RODAJE
... A44: 46174 | C44: 01 | D44: 00F003 | F44: 3894884 | G44: 6 | H44: 20101973922 | I44: =IF(H44="","",VLOOKUP(H44,[1]ENTIDAD!$B$2:$C$605,2,0)) -> ASOCIACION AUTOMOTRIZ DEL PERU | N44: 0 | O44: =N44*0.18 -> 0 | P44: 0 | R44: 66.8 | S44: 66.8 | AB44: S | AD44: 46205 | AE44: CRE | AF44: 6599095 | AG44: 1413 | AH44: 4212 | AR44: 18 | AS44: POR DERECHO DE EMISION DE PLACA DE RODAJE
A45: 46174 | C45: 01 | D45: 00E001 | F45: 1903 | G45: 6 | H45: 20486339510 | I45: =IF(H45="","",VLOOKUP(H45,[1]ENTIDAD!$B$2:$C$605,2,0)) -> SERVICIOS CONTABLES Y AUDITORIA INTERNA S.A. | N45: =(S45-P45)/1.18 -> 1694.9153 | O45: =N45*0.18 -> 305.08475 | P45: 0 | S45: 2000 | AB45: S | AD45: 46204 | AE45: CRE | AF45: 6323094 | AH45: 4212 | AR45: 18 | AS45: SERVICIO CONTABLE
A46: 46174 | C46: 01 | D46: 00E001 | F46: 210 | G46: 6 | H46: 20444327066 | I46: =IF(H46="","",VLOOKUP(H46,[1]ENTIDAD!$B$2:$C$605,2,0)) -> CAMARA DE COMERCIO E INDUSTRIAS SATIPO | N46: =(S46-P46)/1.18 -> 0 | O46: =N46*0.18 -> 0 | P46: 73 | S46: 73 | AB46: S | AD46: 46204 | AE46: CRE | AF46: 6591094 | AH46: 4212 | AR46: 18 | AS46: DONACION POR APOYO Y EFICIENTE ATENCION AL CLIENTE-052026
A47: 46174 | C47: 14 | D47: 00SB01 | F47: 630547811 | G47: 6 | H47: 20467534026 | I47: =IF(H47="","",VLOOKUP(H47,[1]ENTIDAD!$B$2:$C$605,2,0)) -> AMERICA MOVIL PERU S.A.C. | N47: =(S47-P47)/1.18 -> 75.423729 | O47: =N47*0.18 -> 13.576271 | P47: 0 | S47: 89 | AB47: S | AD47: 46192 | AE47: CRE | AF47: 6365095 | AH47: 4212 | AR47: 18 | AS47: SERVICIO DE INTERNET 062026
A48: 46175 | C48: 01 | D48: 00F003 | F48: 3896601 | G48: 6 | H48: 20101973922 | I48: =IF(H48="","",VLOOKUP(H48,[1]ENTIDAD!$B$2:$C$605,2,0)) -> ASOCIACION AUTOMOTRIZ DEL PERU | N48: 0 | O48: =N48*0.18 -> 0 | P48: 0 | R48: 66.8 | S48: 66.8 | AB48: S | AD48: 46205 | AE48: CRE | AF48: 6599095 | AG48: 1413 | AH48: 4212 | AR48: 18 | AS48: POR DERECHO DE EMISION DE PLACA DE RODAJE
A49: 46175 | C49: 01 | D49: 00F003 | F49: 3896600 | G49: 6 | H49: 20101973922 | I49: =IF(H49="","",VLOOKUP(H49,[1]ENTIDAD!$B$2:$C$605,2,0)) -> ASOCIACION AUTOMOTRIZ DEL PERU | N49: 0 | O49: =N49*0.18 -> 0 | P49: 0 | R49: 66.8 | S49: 66.8 | AB49: S | AD49: 46205 | AE49: CRE | AF49: 6599095 | AG49: 1413 | AH49: 4212 | AR49: 18 | AS49: POR DERECHO DE EMISION DE PLACA DE RODAJE
A50: 46175 | C50: 01 | D50: 00F003 | F50: 3896599 | G50: 6 | H50: 20101973922 | I50: =IF(H50="","",VLOOKUP(H50,[1]ENTIDAD!$B$2:$C$605,2,0)) -> ASOCIACION AUTOMOTRIZ DEL PERU | N50: 0 | O50: =N50*0.18 -> 0 | P50: 0 | R50: 66.8 | S50: 66.8 | AB50: S | AD50: 46205 | AE50: CRE | AF50: 6599095 | AG50: 1413 | AH50: 4212 | AR50: 18 | AS50: POR DERECHO DE EMISION DE PLACA DE RODAJE
A51: 46175 | C51: 01 | D51: 00F003 | F51: 3896598 | G51: 6 | H51: 20101973922 | I51: =IF(H51="","",VLOOKUP(H51,[1]ENTIDAD!$B$2:$C$605,2,0)) -> ASOCIACION AUTOMOTRIZ DEL PERU | N51: 0 | O51: =N51*0.18 -> 0 | P51: 0 | R51: 66.8 | S51: 66.8 | AB51: S | AD51: 46205 | AE51: CRE | AF51: 6599095 | AG51: 1413 | AH51: 4212 | AR51: 18 | AS51: POR DERECHO DE EMISION DE PLACA DE RODAJE
A52: 46175 | C52: 01 | D52: 00E001 | F52: 1392 | G52: 6 | H52: 20573301715 | I52: =IF(H52="","",VLOOKUP(H52,[1]ENTIDAD!$B$2:$C$605,2,0)) -> CASCOS FORRADOS PERICO S.A.C | N52: =(S52-P52)/1.18 -> 0 | O52: =N52*0.18 -> 0 | P52: 3600 | S52: 3600 | AB52: S | AD52: 46205 | AE52: CRE | AF52: 6011020 | AH52: 4212 | AR52: 18 | AS52: CASCOS FORRADOS PARA MOTOS, ADICIONALES
A53: 46175 | C53: 01 | D53: 00E001 | F53: 241 | G53: 6 | H53: 10447422951 | I53: =IF(H53="","",VLOOKUP(H53,[1]ENTIDAD!$B$2:$C$605,2,0)) -> ZEGARRA AZAÑERO JORGE KEY | N53: =(S53-P53)/1.18 -> 0 | O53: =N53*0.18 -> 0 | P53: 450 | S53: 450 | AB53: S | AD53: 46175 | AE53: CRE | AF53: 6329094 | AH53: 4212 | AR53: 18 | AS53: SOPORTE TECNICO 052026
A54: 46175 | C54: 01 | D54: 00FC05 | F54: 5151278 | G54: 6 | H54: 20100130204 | I54: =IF(H54="","",VLOOKUP(H54,[1]ENTIDAD!$B$2:$C$605,2,0)) -> BANCO BBVA PERU | N54: =(S54-P54)/1.18 -> 0 | O54: =N54*0.18 -> 0 | P54: 40 | S54: 40 | AB54: S | AD54: 46205 | AE54: CRE | AF54: 6391094 | AH54: 4212 | AR54: 18 | AS54: POR LA COMISION BANCARIA
A55: 46176 | C55: 01 | D55: 00F001 | F55: 12762 | G55: 6 | H55: 10209907327 | I55: =IF(H55="","",VLOOKUP(H55,[1]ENTIDAD!$B$2:$C$605,2,0)) -> TORPOCO,MAYTA,HECTOR,ALFONSO | N55: =(S55-P55)/1.18 -> 0 | O55: =N55*0.18 -> 0 | P55: 10 | S55: 10 | AB55: S | AD55: 46176 | AE55: CON | AF55: 656009501 | AH55: 4212 | AR55: 18 | AS55: COMBUSTIBLE
A56: 46176 | C56: 01 | D56: 00E001 | F56: 125 | G56: 6 | H56: 10410993487 | I56: =IF(H56="","",VLOOKUP(H56,[1]ENTIDAD!$B$2:$C$605,2,0)) -> VICENTE MANDUJANO WILMER ARTURO | N56: =(S56-P56)/1.18 -> 508.47458 | O56: =N56*0.18 -> 91.525424 | P56: 0 | S56: 600 | AB56: S | AD56: 46206 | AE56: CRED | AF56: 6530094 | AH56: 4212 | AR56: 18 | AS56: RENOVACION DE HOTING Y DOMINIO
A57: 46177 | C57: 01 | D57: 00FF08 | F57: 964 | G57: 6 | H57: 20611526572 | I57: =IF(H57="","",VLOOKUP(H57,[1]ENTIDAD!$B$2:$C$605,2,0)) -> GRUPO SUKKIE E.I.R.L. | N57: =(S57-P57)/1.18 -> 0 | O57: =N57*0.18 -> 0 | P57: 66.8 | S57: 66.8 | AB57: S | AD57: 46177 | AE57: CON | AF57: 656009502 | AH57: 4212 | AR57: 18 | AS57: ARTICULOS DE LIMPIEZA
A58: 46177 | C58: 01 | D58: 00FE01 | F58: 2912789 | G58: 6 | H58: 20100047218 | I58: =IF(H58="","",VLOOKUP(H58,[1]ENTIDAD!$B$2:$C$605,2,0)) -> BANCO DE CREDITO DEL PERU | N58: =(S58-P58)/1.18 -> 1.2043097e-14 | O58: =N58*0.18 -> 2.1677575e-15 | P58: 119.77 | S58: =W58*AC58 -> 119.77 | W58: 3.422 | AB58: D | AC58: 35 | AD58: 46207 | AE58: CRE | AF58: 6391094 | AH58: 4212 | AR58: 18 | AS58: COMISION TELECREDITO
A59: 46177 | C59: 01 | D59: 00F341 | F59: 10942 | G59: 6 | H59: 20512528458 | I59: =IF(H59="","",VLOOKUP(H59,[1]ENTIDAD!$B$2:$C$605,2,0)) -> SHALOM EMPRESARIAL S.A.C. | N59: =(S59-P59)/1.18 -> 92.372881 | O59: =N59*0.18 -> 16.627119 | P59: 0 | S59: 109 | AB59: S | AD59: 46177 | AE59: CON | AF59: 6311194 | AH59: 4212 | AR59: 18 | AS59: UN BULTO SERVICIO DE REPARTO
A60: 46177 | C60: 01 | D60: 00F002 | F60: 154 | G60: 6 | H60: 20600454065 | I60: =IF(H60="","",VLOOKUP(H60,[1]ENTIDAD!$B$2:$C$605,2,0)) -> REPUESTOS Y SERVICIOS ARAUCO E.I.R.L. | N60: =(S60-P60)/1.18 -> 0 | O60: =N60*0.18 -> 0 | P60: 2575 | S60: 2575 | AB60: S | AD60: 46207 | AE60: CRE | AF60: 6343095 | AH60: 4212 | AR60: 18 | AS60: MANTENIMIENTO DE MOTOS VENDIDAS - GARANTIA
A61: 46177 | C61: 01 | D61: 00F002 | F61: 215 | G61: 6 | H61: 20486549328 | I61: =IF(H61="","",VLOOKUP(H61,[1]ENTIDAD!$B$2:$C$605,2,0)) -> SANTISIMA TRINIDAD E.I.R.L. | N61: =(S61-P61)/1.18 -> 0 | O61: =N61*0.18 -> 0 | P61: 30 | S61: 30 | AB61: S | AD61: 46177 | AE61: CON | AF61: 656009503 | AH61: 4212 | AR61: 18 | AS61: LIBRO DE RECLAMACIONES
A62: 46178 | C62: 01 | D62: 00FI01 | F62: 19733236 | G62: 6 | H62: 20100047218 | I62: =IF(H62="","",VLOOKUP(H62,[1]ENTIDAD!$B$2:$C$605,2,0)) -> BANCO DE CREDITO DEL PERU | N62: =(S62-P62)/1.18 -> 0.0033898305 | O62: =N62*0.18 -> 0.00061016949 | P62: 61.52 | S62: =W62*AC62 -> 61.524 | W62: 3.418 | AB62: D | AC62: 18 | AD62: 46208 | AE62: CRE | AF62: 6391094 | AH62: 4212 | AR62: 18 | AS62: PAGO PORTES , CARGO COMISION
A63: 46178 | C63: 01 | D63: 00FI01 | F63: 19733186 | G63: 6 | H63: 20100047218 | I63: =IF(H63="","",VLOOKUP(H63,[1]ENTIDAD!$B$2:$C$605,2,0)) -> BANCO DE CREDITO DEL PERU | N63: =(S63-P63)/1.18 -> 0 | O63: =N63*0.18 -> 0 | P63: 760.5 | S63: 760.5 | AB63: S | AD63: 46208 | AE63: CRE | AF63: 6391094 | AH63: 4212 | AR63: 18 | AS63: PAGO PORTES ,EXCESO ON LINE,COMISION
A64: 46178 | C64: 01 | D64: 00FV16 | F64: 1379493 | G64: 6 | H64: 20100047218 | I64: =IF(H64="","",VLOOKUP(H64,[1]ENTIDAD!$B$2:$C$605,2,0)) -> BANCO DE CREDITO DEL PERU | N64: =(S64-P64)/1.18 -> 0 | O64: =N64*0.18 -> 0 | P64: 215 | S64: 215 | AB64: S | AD64: 46208 | AE64: CRE | AF64: 6391094 | AH64: 4212 | AR64: 18 | AS64: PAGO MANTENIMIENTO,OPER.EXC,PORTE X ESTADO
A65: 46178 | C65: 01 | D65: 00FF08 | F65: 969 | G65: 6 | H65: 20611526572 | I65: =IF(H65="","",VLOOKUP(H65,[1]ENTIDAD!$B$2:$C$605,2,0)) -> GRUPO SUKKIE E.I.R.L. | N65: =(S65-P65)/1.18 -> 0 | O65: =N65*0.18 -> 0 | P65: 32 | S65: 32 | AB65: S | AD65: 46178 | AE65: CON | AF65: 656009503 | AH65: 4212 | AR65: 18 | AS65: 02 FILF, USO ADMINISTRATIVO
A66: 46178 | C66: 01 | D66: 00F001 | F66: 820 | G66: 6 | H66: 10733910921 | I66: =IF(H66="","",VLOOKUP(H66,[1]ENTIDAD!$B$2:$C$605,2,0)) -> MADUEÑO HUAMAN LILI CLISSELY | N66: =(S66-P66)/1.18 -> 0 | O66: =N66*0.18 -> 0 | P66: 30 | S66: 30 | AB66: S | AD66: 46208 | AE66: CRE | AF66: 6560095 | AH66: 4212 | AR66: 18 | AS66: CINTA AISLANTE GRANDE 3M
A67: 46178 | C67: 01 | D67: 00F424 | F67: 754 | G67: 6 | H67: 20132757187 | I67: =IF(H67="","",VLOOKUP(H67,[1]ENTIDAD!$B$2:$C$605,2,0)) -> EMPRESA DE TRANSPORTES EXPRESO LOBATO S.A.C. | N67: =(S67-P67)/1.18 -> 42.372881 | O67: =N67*0.18 -> 7.6271186 | P67: 0 | S67: 50 | AB67: S | AD67: 46178 | AE67: CON | AF67: 6311194 | AH67: 4212 | AR67: 18 | AS67: ENVIO 03 CAJAS CON DOCUMENTOS
A68: 46179 | C68: 01 | D68: 00F005 | F68: 18676 | G68: 6 | H68: 20493508645 | I68: =IF(H68="","",VLOOKUP(H68,ENTIDAD!$B$2:$C$613,2,0)) -> HONDA SELVA DEL PERU S.A. | N68: =(S68-P68)/1.18 -> 0.001559322 | O68: =N68*0.18 -> 0.00028067797 | P68: 61439.92 | S68: =W68*AC68 -> 61439.922 | W68: 3.443 | AB68: D | AC68: 17844.88 | AD68: 46209 | AE68: CRE | AF68: 6011021 | AH68: 4212 | AR68: 18 | AS68: EXISTENCIAS POR RECIBIR
A69: 46179 | C69: 01 | D69: 00F005 | F69: 18677 | G69: 6 | H69: 20493508645 | I69: =IF(H69="","",VLOOKUP(H69,[1]ENTIDAD!$B$2:$C$605,2,0)) -> HONDA SELVA DEL PERU S.A. | N69: =(S69-P69)/1.18 -> 0.0020932203 | O69: =N69*0.18 -> 0.00037677966 | P69: 20479.96 | S69: =W69*AC69 -> 20479.962 | W69: 3.443 | AB69: D | AC69: 5948.29 | AD69: 46209 | AE69: CRE | AF69: 6011021 | AH69: 4212 | AR69: 18 | AS69: EXISTENCIAS POR RECIBIR
A70: 46179 | C70: 01 | D70: 00F006 | F70: 2090 | G70: 6 | H70: 20606549386 | I70: =IF(H70="","",VLOOKUP(H70,[1]ENTIDAD!$B$2:$C$605,2,0)) -> GREAV EMPRESA INDIVIDUAL DE RESPONSABILIDAD LIMITADA | N70: =(S70-P70)/1.18 -> 0 | O70: =N70*0.18 -> 0 | P70: 10 | S70: 10 | AB70: S | AD70: 46209 | AE70: CON | AF70: 6560095 | AH70: 4212 | AR70: 18 | AS70: DESARMADOR CONFORT
A71: 46181 | C71: 01 | D71: 00F001 | F71: 12781 | G71: 6 | H71: 10209907327 | I71: =IF(H71="","",VLOOKUP(H71,[1]ENTIDAD!$B$2:$C$605,2,0)) -> TORPOCO,MAYTA,HECTOR,ALFONSO | N71: 0 | O71: =N71*0.18 -> 0 | P71: 20 | S71: 20 | AB71: S | AD71: 46181 | AE71: CON | AF71: 656009501 | AH71: 4212 | AR71: 18 | AS71: COMBUSTIBLE PLACA 3769-XW
A72: 46181 | C72: 01 | D72: 00F003 | F72: 60753 | G72: 6 | H72: 20493508645 | I72: =IF(H72="","",VLOOKUP(H72,[1]ENTIDAD!$B$2:$C$605,2,0)) -> HONDA SELVA DEL PERU S.A. | N72: 0 | O72: =N72*0.18 -> 0 | P72: 118.78 | S72: =W72*AC72 -> 118.7835 | W72: 3.443 | AB72: D | AC72: 34.5 | AD72: 46211 | AE72: CRE | AF72: 6011021 | AH72: 4212 | AR72: 18 | AS72: EXISTENCIAS POR RECIBIR
A73: 46181 | C73: 01 | D73: 00E001 | F73: 1807 | G73: 6 | H73: 20611910887 | I73: =IF(H73="","",VLOOKUP(H73,[1]ENTIDAD!$B$2:$C$605,2,0)) -> CORPORACION UNIVERSAL M&F SOCIEDAD ANONIMA CERRADA | N73: =(S73-P73)/1.18 -> 0 | O73: =N73*0.18 -> 0 | P73: 200 | S73: 200 | AB73: S | AD73: 46181 | AE73: CRE | AF73: 6560095 | AH73: 4212 | AR73: 18 | AS73: IMPRESIÓN DE FORMATOS
